Workbook

Sheet Unified_Spec
A1: AUTOMETRIC — UNIFIED BRAND × CAMPAIGN MATCH SPEC
A2: One model that keeps Brand, Campaign, Content Style, and Creator/Brand Personality explicit. The original Brand Match engine remains intact; Unified Match adds Campaign Fit as a contextual layer.
A4: Layer | B4: What it answers | C4: Included signals | D4: Where
A5: BRAND | B5: Is this creator a fit for the brand itself? | C5: Industry, category, keywords, audience, content/category, brand personality, performance, safety | D5: Matching_Engine
A6: CAMPAIGN | B6: Is this creator suitable for this specific activation? | C6: Campaign objective, audience, content style, creator personality, communication style, platform | D6: Campaign_Profile + Campaign_Match
A7: CONTENT STYLE | B7: How should the creator make the content? | C7: Content Style Match + campaign Content Style | D7: Matching_Engine W + Campaign_Profile
A8: PERSONALITY | B8: Does creator personality fit brand/campaign personality? | C8: Brand Personality Fit, creator personality, tone, values, communication style | D8: Matching_Engine Y:AB + Campaign_Profile
A9: UNIFIED SCORE | B9: What is the final contextual fit for this campaign? | C9: 70% Brand Match + 30% Campaign Fit | D9: Unified_Match
A11: DEFAULT WEIGHTS | B11: Value | C11: Notes
A12: Base Brand Match | B12: 70% | C12: Preserves existing Brand Match score and its six component groups.
A13: Campaign Fit | B13: 30% | C13: Campaign-specific context; editable in Campaign_Match formula.
A14: Campaign Fit internals | B14: 30% Audience / 30% Style / 25% Personality / 15% Communication Style | C14: Objective remains a campaign descriptor and can later become a dedicated signal if backend data supports it.
A16: IMPORTANT | B16: Style and personality are NOT merged into generic category labels. Brand and campaign remain separate contexts, so the same creator can score differently across brands and campaigns.
A17: DATA NOTE
A18: VALIDATION TARGET

Sheet README
A1: AUTOMETRIC — KOL DISCOVERY BRAND MATCH ENGINE
A2: Specification and calculation workbook. Twelve sheets: two of inputs, one engine, seven views, one lookup sheet and this page. Generated by scripts/build-brand-match-workbook.mjs and verified by scripts/verify-brand-match-workbook.mjs.
A4: 1. PURPOSE
B5: This workbook is the source of truth for the Autometric KOL Discovery Brand Match calculation. It is not a mock-up: every score on every sheet is an Excel formula over the values in Brand_Profile and KOL_Database, weighted by the constants on Lookup_Lists. Change an input and the workbook re-answers. Hand it to a backend developer and the formulas are the specification — there is no second document that says what the code should do.
B6: It exists because the product needs a Brand Match today and the KOL database cannot supply one: feature.brand_fit_analysis holds 0 rows, which is why four of the eight Smart Preset chips in the running prototype are disabled. The logic has to be agreed and written down before the pipeline is built, not after.
A7: 2. BRAND_PROFILE — the brand half of the inputs
B8: Four sections, matching the Brand Profile & Matching UI: A. Company Profile, B. Target Audience, C. Brand Identification, D. Ideal Creator Profile. A fifth block, E. Matching Configuration, holds the switches that decide which rules act as hard filters.
B9: Columns D, E and F are the three brands. Column G is whichever brand cell B4 names, and that is the column the active-brand views (Match_Explanation, Discovery_Ranking) read. Two calculated blocks sit under the fields: a token helper that splits the comma-separated list fields into five addressable slots, and the audience sub-weights, which move weight onto whichever dimension Audience Demographics Priority names.
A10: 3. KOL_DATABASE — the creator half of the inputs
B11: Thirty creators on Instagram and TikTok, in six blocks: identity, performance, audience, content, commercial, safety — plus the exclusion state and the freshness columns Discovery needs. Tier, CPV, CPE, CPM, Estimated Reach, Estimated ROI, View-to-Follower Ratio, Cost Efficiency, Data Completeness and Data Status are calculated from the columns beside them.
B12: Several creators are missing a field on purpose — a blank Median Views, a blank rate card, a blank audience city. The real roster is full of holes, the Confidence column exists to report them, and every formula here is written to survive one without printing #DIV/0!.
A13: 4. THE SIX COMPONENTS
A14: Brand & Business Relevance | B14: Brand Industry, Product / Service Category, Main Business Keywords, Brand Keywords and Brand Niche against the creator Category, Sub Category, Content Topics and Audience Interests. Industry Match 40%, Category Match 30%, Keyword Match 30% — the last being the two keyword lists scored separately and averaged.
A15: Target Audience Relevance | B15: Age 25%, Gender 15%, Location 30%, Interest 30% — before Audience Demographics Priority moves 12 points onto one of them and takes a third of that off each of the others.
A16: Content & Category Relevance | B16: Preferred Category 30%, Preferred Sub Category 20%, Preferred Content Topics 30%, Preferred Content Style 20%.
A17: Brand Personality Fit | B17: Personality 35%, Tone against Content Style 25%, Values overlap 25%, Communication Style 15%. Related matches count: Innovative is answered by a Tech-savvy or Creative creator, not only by one who calls themselves Innovative.
A18: Performance Quality | B18: Engagement Rate 35%, Audience Quality 20%, Consistency 20%, Community 10%, Average Views 10%, Recent Growth 5%, each normalised to 0–100 against a calibration target on Lookup_Lists.
A19: Brand Safety | B19: Brand Safety Score 80%, head-room from Competitor Saturation 20%, multiplied by the Risk Flag discount (High 0.6, Medium 0.85, Low 0.95). Saturation lowers the score; it never excludes on its own.
A20: 5. WEIGHTING — the master formula
A21: FINAL MATCH = 20% Brand & Business + 30% Target Audience + 20% Content & Category + 10% Brand Personality + 10% Performance + 10% Brand Safety
B23: The six weights live in the COMPONENT WEIGHTS block on Lookup_Lists and nowhere else. The engine divides by their sum rather than by a literal 100, so a workbook whose weights have been edited still produces a 0–100 score; the CHECK_WEIGHT_TOTAL cell beside them says out loud whether they still total 100.
A24: 6. FORMULA LOGIC — how a comparison becomes a number
A25: Category-style comparisons | B25: A matrix lookup on Lookup_Lists, on the 100 / 80 / 60 / 40 / 20 ladder: exact, strongly related, partially related, weakly related, unrelated. Five matrices — Industry × Category, Category × Category, Brand Personality × Creator Personality, Brand Tone × Content Style, Communication Style × Content Style, Content Style × Content Style. Every cell is editable, which is what makes a disputed score a conversation about one number rather than about a model.
A26: List comparisons | B26: Overlap counting. The brand list is split into five slots by the token helper; each slot is looked for in the creator text with SEARCH; the score is matches ÷ slots filled × 100. A brand that names three keywords is judged out of three.
A27: Numeric comparisons | B27: Normalisation against a target on Lookup_Lists: MIN(100, value ÷ target × 100). Engagement Rate scores 100 at 6%; views per follower at 0.5; 30-day growth at 8%, and 0 at −2%.
A28: Missing data | B28: A blank input scores the neutral 50 where the brand left a preference blank, and 0 where the creator is missing a measurement — those are different situations and the formulas keep them apart. Nothing ever divides by an unguarded cell.
A29: Two inputs that carry no weight | B29: Company Description is free text for the brief. Brand Positioning is carried and printed in the Personality Match Reason, but it is deliberately not weighted: the honest thing to weigh a Premium or Luxury positioning against is production quality, and there is no measured production-quality signal on the roster to weigh it against. Inventing one would be the same mistake as the four Smart Preset chips that used to rank by a hash of the creator id. Give it a weight the day a real signal exists.
A30: 7. HARD FILTERS — remove the creator
B31: Platform, Minimum and Maximum Followers, Minimum Engagement Rate, Tier, Minimum Audience Quality, Minimum Brand Safety, Audience Country and Category (both switchable), Max Competitor Saturation, the four exclusion toggles, and Minimum Brand Match. The engine computes the reason first and the verdict from it, so an excluded creator always carries the sentence that explains why. See Filter_Logic.
A32: 8. SOFT MATCHING — reorder the list
B33: Brand Match, Audience Match, Content Relevance, Personality Fit, Performance, Opportunity, Estimated ROI and Competitor Saturation. A low soft score never removes a creator. Competitor Saturation in particular is a warning, not a rejection: it can only exclude through the explicit Max Competitor Saturation setting.
A34: 9. DISCOVERY RANKING
B35: Default order is Brand Match, then Audience Match, then Content Relevance, then Performance, then Brand Safety, encoded as one Default Sort Key so the tie-break order is inspectable. Thirty presets are defined on Lookup_Lists; the picker on Discovery_Ranking reads the metric column each one names. The "Available today" column tells you which of them the KOL database can actually answer — the prototype ships four of its eight chips disabled for exactly this reason.
A36: 10. MATCH EXPLANATION
B37: Generated, not written. The three strengths are the three highest components and the three considerations the three lowest, read with LARGE and SMALL over the same cells the score came from, so an explanation cannot drift away from the number it explains. Each component also carries its own reason line naming its sub-scores.
A38: 11. SAMPLE BRANDS AND SAMPLE OUTPUT
B39: Three briefs — Technology / SaaS, Beauty & Skincare, Food & Beverage — run against one roster of thirty. Sample_Output puts the three scores for each creator side by side and reports the spread. If the engine were ranking creators globally rather than matching brand to creator, that spread would be zero on every row; the verdict cell says whether it is.
A40: 12. TAXONOMY — the tree everything classifies against
B41: One sheet, because the whole point is that the four things are one object: a creator sub category, a brand niche, a raw kol_categories row and a matching keyword are four views of a single tree. Lookup_Lists derives its Category, Sub Category, Industry and Niche dropdowns from it, so no list in this workbook can drift from another.
A42: Three axes | B42: A label answers one question — what the creator makes, who watches, or how it is shot. public.kol_categories mixes all three: "Moms" is an audience and "Gen Z" is an age band, both sitting in a content column. Only the content axis may feed the Category and Sub Category ladders; the audience axis already has its own 30% of the score.
A43: The crosswalk | B43: Brand Niche is collected on Brand_Profile and read by no formula in the engine. Section E is what would give it weight: it names the sub categories each niche is actually asking for, over a default that comes from matrix 5 rather than from nowhere. The derived value is printed beside every override so an override reads as an override.
A44: What it is for | B44: Category covers 54,1% of the roster, Sub Category has no column at all, and Content Topic has none of its 0 rows filled. Section F is the alias table the backend plan is waiting on, and section G is how the 3.547 creators with no category get one — including the rule that a modelled category may rank but must never act as a hard filter.
A45: 13. FOR THE BACKEND — translating this into code
A46: Shape | B46: One pure function: score(brand, creator) → { components, subScores, final, level, confidence, reasons, exclusion }. No I/O, no database access, deterministic. The Field Key column on Brand_Profile is the payload shape; the KOL_Database headers are the creator shape.
A47: Where the constants live | B47: Load the Lookup_Lists blocks — weights, matrices, calibration, bands — from configuration, not from constants in the source. They are meant to be tuned by whoever owns the matching quality, and a redeploy is the wrong unit of change.
A48: Order of operations | B48: Compute all six components, then the Final Match Score, then evaluate the hard filters (Minimum Brand Match needs the score), then rank. Never fold a hard filter into the SQL when it rests on a computed value — the roster pages server-side, and filtering the page you already fetched gives a result count that means nothing.
A49: Provenance | B49: Carry a per-field basis flag the way @/lib/discover/creatorMatch does with SignalBasis. A score built from modelled inputs is useful for ranking and must never be presented as a measurement, and it must never be used as a hard filter.
A50: What to build first | B50: The columns the KOL database cannot answer today are listed with their coverage on Discovery_Filters. The short list: populate feature.brand_fit_analysis; fill audience_demographics_daily with audience_type='age'; widen feature.{ig,tt}_audience_analysis past 23 creators; fill creator_city; populate l1_silver.unified_rate_card. Until then, a filter that rests on one of those must ship disabled with its reason shown, not silently returning nothing.

Sheet Brand_Profile
A1: BRAND PROFILE · Company Profile · Target Audience · Brand Identification · Ideal Creator Profile
A2: The inputs. Columns D–F are the three brands, each cell typed by hand or picked from a dropdown; column G is whichever brand cell B4 names, and that is the column the engine reads for every active-brand view. Nothing on this sheet is calculated from a creator — it is what the brand says about itself before it has seen the roster.
A4: Active Brand → | B4: BRAND-A | G4: active column → | H4: =MATCH($B$4,$D$6:$F$6,0) -> 1
A6: Section | B6: Field | C6: Field Key | D6: BRAND-A | E6: BRAND-B | F6: BRAND-C | G6: Active Value | H6: Input type / allowed values
A7: A. COMPANY PROFILE
A8: COMPANY PROFILE | B8: Brand ID | C8: brand_id | D8: BRAND-A | E8: BRAND-B | F8: BRAND-C | G8: =INDEX($D8:$F8,1,$H$4) -> BRAND-A | H8: Free text
A9: COMPANY PROFILE | B9: Brand Name | C9: brand_name | D9: Nusatech Cloud | E9: Lumaya Skin | F9: Rasa Nusantara | G9: =INDEX($D9:$F9,1,$H$4) -> Nusatech Cloud | H9: Free text
A10: COMPANY PROFILE | B10: Industry | C10: industry | D10: Technology / SaaS | E10: Beauty & Skincare | F10: Food & Beverage | G10: =INDEX($D10:$F10,1,$H$4) -> Technology / SaaS | H10: Dropdown — Lookup_Lists.Industry
A11: COMPANY PROFILE | B11: Company Description | C11: company_description | D11: Workflow automation and team collaboration for Indonesian SMEs. | E11: Dermatologist-tested skincare for humid-climate skin barriers. | F11: Ready-to-drink archipelago flavours for everyday family tables. | G11: =INDEX($D11:$F11,1,$H$4) -> Workflow automation and team collaboration for Indonesian SMEs. | H11: Free text
A12: COMPANY PROFILE | B12: Product / Service Category | C12: product_category | D12: Software & SaaS | E12: Skincare | F12: Coffee & Beverage | G12: =INDEX($D12:$F12,1,$H$4) -> Software & SaaS | H12: Dropdown — Lookup_Lists.SubCategory
A13: COMPANY PROFILE | B13: Main Business Keywords | C13: business_keywords | D13: Technology, Productivity, Business, Education, Finance | E13: Skincare, Beauty, Makeup, Health, Shopping | F13: Food, Cooking, Coffee, Shopping, Entertainment | G13: =INDEX($D13:$F13,1,$H$4) -> Technology, Productivity, Business, Education, Finance | H13: Up to 5 items, comma-separated
A14: COMPANY PROFILE | B14: Brand Niche | C14: brand_niche | D14: B2B SaaS | E14: Derma Skincare | F14: Ready-to-Drink | G14: =INDEX($D14:$F14,1,$H$4) -> B2B SaaS | H14: Dropdown — Lookup_Lists.Niche
A15: B. TARGET AUDIENCE
A16: TARGET AUDIENCE | B16: Primary Age Range | C16: primary_age_range | D16: 25-34 | E16: 18-24 | F16: 25-34 | G16: =INDEX($D16:$F16,1,$H$4) -> 25-34 | H16: Dropdown — Lookup_Lists.AgeBand
A17: TARGET AUDIENCE | B17: Secondary Age Range | C17: secondary_age_range | D17: 18-24 | E17: 25-34 | F17: 35-44 | G17: =INDEX($D17:$F17,1,$H$4) -> 18-24 | H17: Dropdown — Lookup_Lists.AgeBand
A18: TARGET AUDIENCE | B18: Gender Majority | C18: gender_majority | D18: Any | E18: Female | F18: Balanced | G18: =INDEX($D18:$F18,1,$H$4) -> Any | H18: Dropdown — Lookup_Lists.GenderMajority
A19: TARGET AUDIENCE | B19: Target Country | C19: target_country | D19: Indonesia | E19: Indonesia | F19: Indonesia | G19: =INDEX($D19:$F19,1,$H$4) -> Indonesia | H19: Dropdown — Lookup_Lists.Country
A20: TARGET AUDIENCE | B20: Target Region / Province | C20: target_region | D20: DKI Jakarta | E20: Nasional | F20: Nasional | G20: =INDEX($D20:$F20,1,$H$4) -> DKI Jakarta | H20: Dropdown — Lookup_Lists.Region
A21: TARGET AUDIENCE | B21: Target City | C21: target_city | D21: Jakarta | E21: Jakarta | F21: Nasional | G21: =INDEX($D21:$F21,1,$H$4) -> Jakarta | H21: Dropdown — Lookup_Lists.City
A22: TARGET AUDIENCE | B22: Audience Interests | C22: audience_interests | D22: Technology, Business, Productivity, Education, Finance | E22: Skincare, Beauty, Makeup, Fashion, Shopping | F22: Food, Cooking, Coffee, Travel, Entertainment | G22: =INDEX($D22:$F22,1,$H$4) -> Technology, Business, Productivity, Education, Finance | H22: Up to 5 items, comma-separated
A23: TARGET AUDIENCE | B23: Audience Demographics Priority | C23: audience_priority | D23: Interest | E23: Gender | F23: Age | G23: =INDEX($D23:$F23,1,$H$4) -> Interest | H23: Dropdown — Lookup_Lists.AudiencePriority
A24: C. BRAND IDENTIFICATION
A25: BRAND IDENTIFICATION | B25: Brand Personality | C25: brand_personality | D25: Innovative | E25: Premium | F25: Friendly | G25: =INDEX($D25:$F25,1,$H$4) -> Innovative | H25: Dropdown — Lookup_Lists.BrandPersonality
A26: BRAND IDENTIFICATION | B26: Brand Values | C26: brand_values | D26: Innovation, Trust, Transparency, Quality, Empowerment | E26: Quality, Authenticity, Trust, Craftsmanship, Health | F26: Fun, Community, Affordability, Authenticity, Family | G26: =INDEX($D26:$F26,1,$H$4) -> Innovation, Trust, Transparency, Quality, Empowerment | H26: Up to 5 items, comma-separated
A27: BRAND IDENTIFICATION | B27: Brand Tone | C27: brand_tone | D27: Informative | E27: Aspirational | F27: Warm | G27: =INDEX($D27:$F27,1,$H$4) -> Informative | H27: Dropdown — Lookup_Lists.BrandTone
A28: BRAND IDENTIFICATION | B28: Brand Positioning | C28: brand_positioning | D28: Mid-market | E28: Premium | F28: Mass | G28: =INDEX($D28:$F28,1,$H$4) -> Mid-market | H28: Dropdown — Lookup_Lists.Positioning
A29: BRAND IDENTIFICATION | B29: Brand Keywords | C29: brand_keywords | D29: Technology, Productivity, Business, Education, Finance | E29: Skincare, Beauty, Health, Makeup, Shopping | F29: Food, Cooking, Coffee, Entertainment, Shopping | G29: =INDEX($D29:$F29,1,$H$4) -> Technology, Productivity, Business, Education, Finance | H29: Up to 5 items, comma-separated
A30: BRAND IDENTIFICATION | B30: Communication Style | C30: communication_style | D30: Educational | E30: Visual-first | F30: Storytelling | G30: =INDEX($D30:$F30,1,$H$4) -> Educational | H30: Dropdown — Lookup_Lists.CommStyle
A31: D. IDEAL CREATOR PROFILE
A32: IDEAL CREATOR PROFILE | B32: Preferred Platform | C32: preferred_platform | D32: Instagram, TikTok | E32: Instagram, TikTok | F32: Instagram, TikTok | G32: =INDEX($D32:$F32,1,$H$4) -> Instagram, TikTok | H32: One or more of the Platform list, comma-separated
A33: IDEAL CREATOR PROFILE | B33: Preferred Category | C33: preferred_category | D33: Tech | E33: Beauty | F33: Food | G33: =INDEX($D33:$F33,1,$H$4) -> Tech | H33: Dropdown — Lookup_Lists.Category
A34: IDEAL CREATOR PROFILE | B34: Preferred Sub Category | C34: preferred_subcategory | D34: Software & SaaS | E34: Skincare | F34: Culinary Review | G34: =INDEX($D34:$F34,1,$H$4) -> Software & SaaS | H34: Dropdown — Lookup_Lists.SubCategory
A35: IDEAL CREATOR PROFILE | B35: Preferred Tier | C35: preferred_tier | D35: Micro, Mid-tier, Macro | E35: Micro, Mid-tier | F35: Nano, Micro, Mid-tier | G35: =INDEX($D35:$F35,1,$H$4) -> Micro, Mid-tier, Macro | H35: One or more of the Tier list, comma-separated
A36: IDEAL CREATOR PROFILE | B36: Preferred Follower Range — Min | C36: preferred_followers_min | D36: 10000 | E36: 10000 | F36: 5000 | G36: =INDEX($D36:$F36,1,$H$4) -> 10000 | H36: Whole number
A37: IDEAL CREATOR PROFILE | B37: Preferred Follower Range — Max | C37: preferred_followers_max | D37: 1000000 | E37: 500000 | F37: 400000 | G37: =INDEX($D37:$F37,1,$H$4) -> 1000000 | H37: Whole number
A38: IDEAL CREATOR PROFILE | B38: Minimum Engagement Rate (%) | C38: min_engagement_rate | D38: 2.5 | E38: 3 | F38: 3.5 | G38: =INDEX($D38:$F38,1,$H$4) -> 2.5 | H38: Percent, e.g. 3.5 means 3,5%
A39: IDEAL CREATOR PROFILE | B39: Preferred Content Style | C39: preferred_content_style | D39: Educational | E39: Review | F39: Storytelling | G39: =INDEX($D39:$F39,1,$H$4) -> Educational | H39: Dropdown — Lookup_Lists.ContentStyle
A40: IDEAL CREATOR PROFILE | B40: Preferred Content Topics | C40: preferred_content_topics | D40: Technology, Business, Education, Productivity, Finance | E40: Skincare, Beauty, Makeup, Health, Shopping | F40: Food, Cooking, Coffee, Entertainment, Travel | G40: =INDEX($D40:$F40,1,$H$4) -> Technology, Business, Education, Productivity, Finance | H40: Up to 5 items, comma-separated
A41: IDEAL CREATOR PROFILE | B41: Preferred Creator Personality | C41: preferred_creator_personality | D41: Educational | E41: Reviewer | F41: Relatable | G41: =INDEX($D41:$F41,1,$H$4) -> Educational | H41: Dropdown — Lookup_Lists.CreatorPersonality
A42: IDEAL CREATOR PROFILE | B42: Preferred Creator Values | C42: preferred_creator_values | D42: Innovation, Trust, Quality, Transparency, Empowerment | E42: Authenticity, Quality, Trust, Health, Craftsmanship | F42: Fun, Community, Authenticity, Family, Affordability | G42: =INDEX($D42:$F42,1,$H$4) -> Innovation, Trust, Quality, Transparency, Empowerment | H42: Up to 5 items, comma-separated
A43: IDEAL CREATOR PROFILE | B43: Minimum Audience Quality | C43: min_audience_quality | D43: 65 | E43: 70 | F43: 60 | G43: =INDEX($D43:$F43,1,$H$4) -> 65 | H43: 0–100 (0 turns the rule off)
A44: IDEAL CREATOR PROFILE | B44: Minimum Brand Safety | C44: min_brand_safety | D44: 70 | E44: 75 | F44: 65 | G44: =INDEX($D44:$F44,1,$H$4) -> 70 | H44: 0–100 (0 turns the rule off)
A45: E. MATCHING CONFIGURATION
A46: MATCHING CONFIGURATION | B46: Category is a Hard Filter | C46: category_hard_filter | D46: No | E46: No | F46: No | G46: =INDEX($D46:$F46,1,$H$4) -> No | H46: Dropdown — Lookup_Lists.YesNo
A47: MATCHING CONFIGURATION | B47: Audience Country is a Hard Filter | C47: country_hard_filter | D47: Yes | E47: Yes | F47: Yes | G47: =INDEX($D47:$F47,1,$H$4) -> Yes | H47: Dropdown — Lookup_Lists.YesNo
A48: MATCHING CONFIGURATION | B48: Max Competitor Saturation (0 = off) | C48: max_competitor_saturation | D48: 0 | E48: 0 | F48: 0 | G48: =INDEX($D48:$F48,1,$H$4) -> 0 | H48: 0–100 (0 turns the rule off)
A49: MATCHING CONFIGURATION | B49: Minimum Brand Match (0 = off) | C49: min_brand_match | D49: 0 | E49: 0 | F49: 0 | G49: =INDEX($D49:$F49,1,$H$4) -> 0 | H49: 0–100 (0 turns the rule off)
A50: MATCHING CONFIGURATION | B50: Exclude Already Selected | C50: exclude_already_selected | D50: No | E50: No | F50: No | G50: =INDEX($D50:$F50,1,$H$4) -> No | H50: Dropdown — Lookup_Lists.YesNo
A51: MATCHING CONFIGURATION | B51: Exclude Already in Cart | C51: exclude_in_cart | D51: No | E51: No | F51: No | G51: =INDEX($D51:$F51,1,$H$4) -> No | H51: Dropdown — Lookup_Lists.YesNo
A52: MATCHING CONFIGURATION | B52: Exclude Existing Partner | C52: exclude_existing_partner | D52: No | E52: Yes | F52: No | G52: =INDEX($D52:$F52,1,$H$4) -> No | H52: Dropdown — Lookup_Lists.YesNo
A53: MATCHING CONFIGURATION | B53: Exclude Excluded Creator | C53: exclude_excluded_creator | D53: Yes | E53: Yes | F53: Yes | G53: =INDEX($D53:$F53,1,$H$4) -> Yes | H53: Dropdown — Lookup_Lists.YesNo
A55: TOKEN HELPER (calculated) · the comma-separated list fields split into five slots, so overlap can be counted with plain formulas rather than an array
A56: List field | B56: Slot | C56: Key | D56: BRAND-A | E56: BRAND-B | F56: BRAND-C | G56: Active Value | H56: How it is built
A57: Main Business Keywords | B57: slot 1 | C57: business_keywords_1 | D57: =TRIM(MID(SUBSTITUTE($D$13,",",REPT(" ",120)),1,120)) -> Technology | E57: =TRIM(MID(SUBSTITUTE($E$13,",",REPT(" ",120)),1,120)) -> Skincare | F57: =TRIM(MID(SUBSTITUTE($F$13,",",REPT(" ",120)),1,120)) -> Food | G57: =INDEX($D57:$F57,1,$H$4) -> Technology | H57: TRIM(MID(SUBSTITUTE(list, ",", REPT(" ",120)), (slot-1)*120+1, 120)) — the standard non-array split. Empty slots come back as "".
B58: slot 2 | C58: business_keywords_2 | D58: =TRIM(MID(SUBSTITUTE($D$13,",",REPT(" ",120)),121,120)) -> Productivity | E58: =TRIM(MID(SUBSTITUTE($E$13,",",REPT(" ",120)),121,120)) -> Beauty | F58: =TRIM(MID(SUBSTITUTE($F$13,",",REPT(" ",120)),121,120)) -> Cooking | G58: =INDEX($D58:$F58,1,$H$4) -> Productivity
B59: slot 3 | C59: business_keywords_3 | D59: =TRIM(MID(SUBSTITUTE($D$13,",",REPT(" ",120)),241,120)) -> Business | E59: =TRIM(MID(SUBSTITUTE($E$13,",",REPT(" ",120)),241,120)) -> Makeup | F59: =TRIM(MID(SUBSTITUTE($F$13,",",REPT(" ",120)),241,120)) -> Coffee | G59: =INDEX($D59:$F59,1,$H$4) -> Business
B60: slot 4 | C60: business_keywords_4 | D60: =TRIM(MID(SUBSTITUTE($D$13,",",REPT(" ",120)),361,120)) -> Education | E60: =TRIM(MID(SUBSTITUTE($E$13,",",REPT(" ",120)),361,120)) -> Health | F60: =TRIM(MID(SUBSTITUTE($F$13,",",REPT(" ",120)),361,120)) -> Shopping | G60: =INDEX($D60:$F60,1,$H$4) -> Education
B61: slot 5 | C61: business_keywords_5 | D61: =TRIM(MID(SUBSTITUTE($D$13,",",REPT(" ",120)),481,120)) -> Finance | E61: =TRIM(MID(SUBSTITUTE($E$13,",",REPT(" ",120)),481,120)) -> Shopping | F61: =TRIM(MID(SUBSTITUTE($F$13,",",REPT(" ",120)),481,120)) -> Entertainment | G61: =INDEX($D61:$F61,1,$H$4) -> Finance
B62: count | C62: business_keywords_count | D62: =IF($D$57="",0,1)+IF($D$58="",0,1)+IF($D$59="",0,1)+IF($D$60="",0,1)+IF($D$61="",0,1) -> 5 | E62: =IF($E$57="",0,1)+IF($E$58="",0,1)+IF($E$59="",0,1)+IF($E$60="",0,1)+IF($E$61="",0,1) -> 5 | F62: =IF($F$57="",0,1)+IF($F$58="",0,1)+IF($F$59="",0,1)+IF($F$60="",0,1)+IF($F$61="",0,1) -> 5 | G62: =INDEX($D62:$F62,1,$H$4) -> 5 | H62: Denominator for the overlap score. A brand that names three keywords is judged out of three, not out of five.
A63: Audience Interests | B63: slot 1 | C63: audience_interests_1 | D63: =TRIM(MID(SUBSTITUTE($D$22,",",REPT(" ",120)),1,120)) -> Technology | E63: =TRIM(MID(SUBSTITUTE($E$22,",",REPT(" ",120)),1,120)) -> Skincare | F63: =TRIM(MID(SUBSTITUTE($F$22,",",REPT(" ",120)),1,120)) -> Food | G63: =INDEX($D63:$F63,1,$H$4) -> Technology | H63: TRIM(MID(SUBSTITUTE(list, ",", REPT(" ",120)), (slot-1)*120+1, 120)) — the standard non-array split. Empty slots come back as "".
B64: slot 2 | C64: audience_interests_2 | D64: =TRIM(MID(SUBSTITUTE($D$22,",",REPT(" ",120)),121,120)) -> Business | E64: =TRIM(MID(SUBSTITUTE($E$22,",",REPT(" ",120)),121,120)) -> Beauty | F64: =TRIM(MID(SUBSTITUTE($F$22,",",REPT(" ",120)),121,120)) -> Cooking | G64: =INDEX($D64:$F64,1,$H$4) -> Business
B65: slot 3 | C65: audience_interests_3 | D65: =TRIM(MID(SUBSTITUTE($D$22,",",REPT(" ",120)),241,120)) -> Productivity | E65: =TRIM(MID(SUBSTITUTE($E$22,",",REPT(" ",120)),241,120)) -> Makeup | F65: =TRIM(MID(SUBSTITUTE($F$22,",",REPT(" ",120)),241,120)) -> Coffee | G65: =INDEX($D65:$F65,1,$H$4) -> Productivity
B66: slot 4 | C66: audience_interests_4 | D66: =TRIM(MID(SUBSTITUTE($D$22,",",REPT(" ",120)),361,120)) -> Education | E66: =TRIM(MID(SUBSTITUTE($E$22,",",REPT(" ",120)),361,120)) -> Fashion | F66: =TRIM(MID(SUBSTITUTE($F$22,",",REPT(" ",120)),361,120)) -> Travel | G66: =INDEX($D66:$F66,1,$H$4) -> Education
B67: slot 5 | C67: audience_interests_5 | D67: =TRIM(MID(SUBSTITUTE($D$22,",",REPT(" ",120)),481,120)) -> Finance | E67: =TRIM(MID(SUBSTITUTE($E$22,",",REPT(" ",120)),481,120)) -> Shopping | F67: =TRIM(MID(SUBSTITUTE($F$22,",",REPT(" ",120)),481,120)) -> Entertainment | G67: =INDEX($D67:$F67,1,$H$4) -> Finance
B68: count | C68: audience_interests_count | D68: =IF($D$63="",0,1)+IF($D$64="",0,1)+IF($D$65="",0,1)+IF($D$66="",0,1)+IF($D$67="",0,1) -> 5 | E68: =IF($E$63="",0,1)+IF($E$64="",0,1)+IF($E$65="",0,1)+IF($E$66="",0,1)+IF($E$67="",0,1) -> 5 | F68: =IF($F$63="",0,1)+IF($F$64="",0,1)+IF($F$65="",0,1)+IF($F$66="",0,1)+IF($F$67="",0,1) -> 5 | G68: =INDEX($D68:$F68,1,$H$4) -> 5 | H68: Denominator for the overlap score. A brand that names three keywords is judged out of three, not out of five.
A69: Brand Keywords | B69: slot 1 | C69: brand_keywords_1 | D69: =TRIM(MID(SUBSTITUTE($D$29,",",REPT(" ",120)),1,120)) -> Technology | E69: =TRIM(MID(SUBSTITUTE($E$29,",",REPT(" ",120)),1,120)) -> Skincare | F69: =TRIM(MID(SUBSTITUTE($F$29,",",REPT(" ",120)),1,120)) -> Food | G69: =INDEX($D69:$F69,1,$H$4) -> Technology | H69: TRIM(MID(SUBSTITUTE(list, ",", REPT(" ",120)), (slot-1)*120+1, 120)) — the standard non-array split. Empty slots come back as "".
B70: slot 2 | C70: brand_keywords_2 | D70: =TRIM(MID(SUBSTITUTE($D$29,",",REPT(" ",120)),121,120)) -> Productivity | E70: =TRIM(MID(SUBSTITUTE($E$29,",",REPT(" ",120)),121,120)) -> Beauty | F70: =TRIM(MID(SUBSTITUTE($F$29,",",REPT(" ",120)),121,120)) -> Cooking | G70: =INDEX($D70:$F70,1,$H$4) -> Productivity
B71: slot 3 | C71: brand_keywords_3 | D71: =TRIM(MID(SUBSTITUTE($D$29,",",REPT(" ",120)),241,120)) -> Business | E71: =TRIM(MID(SUBSTITUTE($E$29,",",REPT(" ",120)),241,120)) -> Health | F71: =TRIM(MID(SUBSTITUTE($F$29,",",REPT(" ",120)),241,120)) -> Coffee | G71: =INDEX($D71:$F71,1,$H$4) -> Business
B72: slot 4 | C72: brand_keywords_4 | D72: =TRIM(MID(SUBSTITUTE($D$29,",",REPT(" ",120)),361,120)) -> Education | E72: =TRIM(MID(SUBSTITUTE($E$29,",",REPT(" ",120)),361,120)) -> Makeup | F72: =TRIM(MID(SUBSTITUTE($F$29,",",REPT(" ",120)),361,120)) -> Entertainment | G72: =INDEX($D72:$F72,1,$H$4) -> Education
B73: slot 5 | C73: brand_keywords_5 | D73: =TRIM(MID(SUBSTITUTE($D$29,",",REPT(" ",120)),481,120)) -> Finance | E73: =TRIM(MID(SUBSTITUTE($E$29,",",REPT(" ",120)),481,120)) -> Shopping | F73: =TRIM(MID(SUBSTITUTE($F$29,",",REPT(" ",120)),481,120)) -> Shopping | G73: =INDEX($D73:$F73,1,$H$4) -> Finance
B74: count | C74: brand_keywords_count | D74: =IF($D$69="",0,1)+IF($D$70="",0,1)+IF($D$71="",0,1)+IF($D$72="",0,1)+IF($D$73="",0,1) -> 5 | E74: =IF($E$69="",0,1)+IF($E$70="",0,1)+IF($E$71="",0,1)+IF($E$72="",0,1)+IF($E$73="",0,1) -> 5 | F74: =IF($F$69="",0,1)+IF($F$70="",0,1)+IF($F$71="",0,1)+IF($F$72="",0,1)+IF($F$73="",0,1) -> 5 | G74: =INDEX($D74:$F74,1,$H$4) -> 5 | H74: Denominator for the overlap score. A brand that names three keywords is judged out of three, not out of five.
A75: Brand Values | B75: slot 1 | C75: brand_values_1 | D75: =TRIM(MID(SUBSTITUTE($D$26,",",REPT(" ",120)),1,120)) -> Innovation | E75: =TRIM(MID(SUBSTITUTE($E$26,",",REPT(" ",120)),1,120)) -> Quality | F75: =TRIM(MID(SUBSTITUTE($F$26,",",REPT(" ",120)),1,120)) -> Fun | G75: =INDEX($D75:$F75,1,$H$4) -> Innovation | H75: TRIM(MID(SUBSTITUTE(list, ",", REPT(" ",120)), (slot-1)*120+1, 120)) — the standard non-array split. Empty slots come back as "".
B76: slot 2 | C76: brand_values_2 | D76: =TRIM(MID(SUBSTITUTE($D$26,",",REPT(" ",120)),121,120)) -> Trust | E76: =TRIM(MID(SUBSTITUTE($E$26,",",REPT(" ",120)),121,120)) -> Authenticity | F76: =TRIM(MID(SUBSTITUTE($F$26,",",REPT(" ",120)),121,120)) -> Community | G76: =INDEX($D76:$F76,1,$H$4) -> Trust
B77: slot 3 | C77: brand_values_3 | D77: =TRIM(MID(SUBSTITUTE($D$26,",",REPT(" ",120)),241,120)) -> Transparency | E77: =TRIM(MID(SUBSTITUTE($E$26,",",REPT(" ",120)),241,120)) -> Trust | F77: =TRIM(MID(SUBSTITUTE($F$26,",",REPT(" ",120)),241,120)) -> Affordability | G77: =INDEX($D77:$F77,1,$H$4) -> Transparency
B78: slot 4 | C78: brand_values_4 | D78: =TRIM(MID(SUBSTITUTE($D$26,",",REPT(" ",120)),361,120)) -> Quality | E78: =TRIM(MID(SUBSTITUTE($E$26,",",REPT(" ",120)),361,120)) -> Craftsmanship | F78: =TRIM(MID(SUBSTITUTE($F$26,",",REPT(" ",120)),361,120)) -> Authenticity | G78: =INDEX($D78:$F78,1,$H$4) -> Quality
B79: slot 5 | C79: brand_values_5 | D79: =TRIM(MID(SUBSTITUTE($D$26,",",REPT(" ",120)),481,120)) -> Empowerment | E79: =TRIM(MID(SUBSTITUTE($E$26,",",REPT(" ",120)),481,120)) -> Health | F79: =TRIM(MID(SUBSTITUTE($F$26,",",REPT(" ",120)),481,120)) -> Family | G79: =INDEX($D79:$F79,1,$H$4) -> Empowerment
B80: count | C80: brand_values_count | D80: =IF($D$75="",0,1)+IF($D$76="",0,1)+IF($D$77="",0,1)+IF($D$78="",0,1)+IF($D$79="",0,1) -> 5 | E80: =IF($E$75="",0,1)+IF($E$76="",0,1)+IF($E$77="",0,1)+IF($E$78="",0,1)+IF($E$79="",0,1) -> 5 | F80: =IF($F$75="",0,1)+IF($F$76="",0,1)+IF($F$77="",0,1)+IF($F$78="",0,1)+IF($F$79="",0,1) -> 5 | G80: =INDEX($D80:$F80,1,$H$4) -> 5 | H80: Denominator for the overlap score. A brand that names three keywords is judged out of three, not out of five.
A81: Preferred Content Topics | B81: slot 1 | C81: preferred_content_topics_1 | D81: =TRIM(MID(SUBSTITUTE($D$40,",",REPT(" ",120)),1,120)) -> Technology | E81: =TRIM(MID(SUBSTITUTE($E$40,",",REPT(" ",120)),1,120)) -> Skincare | F81: =TRIM(MID(SUBSTITUTE($F$40,",",REPT(" ",120)),1,120)) -> Food | G81: =INDEX($D81:$F81,1,$H$4) -> Technology | H81: TRIM(MID(SUBSTITUTE(list, ",", REPT(" ",120)), (slot-1)*120+1, 120)) — the standard non-array split. Empty slots come back as "".
B82: slot 2 | C82: preferred_content_topics_2 | D82: =TRIM(MID(SUBSTITUTE($D$40,",",REPT(" ",120)),121,120)) -> Business | E82: =TRIM(MID(SUBSTITUTE($E$40,",",REPT(" ",120)),121,120)) -> Beauty | F82: =TRIM(MID(SUBSTITUTE($F$40,",",REPT(" ",120)),121,120)) -> Cooking | G82: =INDEX($D82:$F82,1,$H$4) -> Business
B83: slot 3 | C83: preferred_content_topics_3 | D83: =TRIM(MID(SUBSTITUTE($D$40,",",REPT(" ",120)),241,120)) -> Education | E83: =TRIM(MID(SUBSTITUTE($E$40,",",REPT(" ",120)),241,120)) -> Makeup | F83: =TRIM(MID(SUBSTITUTE($F$40,",",REPT(" ",120)),241,120)) -> Coffee | G83: =INDEX($D83:$F83,1,$H$4) -> Education
B84: slot 4 | C84: preferred_content_topics_4 | D84: =TRIM(MID(SUBSTITUTE($D$40,",",REPT(" ",120)),361,120)) -> Productivity | E84: =TRIM(MID(SUBSTITUTE($E$40,",",REPT(" ",120)),361,120)) -> Health | F84: =TRIM(MID(SUBSTITUTE($F$40,",",REPT(" ",120)),361,120)) -> Entertainment | G84: =INDEX($D84:$F84,1,$H$4) -> Productivity
B85: slot 5 | C85: preferred_content_topics_5 | D85: =TRIM(MID(SUBSTITUTE($D$40,",",REPT(" ",120)),481,120)) -> Finance | E85: =TRIM(MID(SUBSTITUTE($E$40,",",REPT(" ",120)),481,120)) -> Shopping | F85: =TRIM(MID(SUBSTITUTE($F$40,",",REPT(" ",120)),481,120)) -> Travel | G85: =INDEX($D85:$F85,1,$H$4) -> Finance
B86: count | C86: preferred_content_topics_count | D86: =IF($D$81="",0,1)+IF($D$82="",0,1)+IF($D$83="",0,1)+IF($D$84="",0,1)+IF($D$85="",0,1) -> 5 | E86: =IF($E$81="",0,1)+IF($E$82="",0,1)+IF($E$83="",0,1)+IF($E$84="",0,1)+IF($E$85="",0,1) -> 5 | F86: =IF($F$81="",0,1)+IF($F$82="",0,1)+IF($F$83="",0,1)+IF($F$84="",0,1)+IF($F$85="",0,1) -> 5 | G86: =INDEX($D86:$F86,1,$H$4) -> 5 | H86: Denominator for the overlap score. A brand that names three keywords is judged out of three, not out of five.
A87: Preferred Creator Values | B87: slot 1 | C87: preferred_creator_values_1 | D87: =TRIM(MID(SUBSTITUTE($D$42,",",REPT(" ",120)),1,120)) -> Innovation | E87: =TRIM(MID(SUBSTITUTE($E$42,",",REPT(" ",120)),1,120)) -> Authenticity | F87: =TRIM(MID(SUBSTITUTE($F$42,",",REPT(" ",120)),1,120)) -> Fun | G87: =INDEX($D87:$F87,1,$H$4) -> Innovation | H87: TRIM(MID(SUBSTITUTE(list, ",", REPT(" ",120)), (slot-1)*120+1, 120)) — the standard non-array split. Empty slots come back as "".
B88: slot 2 | C88: preferred_creator_values_2 | D88: =TRIM(MID(SUBSTITUTE($D$42,",",REPT(" ",120)),121,120)) -> Trust | E88: =TRIM(MID(SUBSTITUTE($E$42,",",REPT(" ",120)),121,120)) -> Quality | F88: =TRIM(MID(SUBSTITUTE($F$42,",",REPT(" ",120)),121,120)) -> Community | G88: =INDEX($D88:$F88,1,$H$4) -> Trust
B89: slot 3 | C89: preferred_creator_values_3 | D89: =TRIM(MID(SUBSTITUTE($D$42,",",REPT(" ",120)),241,120)) -> Quality | E89: =TRIM(MID(SUBSTITUTE($E$42,",",REPT(" ",120)),241,120)) -> Trust | F89: =TRIM(MID(SUBSTITUTE($F$42,",",REPT(" ",120)),241,120)) -> Authenticity | G89: =INDEX($D89:$F89,1,$H$4) -> Quality
B90: slot 4 | C90: preferred_creator_values_4 | D90: =TRIM(MID(SUBSTITUTE($D$42,",",REPT(" ",120)),361,120)) -> Transparency | E90: =TRIM(MID(SUBSTITUTE($E$42,",",REPT(" ",120)),361,120)) -> Health | F90: =TRIM(MID(SUBSTITUTE($F$42,",",REPT(" ",120)),361,120)) -> Family | G90: =INDEX($D90:$F90,1,$H$4) -> Transparency
B91: slot 5 | C91: preferred_creator_values_5 | D91: =TRIM(MID(SUBSTITUTE($D$42,",",REPT(" ",120)),481,120)) -> Empowerment | E91: =TRIM(MID(SUBSTITUTE($E$42,",",REPT(" ",120)),481,120)) -> Craftsmanship | F91: =TRIM(MID(SUBSTITUTE($F$42,",",REPT(" ",120)),481,120)) -> Affordability | G91: =INDEX($D91:$F91,1,$H$4) -> Empowerment
B92: count | C92: preferred_creator_values_count | D92: =IF($D$87="",0,1)+IF($D$88="",0,1)+IF($D$89="",0,1)+IF($D$90="",0,1)+IF($D$91="",0,1) -> 5 | E92: =IF($E$87="",0,1)+IF($E$88="",0,1)+IF($E$89="",0,1)+IF($E$90="",0,1)+IF($E$91="",0,1) -> 5 | F92: =IF($F$87="",0,1)+IF($F$88="",0,1)+IF($F$89="",0,1)+IF($F$90="",0,1)+IF($F$91="",0,1) -> 5 | G92: =INDEX($D92:$F92,1,$H$4) -> 5 | H92: Denominator for the overlap score. A brand that names three keywords is judged out of three, not out of five.
A94: AUDIENCE SUB-WEIGHTS (calculated) · Audience Demographics Priority moves weight onto one dimension and takes a third of the bonus off each of the others
A95: Dimension | B95: Base weight | C95: Key | D95: BRAND-A | E95: BRAND-B | F95: BRAND-C | G95: Active Value | H95: Rule
A96: Age Match | B96: =Lookup_Lists!$D$113 -> 25 | C96: w_age | D96: =MAX(0,Lookup_Lists!$D$113+IF($D$23="Age",Lookup_Lists!$D$117,IF($D$23="Balanced",0,-Lookup_Lists!$D$117/3))) -> 21 | E96: =MAX(0,Lookup_Lists!$D$113+IF($E$23="Age",Lookup_Lists!$D$117,IF($E$23="Balanced",0,-Lookup_Lists!$D$117/3))) -> 21 | F96: =MAX(0,Lookup_Lists!$D$113+IF($F$23="Age",Lookup_Lists!$D$117,IF($F$23="Balanced",0,-Lookup_Lists!$D$117/3))) -> 37 | G96: =INDEX($D96:$F96,1,$H$4) -> 21 | H96: base + bonus when priority = Age, base − bonus/3 otherwise
A97: Gender Match | B97: =Lookup_Lists!$D$114 -> 15 | C97: w_gender | D97: =MAX(0,Lookup_Lists!$D$114+IF($D$23="Gender",Lookup_Lists!$D$117,IF($D$23="Balanced",0,-Lookup_Lists!$D$117/3))) -> 11 | E97: =MAX(0,Lookup_Lists!$D$114+IF($E$23="Gender",Lookup_Lists!$D$117,IF($E$23="Balanced",0,-Lookup_Lists!$D$117/3))) -> 27 | F97: =MAX(0,Lookup_Lists!$D$114+IF($F$23="Gender",Lookup_Lists!$D$117,IF($F$23="Balanced",0,-Lookup_Lists!$D$117/3))) -> 11 | G97: =INDEX($D97:$F97,1,$H$4) -> 11 | H97: base + bonus when priority = Gender, base − bonus/3 otherwise
A98: Location Match | B98: =Lookup_Lists!$D$115 -> 30 | C98: w_location | D98: =MAX(0,Lookup_Lists!$D$115+IF($D$23="Location",Lookup_Lists!$D$117,IF($D$23="Balanced",0,-Lookup_Lists!$D$117/3))) -> 26 | E98: =MAX(0,Lookup_Lists!$D$115+IF($E$23="Location",Lookup_Lists!$D$117,IF($E$23="Balanced",0,-Lookup_Lists!$D$117/3))) -> 26 | F98: =MAX(0,Lookup_Lists!$D$115+IF($F$23="Location",Lookup_Lists!$D$117,IF($F$23="Balanced",0,-Lookup_Lists!$D$117/3))) -> 26 | G98: =INDEX($D98:$F98,1,$H$4) -> 26 | H98: base + bonus when priority = Location, base − bonus/3 otherwise
A99: Interest Match | B99: =Lookup_Lists!$D$116 -> 30 | C99: w_interest | D99: =MAX(0,Lookup_Lists!$D$116+IF($D$23="Interest",Lookup_Lists!$D$117,IF($D$23="Balanced",0,-Lookup_Lists!$D$117/3))) -> 42 | E99: =MAX(0,Lookup_Lists!$D$116+IF($E$23="Interest",Lookup_Lists!$D$117,IF($E$23="Balanced",0,-Lookup_Lists!$D$117/3))) -> 26 | F99: =MAX(0,Lookup_Lists!$D$116+IF($F$23="Interest",Lookup_Lists!$D$117,IF($F$23="Balanced",0,-Lookup_Lists!$D$117/3))) -> 26 | G99: =INDEX($D99:$F99,1,$H$4) -> 42 | H99: base + bonus when priority = Interest, base − bonus/3 otherwise

Sheet Campaign_Profile
A1: CAMPAIGN PROFILE · campaign is a context layer on top of Brand Match
A2: Brand defines the long-term identity; Campaign defines the specific activation. Style and personality remain explicit inputs, while Campaign Fit captures objective-specific requirements.
A4: Field | B4: Campaign A | C4: Campaign B | D4: Campaign C
A5: Campaign ID | B5: CAMP-A | C5: CAMP-B | D5: CAMP-C
A6: Brand ID | B6: BRAND-A | C6: BRAND-B | D6: BRAND-C
A7: Campaign Name | B7: Tech Productivity Launch | C7: Glow Up Routine | D7: Everyday Meal Moment
A8: Objective | B8: Awareness | C8: Engagement | D8: Conversion
A9: Platform | B9: Instagram | C9: TikTok | D9: Instagram
A10: Target Age | B10: 18-24 | C10: 18-24 | D10: 25-34
A11: Gender | B11: Balanced | C11: Female | D11: Balanced
A12: Target Country | B12: Indonesia | C12: Indonesia | D12: Indonesia
A13: Campaign Category | B13: Tech | C13: Beauty | D13: Food
A14: Key Topics | B14: Technology, Productivity, Business | C14: Skincare, Beauty, Makeup | D14: Food, Lifestyle, Cooking
A15: Content Style | B15: Educational | C15: Tutorial | D15: Review
... A20: Campaign Type | B20: Product Launch | C20: Engagement Challenge | D20: Conversion Campaign
A22: EDITABLE DEFAULT: Campaign Weight in Unified_Match = 30%; Base Brand Match = 70%.

Sheet Campaign_Match
A4: Campaign ID | B4: Brand ID | C4: KOL ID | D4: Creator | E4: Platform | F4: Category | G4: Brand Match | H4: Audience Fit | I4: Style Fit | J4: Personality Fit | K4: Tone Fit | L4: Comm. Style Fit | M4: Campaign Fit | N4: Unified Match | O4: Match Level | P4: Campaign Reason
A5: =Campaign_Profile!$B$5 -> CAMP-A | B5: =Campaign_Profile!$B$6 -> BRAND-A | C5: =KOL_Database!$A$5 -> KOL-01 | D5: =KOL_Database!$B$5 -> Ardi Nugraha | E5: =KOL_Database!$D$5 -> Instagram | F5: =KOL_Database!$E$5 -> Tech | G5: =IFERROR(INDEX(Matching_Engine!$AY$6:$AY$95,MATCH($B5&"|"&$C5,Matching_Engine!$AZ$6:$AZ$95,0)),0) -> 80 | H5: =IFERROR(INDEX(Matching_Engine!$S$6:$S$95,MATCH($B5&"|"&$C5,Matching_Engine!$AZ$6:$AZ$95,0)),0) -> 83 | I5: =IFERROR(INDEX(Matching_Engine!$W$6:$W$95,MATCH($B5&"|"&$C5,Matching_Engine!$AZ$6:$AZ$95,0)),0) -> 80 | J5: =IFERROR(INDEX(Matching_Engine!$Y$6:$Y$95,MATCH($B5&"|"&$C5,Matching_Engine!$AZ$6:$AZ$95,0)),0) -> 85 | K5: =IFERROR(INDEX(Matching_Engine!$Z$6:$Z$95,MATCH($B5&"|"&$C5,Matching_Engine!$AZ$6:$AZ$95,0)),0) -> 90 | L5: =IFERROR(INDEX(Matching_Engine!$AB$6:$AB$95,MATCH($B5&"|"&$C5,Matching_Engine!$AZ$6:$AZ$95,0)),0) -> 70 | M5: =ROUND($H5*0.3+$I5*0.3+$J5*0.25+$L5*0.15,1) -> 80.7 | N5: =ROUND($G5*0.7+$M5*0.3,1) -> 80.2 | O5: =IF($N5>=85,"Excellent Match",IF($N5>=70,"Strong Match",IF($N5>=55,"Good Match","Weak Match"))) -> Strong Match | P5: ="Brand "&ROUND($G5,0)&"/100; Audience "&ROUND($H5,0)&"/100; Style "&ROUND($I5,0)&"/100; Personality "&ROUND($J5,0)&"/100. Campaign Fit "&ROUND($M5,0)&"/100." -> Brand 80/100; Audience 83/100; Style 80/100; Personality 85/100. Campaign Fit 81/100.
A6: =Campaign_Profile!$B$5 -> CAMP-A | B6: =Campaign_Profile!$B$6 -> BRAND-A | C6: =KOL_Database!$A$6 -> KOL-02 | D6: =KOL_Database!$B$6 -> Rifqi Pratama | E6: =KOL_Database!$D$6 -> TikTok | F6: =KOL_Database!$E$6 -> Tech | G6: =IFERROR(INDEX(Matching_Engine!$AY$6:$AY$95,MATCH($B6&"|"&$C6,Matching_Engine!$AZ$6:$AZ$95,0)),0) -> 93 | H6: =IFERROR(INDEX(Matching_Engine!$S$6:$S$95,MATCH($B6&"|"&$C6,Matching_Engine!$AZ$6:$AZ$95,0)),0) -> 91 | I6: =IFERROR(INDEX(Matching_Engine!$W$6:$W$95,MATCH($B6&"|"&$C6,Matching_Engine!$AZ$6:$AZ$95,0)),0) -> 100 | J6: =IFERROR(INDEX(Matching_Engine!$Y$6:$Y$95,MATCH($B6&"|"&$C6,Matching_Engine!$AZ$6:$AZ$95,0)),0) -> 95 | K6: =IFERROR(INDEX(Matching_Engine!$Z$6:$Z$95,MATCH($B6&"|"&$C6,Matching_Engine!$AZ$6:$AZ$95,0)),0) -> 100 | L6: =IFERROR(INDEX(Matching_Engine!$AB$6:$AB$95,MATCH($B6&"|"&$C6,Matching_Engine!$AZ$6:$AZ$95,0)),0) -> 100 | M6: =ROUND($H6*0.3+$I6*0.3+$J6*0.25+$L6*0.15,1) -> 96.1 | N6: =ROUND($G6*0.7+$M6*0.3,1) -> 93.9 | O6: =IF($N6>=85,"Excellent Match",IF($N6>=70,"Strong Match",IF($N6>=55,"Good Match","Weak Match"))) -> Excellent Match | P6: ="Brand "&ROUND($G6,0)&"/100; Audience "&ROUND($H6,0)&"/100; Style "&ROUND($I6,0)&"/100; Personality "&ROUND($J6,0)&"/100. Campaign Fit "&ROUND($M6,0)&"/100." -> Brand 93/100; Audience 91/100; Style 100/100; Personality 95/100. Campaign Fit 96/100.
A7: =Campaign_Profile!$B$5 -> CAMP-A | B7: =Campaign_Profile!$B$6 -> BRAND-A | C7: =KOL_Database!$A$7 -> KOL-03 | D7: =KOL_Database!$B$7 -> Salsa Aulia | E7: =KOL_Database!$D$7 -> Instagram | F7: =KOL_Database!$E$7 -> Beauty | G7: =IFERROR(INDEX(Matching_Engine!$AY$6:$AY$95,MATCH($B7&"|"&$C7,Matching_Engine!$AZ$6:$AZ$95,0)),0) -> 48 | H7: =IFERROR(INDEX(Matching_Engine!$S$6:$S$95,MATCH($B7&"|"&$C7,Matching_Engine!$AZ$6:$AZ$95,0)),0) -> 58 | I7: =IFERROR(INDEX(Matching_Engine!$W$6:$W$95,MATCH($B7&"|"&$C7,Matching_Engine!$AZ$6:$AZ$95,0)),0) -> 80 | J7: =IFERROR(INDEX(Matching_Engine!$Y$6:$Y$95,MATCH($B7&"|"&$C7,Matching_Engine!$AZ$6:$AZ$95,0)),0) -> 85 | K7: =IFERROR(INDEX(Matching_Engine!$Z$6:$Z$95,MATCH($B7&"|"&$C7,Matching_Engine!$AZ$6:$AZ$95,0)),0) -> 90 | L7: =IFERROR(INDEX(Matching_Engine!$AB$6:$AB$95,MATCH($B7&"|"&$C7,Matching_Engine!$AZ$6:$AZ$95,0)),0) -> 70 | M7: =ROUND($H7*0.3+$I7*0.3+$J7*0.25+$L7*0.15,1) -> 73.2 | N7: =ROUND($G7*0.7+$M7*0.3,1) -> 55.6 | O7: =IF($N7>=85,"Excellent Match",IF($N7>=70,"Strong Match",IF($N7>=55,"Good Match","Weak Match"))) -> Good Match | P7: ="Brand "&ROUND($G7,0)&"/100; Audience "&ROUND($H7,0)&"/100; Style "&ROUND($I7,0)&"/100; Personality "&ROUND($J7,0)&"/100. Campaign Fit "&ROUND($M7,0)&"/100." -> Brand 48/100; Audience 58/100; Style 80/100; Personality 85/100. Campaign Fit 73/100.
A8: =Campaign_Profile!$B$5 -> CAMP-A | B8: =Campaign_Profile!$B$6 -> BRAND-A | C8: =KOL_Database!$A$8 -> KOL-04 | D8: =KOL_Database!$B$8 -> Nadia Puspa | E8: =KOL_Database!$D$8 -> TikTok | F8: =KOL_Database!$E$8 -> Beauty | G8: =IFERROR(INDEX(Matching_Engine!$AY$6:$AY$95,MATCH($B8&"|"&$C8,Matching_Engine!$AZ$6:$AZ$95,0)),0) -> 46 | H8: =IFERROR(INDEX(Matching_Engine!$S$6:$S$95,MATCH($B8&"|"&$C8,Matching_Engine!$AZ$6:$AZ$95,0)),0) -> 49 | I8: =IFERROR(INDEX(Matching_Engine!$W$6:$W$95,MATCH($B8&"|"&$C8,Matching_Engine!$AZ$6:$AZ$95,0)),0) -> 80 | J8: =IFERROR(INDEX(Matching_Engine!$Y$6:$Y$95,MATCH($B8&"|"&$C8,Matching_Engine!$AZ$6:$AZ$95,0)),0) -> 95 | K8: =IFERROR(INDEX(Matching_Engine!$Z$6:$Z$95,MATCH($B8&"|"&$C8,Matching_Engine!$AZ$6:$AZ$95,0)),0) -> 95 | L8: =IFERROR(INDEX(Matching_Engine!$AB$6:$AB$95,MATCH($B8&"|"&$C8,Matching_Engine!$AZ$6:$AZ$95,0)),0) -> 95 | M8: =ROUND($H8*0.3+$I8*0.3+$J8*0.25+$L8*0.15,1) -> 76.7 | N8: =ROUND($G8*0.7+$M8*0.3,1) -> 55.2 | O8: =IF($N8>=85,"Excellent Match",IF($N8>=70,"Strong Match",IF($N8>=55,"Good Match","Weak Match"))) -> Good Match | P8: ="Brand "&ROUND($G8,0)&"/100; Audience "&ROUND($H8,0)&"/100; Style "&ROUND($I8,0)&"/100; Personality "&ROUND($J8,0)&"/100. Campaign Fit "&ROUND($M8,0)&"/100." -> Brand 46/100; Audience 49/100; Style 80/100; Personality 95/100. Campaign Fit 77/100.
A9: =Campaign_Profile!$B$5 -> CAMP-A | B9: =Campaign_Profile!$B$6 -> BRAND-A | C9: =KOL_Database!$A$9 -> KOL-05 | D9: =KOL_Database!$B$9 -> Bimo Saputra | E9: =KOL_Database!$D$9 -> TikTok | F9: =KOL_Database!$E$9 -> Food | G9: =IFERROR(INDEX(Matching_Engine!$AY$6:$AY$95,MATCH($B9&"|"&$C9,Matching_Engine!$AZ$6:$AZ$95,0)),0) -> 45 | H9: =IFERROR(INDEX(Matching_Engine!$S$6:$S$95,MATCH($B9&"|"&$C9,Matching_Engine!$AZ$6:$AZ$95,0)),0) -> 54 | I9: =IFERROR(INDEX(Matching_Engine!$W$6:$W$95,MATCH($B9&"|"&$C9,Matching_Engine!$AZ$6:$AZ$95,0)),0) -> 80 | J9: =IFERROR(INDEX(Matching_Engine!$Y$6:$Y$95,MATCH($B9&"|"&$C9,Matching_Engine!$AZ$6:$AZ$95,0)),0) -> 50 | K9: =IFERROR(INDEX(Matching_Engine!$Z$6:$Z$95,MATCH($B9&"|"&$C9,Matching_Engine!$AZ$6:$AZ$95,0)),0) -> 90 | L9: =IFERROR(INDEX(Matching_Engine!$AB$6:$AB$95,MATCH($B9&"|"&$C9,Matching_Engine!$AZ$6:$AZ$95,0)),0) -> 70 | M9: =ROUND($H9*0.3+$I9*0.3+$J9*0.25+$L9*0.15,1) -> 63.2 | N9: =ROUND($G9*0.7+$M9*0.3,1) -> 50.5 | O9: =IF($N9>=85,"Excellent Match",IF($N9>=70,"Strong Match",IF($N9>=55,"Good Match","Weak Match"))) -> Weak Match | P9: ="Brand "&ROUND($G9,0)&"/100; Audience "&ROUND($H9,0)&"/100; Style "&ROUND($I9,0)&"/100; Personality "&ROUND($J9,0)&"/100. Campaign Fit "&ROUND($M9,0)&"/100." -> Brand 45/100; Audience 54/100; Style 80/100; Personality 50/100. Campaign Fit 63/100.
A10: =Campaign_Profile!$B$5 -> CAMP-A | B10: =Campaign_Profile!$B$6 -> BRAND-A | C10: =KOL_Database!$A$10 -> KOL-06 | D10: =KOL_Database!$B$10 -> Ayu Lestari | E10: =KOL_Database!$D$10 -> Instagram | F10: =KOL_Database!$E$10 -> Food | G10: =IFERROR(INDEX(Matching_Engine!$AY$6:$AY$95,MATCH($B10&"|"&$C10,Matching_Engine!$AZ$6:$AZ$95,0)),0) -> 44 | H10: =IFERROR(INDEX(Matching_Engine!$S$6:$S$95,MATCH($B10&"|"&$C10,Matching_Engine!$AZ$6:$AZ$95,0)),0) -> 50 | I10: =IFERROR(INDEX(Matching_Engine!$W$6:$W$95,MATCH($B10&"|"&$C10,Matching_Engine!$AZ$6:$AZ$95,0)),0) -> 80 | J10: =IFERROR(INDEX(Matching_Engine!$Y$6:$Y$95,MATCH($B10&"|"&$C10,Matching_Engine!$AZ$6:$AZ$95,0)),0) -> 50 | K10: =IFERROR(INDEX(Matching_Engine!$Z$6:$Z$95,MATCH($B10&"|"&$C10,Matching_Engine!$AZ$6:$AZ$95,0)),0) -> 95 | L10: =IFERROR(INDEX(Matching_Engine!$AB$6:$AB$95,MATCH($B10&"|"&$C10,Matching_Engine!$AZ$6:$AZ$95,0)),0) -> 95 | M10: =ROUND($H10*0.3+$I10*0.3+$J10*0.25+$L10*0.15,1) -> 65.8 | N10: =ROUND($G10*0.7+$M10*0.3,1) -> 50.5 | O10: =IF($N10>=85,"Excellent Match",IF($N10>=70,"Strong Match",IF($N10>=55,"Good Match","Weak Match"))) -> Weak Match | P10: ="Brand "&ROUND($G10,0)&"/100; Audience "&ROUND($H10,0)&"/100; Style "&ROUND($I10,0)&"/100; Personality "&ROUND($J10,0)&"/100. Campaign Fit "&ROUND($M10,0)&"/100." -> Brand 44/100; Audience 50/100; Style 80/100; Personality 50/100. Campaign Fit 66/100.
A11: =Campaign_Profile!$B$5 -> CAMP-A | B11: =Campaign_Profile!$B$6 -> BRAND-A | C11: =KOL_Database!$A$11 -> KOL-07 | D11: =KOL_Database!$B$11 -> Fajar Ramadhan | E11: =KOL_Database!$D$11 -> Instagram | F11: =KOL_Database!$E$11 -> Finance | G11: =IFERROR(INDEX(Matching_Engine!$AY$6:$AY$95,MATCH($B11&"|"&$C11,Matching_Engine!$AZ$6:$AZ$95,0)),0) -> 87 | H11: =IFERROR(INDEX(Matching_Engine!$S$6:$S$95,MATCH($B11&"|"&$C11,Matching_Engine!$AZ$6:$AZ$95,0)),0) -> 100 | I11: =IFERROR(INDEX(Matching_Engine!$W$6:$W$95,MATCH($B11&"|"&$C11,Matching_Engine!$AZ$6:$AZ$95,0)),0) -> 100 | J11: =IFERROR(INDEX(Matching_Engine!$Y$6:$Y$95,MATCH($B11&"|"&$C11,Matching_Engine!$AZ$6:$AZ$95,0)),0) -> 70 | K11: =IFERROR(INDEX(Matching_Engine!$Z$6:$Z$95,MATCH($B11&"|"&$C11,Matching_Engine!$AZ$6:$AZ$95,0)),0) -> 100 | L11: =IFERROR(INDEX(Matching_Engine!$AB$6:$AB$95,MATCH($B11&"|"&$C11,Matching_Engine!$AZ$6:$AZ$95,0)),0) -> 100 | M11: =ROUND($H11*0.3+$I11*0.3+$J11*0.25+$L11*0.15,1) -> 92.5 | N11: =ROUND($G11*0.7+$M11*0.3,1) -> 88.7 | O11: =IF($N11>=85,"Excellent Match",IF($N11>=70,"Strong Match",IF($N11>=55,"Good Match","Weak Match"))) -> Excellent Match | P11: ="Brand "&ROUND($G11,0)&"/100; Audience "&ROUND($H11,0)&"/100; Style "&ROUND($I11,0)&"/100; Personality "&ROUND($J11,0)&"/100. Campaign Fit "&ROUND($M11,0)&"/100." -> Brand 87/100; Audience 100/100; Style 100/100; Personality 70/100. Campaign Fit 93/100.
A12: =Campaign_Profile!$B$5 -> CAMP-A | B12: =Campaign_Profile!$B$6 -> BRAND-A | C12: =KOL_Database!$A$12 -> KOL-08 | D12: =KOL_Database!$B$12 -> Tania Wijaya | E12: =KOL_Database!$D$12 -> TikTok | F12: =KOL_Database!$E$12 -> Finance | G12: =IFERROR(INDEX(Matching_Engine!$AY$6:$AY$95,MATCH($B12&"|"&$C12,Matching_Engine!$AZ$6:$AZ$95,0)),0) | H12: =IFERROR(INDEX(Matching_Engine!$S$6:$S$95,MATCH($B12&"|"&$C12,Matching_Engine!$AZ$6:$AZ$95,0)),0) -> 92 | I12: =IFERROR(INDEX(Matching_Engine!$W$6:$W$95,MATCH($B12&"|"&$C12,Matching_Engine!$AZ$6:$AZ$95,0)),0) -> 100 | J12: =IFERROR(INDEX(Matching_Engine!$Y$6:$Y$95,MATCH($B12&"|"&$C12,Matching_Engine!$AZ$6:$AZ$95,0)),0) -> 95 | K12: =IFERROR(INDEX(Matching_Engine!$Z$6:$Z$95,MATCH($B12&"|"&$C12,Matching_Engine!$AZ$6:$AZ$95,0)),0) -> 100 | L12: =IFERROR(INDEX(Matching_Engine!$AB$6:$AB$95,MATCH($B12&"|"&$C12,Matching_Engine!$AZ$6:$AZ$95,0)),0) -> 100 | M12: =ROUND($H12*0.3+$I12*0.3+$J12*0.25+$L12*0.15,1) -> 96.4 | N12: =ROUND($G12*0.7+$M12*0.3,1) -> #VALUE! | O12: =IF($N12>=85,"Excellent Match",IF($N12>=70,"Strong Match",IF($N12>=55,"Good Match","Weak Match"))) -> #VALUE! | P12: ="Brand "&ROUND($G12,0)&"/100; Audience "&ROUND($H12,0)&"/100; Style "&ROUND($I12,0)&"/100; Personality "&ROUND($J12,0)&"/100. Campaign Fit "&ROUND($M12,0)&"/100." -> #VALUE!
A13: =Campaign_Profile!$B$5 -> CAMP-A | B13: =Campaign_Profile!$B$6 -> BRAND-A | C13: =KOL_Database!$A$13 -> KOL-09 | D13: =KOL_Database!$B$13 -> Gilang Prakoso | E13: =KOL_Database!$D$13 -> TikTok | F13: =KOL_Database!$E$13 -> Education | G13: =IFERROR(INDEX(Matching_Engine!$AY$6:$AY$95,MATCH($B13&"|"&$C13,Matching_Engine!$AZ$6:$AZ$95,0)),0) -> 81 | H13: =IFERROR(INDEX(Matching_Engine!$S$6:$S$95,MATCH($B13&"|"&$C13,Matching_Engine!$AZ$6:$AZ$95,0)),0) -> 83 | I13: =IFERROR(INDEX(Matching_Engine!$W$6:$W$95,MATCH($B13&"|"&$C13,Matching_Engine!$AZ$6:$AZ$95,0)),0) -> 100 | J13: =IFERROR(INDEX(Matching_Engine!$Y$6:$Y$95,MATCH($B13&"|"&$C13,Matching_Engine!$AZ$6:$AZ$95,0)),0) -> 95 | K13: =IFERROR(INDEX(Matching_Engine!$Z$6:$Z$95,MATCH($B13&"|"&$C13,Matching_Engine!$AZ$6:$AZ$95,0)),0) -> 100 | L13: =IFERROR(INDEX(Matching_Engine!$AB$6:$AB$95,MATCH($B13&"|"&$C13,Matching_Engine!$AZ$6:$AZ$95,0)),0) -> 100 | M13: =ROUND($H13*0.3+$I13*0.3+$J13*0.25+$L13*0.15,1) -> 93.7 | N13: =ROUND($G13*0.7+$M13*0.3,1) -> 84.8 | O13: =IF($N13>=85,"Excellent Match",IF($N13>=70,"Strong Match",IF($N13>=55,"Good Match","Weak Match"))) -> Strong Match | P13: ="Brand "&ROUND($G13,0)&"/100; Audience "&ROUND($H13,0)&"/100; Style "&ROUND($I13,0)&"/100; Personality "&ROUND($J13,0)&"/100. Campaign Fit "&ROUND($M13,0)&"/100." -> Brand 81/100; Audience 83/100; Style 100/100; Personality 95/100. Campaign Fit 94/100.
A14: =Campaign_Profile!$B$5 -> CAMP-A | B14: =Campaign_Profile!$B$6 -> BRAND-A | C14: =KOL_Database!$A$14 -> KOL-10 | D14: =KOL_Database!$B$14 -> Mira Handayani | E14: =KOL_Database!$D$14 -> Instagram | F14: =KOL_Database!$E$14 -> Education | G14: =IFERROR(INDEX(Matching_Engine!$AY$6:$AY$95,MATCH($B14&"|"&$C14,Matching_Engine!$AZ$6:$AZ$95,0)),0) -> 74 | H14: =IFERROR(INDEX(Matching_Engine!$S$6:$S$95,MATCH($B14&"|"&$C14,Matching_Engine!$AZ$6:$AZ$95,0)),0) -> 74 | I14: =IFERROR(INDEX(Matching_Engine!$W$6:$W$95,MATCH($B14&"|"&$C14,Matching_Engine!$AZ$6:$AZ$95,0)),0) -> 80 | J14: =IFERROR(INDEX(Matching_Engine!$Y$6:$Y$95,MATCH($B14&"|"&$C14,Matching_Engine!$AZ$6:$AZ$95,0)),0) -> 95 | K14: =IFERROR(INDEX(Matching_Engine!$Z$6:$Z$95,MATCH($B14&"|"&$C14,Matching_Engine!$AZ$6:$AZ$95,0)),0) -> 95 | L14: =IFERROR(INDEX(Matching_Engine!$AB$6:$AB$95,MATCH($B14&"|"&$C14,Matching_Engine!$AZ$6:$AZ$95,0)),0) -> 95 | M14: =ROUND($H14*0.3+$I14*0.3+$J14*0.25+$L14*0.15,1) -> 84.2 | N14: =ROUND($G14*0.7+$M14*0.3,1) -> 77.1 | O14: =IF($N14>=85,"Excellent Match",IF($N14>=70,"Strong Match",IF($N14>=55,"Good Match","Weak Match"))) -> Strong Match | P14: ="Brand "&ROUND($G14,0)&"/100; Audience "&ROUND($H14,0)&"/100; Style "&ROUND($I14,0)&"/100; Personality "&ROUND($J14,0)&"/100. Campaign Fit "&ROUND($M14,0)&"/100." -> Brand 74/100; Audience 74/100; Style 80/100; Personality 95/100. Campaign Fit 84/100.
A15: =Campaign_Profile!$B$5 -> CAMP-A | B15: =Campaign_Profile!$B$6 -> BRAND-A | C15: =KOL_Database!$A$15 -> KOL-11 | D15: =KOL_Database!$B$15 -> Dimas Anggara | E15: =KOL_Database!$D$15 -> Instagram | F15: =KOL_Database!$E$15 -> Fitness | G15: =IFERROR(INDEX(Matching_Engine!$AY$6:$AY$95,MATCH($B15&"|"&$C15,Matching_Engine!$AZ$6:$AZ$95,0)),0) | H15: =IFERROR(INDEX(Matching_Engine!$S$6:$S$95,MATCH($B15&"|"&$C15,Matching_Engine!$AZ$6:$AZ$95,0)),0) -> 58 | I15: =IFERROR(INDEX(Matching_Engine!$W$6:$W$95,MATCH($B15&"|"&$C15,Matching_Engine!$AZ$6:$AZ$95,0)),0) -> 80 | J15: =IFERROR(INDEX(Matching_Engine!$Y$6:$Y$95,MATCH($B15&"|"&$C15,Matching_Engine!$AZ$6:$AZ$95,0)),0) -> 70 | K15: =IFERROR(INDEX(Matching_Engine!$Z$6:$Z$95,MATCH($B15&"|"&$C15,Matching_Engine!$AZ$6:$AZ$95,0)),0) -> 85 | L15: =IFERROR(INDEX(Matching_Engine!$AB$6:$AB$95,MATCH($B15&"|"&$C15,Matching_Engine!$AZ$6:$AZ$95,0)),0) -> 80 | M15: =ROUND($H15*0.3+$I15*0.3+$J15*0.25+$L15*0.15,1) -> 70.9 | N15: =ROUND($G15*0.7+$M15*0.3,1) -> #VALUE! | O15: =IF($N15>=85,"Excellent Match",IF($N15>=70,"Strong Match",IF($N15>=55,"Good Match","Weak Match"))) -> #VALUE! | P15: ="Brand "&ROUND($G15,0)&"/100; Audience "&ROUND($H15,0)&"/100; Style "&ROUND($I15,0)&"/100; Personality "&ROUND($J15,0)&"/100. Campaign Fit "&ROUND($M15,0)&"/100." -> #VALUE!
A16: =Campaign_Profile!$B$5 -> CAMP-A | B16: =Campaign_Profile!$B$6 -> BRAND-A | C16: =KOL_Database!$A$16 -> KOL-12 | D16: =KOL_Database!$B$16 -> Rani Kusuma | E16: =KOL_Database!$D$16 -> TikTok | F16: =KOL_Database!$E$16 -> Fitness | G16: =IFERROR(INDEX(Matching_Engine!$AY$6:$AY$95,MATCH($B16&"|"&$C16,Matching_Engine!$AZ$6:$AZ$95,0)),0) -> 48 | H16: =IFERROR(INDEX(Matching_Engine!$S$6:$S$95,MATCH($B16&"|"&$C16,Matching_Engine!$AZ$6:$AZ$95,0)),0) -> 49 | I16: =IFERROR(INDEX(Matching_Engine!$W$6:$W$95,MATCH($B16&"|"&$C16,Matching_Engine!$AZ$6:$AZ$95,0)),0) -> 80 | J16: =IFERROR(INDEX(Matching_Engine!$Y$6:$Y$95,MATCH($B16&"|"&$C16,Matching_Engine!$AZ$6:$AZ$95,0)),0) -> 70 | K16: =IFERROR(INDEX(Matching_Engine!$Z$6:$Z$95,MATCH($B16&"|"&$C16,Matching_Engine!$AZ$6:$AZ$95,0)),0) -> 95 | L16: =IFERROR(INDEX(Matching_Engine!$AB$6:$AB$95,MATCH($B16&"|"&$C16,Matching_Engine!$AZ$6:$AZ$95,0)),0) -> 95 | M16: =ROUND($H16*0.3+$I16*0.3+$J16*0.25+$L16*0.15,1) -> 70.5 | N16: =ROUND($G16*0.7+$M16*0.3,1) -> 54.8 | O16: =IF($N16>=85,"Excellent Match",IF($N16>=70,"Strong Match",IF($N16>=55,"Good Match","Weak Match"))) -> Weak Match | P16: ="Brand "&ROUND($G16,0)&"/100; Audience "&ROUND($H16,0)&"/100; Style "&ROUND($I16,0)&"/100; Personality "&ROUND($J16,0)&"/100. Campaign Fit "&ROUND($M16,0)&"/100." -> Brand 48/100; Audience 49/100; Style 80/100; Personality 70/100. Campaign Fit 71/100.
A17: =Campaign_Profile!$B$5 -> CAMP-A | B17: =Campaign_Profile!$B$6 -> BRAND-A | C17: =KOL_Database!$A$17 -> KOL-13 | D17: =KOL_Database!$B$17 -> Kevin Halim | E17: =KOL_Database!$D$17 -> Instagram | F17: =KOL_Database!$E$17 -> Fashion | G17: =IFERROR(INDEX(Matching_Engine!$AY$6:$AY$95,MATCH($B17&"|"&$C17,Matching_Engine!$AZ$6:$AZ$95,0)),0) -> 45 | H17: =IFERROR(INDEX(Matching_Engine!$S$6:$S$95,MATCH($B17&"|"&$C17,Matching_Engine!$AZ$6:$AZ$95,0)),0) -> 58 | I17: =IFERROR(INDEX(Matching_Engine!$W$6:$W$95,MATCH($B17&"|"&$C17,Matching_Engine!$AZ$6:$AZ$95,0)),0) -> 45 | J17: =IFERROR(INDEX(Matching_Engine!$Y$6:$Y$95,MATCH($B17&"|"&$C17,Matching_Engine!$AZ$6:$AZ$95,0)),0) -> 95 | K17: =IFERROR(INDEX(Matching_Engine!$Z$6:$Z$95,MATCH($B17&"|"&$C17,Matching_Engine!$AZ$6:$AZ$95,0)),0) -> 50 | L17: =IFERROR(INDEX(Matching_Engine!$AB$6:$AB$95,MATCH($B17&"|"&$C17,Matching_Engine!$AZ$6:$AZ$95,0)),0) -> 45 | M17: =ROUND($H17*0.3+$I17*0.3+$J17*0.25+$L17*0.15,1) -> 61.4 | N17: =ROUND($G17*0.7+$M17*0.3,1) -> 49.9 | O17: =IF($N17>=85,"Excellent Match",IF($N17>=70,"Strong Match",IF($N17>=55,"Good Match","Weak Match"))) -> Weak Match | P17: ="Brand "&ROUND($G17,0)&"/100; Audience "&ROUND($H17,0)&"/100; Style "&ROUND($I17,0)&"/100; Personality "&ROUND($J17,0)&"/100. Campaign Fit "&ROUND($M17,0)&"/100." -> Brand 45/100; Audience 58/100; Style 45/100; Personality 95/100. Campaign Fit 61/100.
A18: =Campaign_Profile!$B$5 -> CAMP-A | B18: =Campaign_Profile!$B$6 -> BRAND-A | C18: =KOL_Database!$A$18 -> KOL-14 | D18: =KOL_Database!$B$18 -> Zahra Amelia | E18: =KOL_Database!$D$18 -> Instagram | F18: =KOL_Database!$E$18 -> Fashion | G18: =IFERROR(INDEX(Matching_Engine!$AY$6:$AY$95,MATCH($B18&"|"&$C18,Matching_Engine!$AZ$6:$AZ$95,0)),0) | H18: =IFERROR(INDEX(Matching_Engine!$S$6:$S$95,MATCH($B18&"|"&$C18,Matching_Engine!$AZ$6:$AZ$95,0)),0) -> 49 | I18: =IFERROR(INDEX(Matching_Engine!$W$6:$W$95,MATCH($B18&"|"&$C18,Matching_Engine!$AZ$6:$AZ$95,0)),0) -> 45 | J18: =IFERROR(INDEX(Matching_Engine!$Y$6:$Y$95,MATCH($B18&"|"&$C18,Matching_Engine!$AZ$6:$AZ$95,0)),0) -> 60 | K18: =IFERROR(INDEX(Matching_Engine!$Z$6:$Z$95,MATCH($B18&"|"&$C18,Matching_Engine!$AZ$6:$AZ$95,0)),0) -> 50 | L18: =IFERROR(INDEX(Matching_Engine!$AB$6:$AB$95,MATCH($B18&"|"&$C18,Matching_Engine!$AZ$6:$AZ$95,0)),0) -> 45 | M18: =ROUND($H18*0.3+$I18*0.3+$J18*0.25+$L18*0.15,1) -> 50 | N18: =ROUND($G18*0.7+$M18*0.3,1) -> #VALUE! | O18: =IF($N18>=85,"Excellent Match",IF($N18>=70,"Strong Match",IF($N18>=55,"Good Match","Weak Match"))) -> #VALUE! | P18: ="Brand "&ROUND($G18,0)&"/100; Audience "&ROUND($H18,0)&"/100; Style "&ROUND($I18,0)&"/100; Personality "&ROUND($J18,0)&"/100. Campaign Fit "&ROUND($M18,0)&"/100." -> #VALUE!
A19: =Campaign_Profile!$B$5 -> CAMP-A | B19: =Campaign_Profile!$B$6 -> BRAND-A | C19: =KOL_Database!$A$19 -> KOL-15 | D19: =KOL_Database!$B$19 -> Andini Rahma | E19: =KOL_Database!$D$19 -> Instagram | F19: =KOL_Database!$E$19 -> Lifestyle | G19: =IFERROR(INDEX(Matching_Engine!$AY$6:$AY$95,MATCH($B19&"|"&$C19,Matching_Engine!$AZ$6:$AZ$95,0)),0) -> 48 | H19: =IFERROR(INDEX(Matching_Engine!$S$6:$S$95,MATCH($B19&"|"&$C19,Matching_Engine!$AZ$6:$AZ$95,0)),0) -> 58 | I19: =IFERROR(INDEX(Matching_Engine!$W$6:$W$95,MATCH($B19&"|"&$C19,Matching_Engine!$AZ$6:$AZ$95,0)),0) -> 45 | J19: =IFERROR(INDEX(Matching_Engine!$Y$6:$Y$95,MATCH($B19&"|"&$C19,Matching_Engine!$AZ$6:$AZ$95,0)),0) -> 50 | K19: =IFERROR(INDEX(Matching_Engine!$Z$6:$Z$95,MATCH($B19&"|"&$C19,Matching_Engine!$AZ$6:$AZ$95,0)),0) -> 55 | L19: =IFERROR(INDEX(Matching_Engine!$AB$6:$AB$95,MATCH($B19&"|"&$C19,Matching_Engine!$AZ$6:$AZ$95,0)),0) -> 50 | M19: =ROUND($H19*0.3+$I19*0.3+$J19*0.25+$L19*0.15,1) -> 50.9 | N19: =ROUND($G19*0.7+$M19*0.3,1) -> 48.9 | O19: =IF($N19>=85,"Excellent Match",IF($N19>=70,"Strong Match",IF($N19>=55,"Good Match","Weak Match"))) -> Weak Match | P19: ="Brand "&ROUND($G19,0)&"/100; Audience "&ROUND($H19,0)&"/100; Style "&ROUND($I19,0)&"/100; Personality "&ROUND($J19,0)&"/100. Campaign Fit "&ROUND($M19,0)&"/100." -> Brand 48/100; Audience 58/100; Style 45/100; Personality 50/100. Campaign Fit 51/100.
A20: =Campaign_Profile!$B$5 -> CAMP-A | B20: =Campaign_Profile!$B$6 -> BRAND-A | C20: =KOL_Database!$A$20 -> KOL-16 | D20: =KOL_Database!$B$20 -> Yoga Pratama | E20: =KOL_Database!$D$20 -> TikTok | F20: =KOL_Database!$E$20 -> Lifestyle | G20: =IFERROR(INDEX(Matching_Engine!$AY$6:$AY$95,MATCH($B20&"|"&$C20,Matching_Engine!$AZ$6:$AZ$95,0)),0) -> 67 | H20: =IFERROR(INDEX(Matching_Engine!$S$6:$S$95,MATCH($B20&"|"&$C20,Matching_Engine!$AZ$6:$AZ$95,0)),0) -> 83 | I20: =IFERROR(INDEX(Matching_Engine!$W$6:$W$95,MATCH($B20&"|"&$C20,Matching_Engine!$AZ$6:$AZ$95,0)),0) -> 45 | J20: =IFERROR(INDEX(Matching_Engine!$Y$6:$Y$95,MATCH($B20&"|"&$C20,Matching_Engine!$AZ$6:$AZ$95,0)),0) -> 70 | K20: =IFERROR(INDEX(Matching_Engine!$Z$6:$Z$95,MATCH($B20&"|"&$C20,Matching_Engine!$AZ$6:$AZ$95,0)),0) -> 65 | L20: =IFERROR(INDEX(Matching_Engine!$AB$6:$AB$95,MATCH($B20&"|"&$C20,Matching_Engine!$AZ$6:$AZ$95,0)),0) -> 60 | M20: =ROUND($H20*0.3+$I20*0.3+$J20*0.25+$L20*0.15,1) -> 64.9 | N20: =ROUND($G20*0.7+$M20*0.3,1) -> 66.4 | O20: =IF($N20>=85,"Excellent Match",IF($N20>=70,"Strong Match",IF($N20>=55,"Good Match","Weak Match"))) -> Good Match | P20: ="Brand "&ROUND($G20,0)&"/100; Audience "&ROUND($H20,0)&"/100; Style "&ROUND($I20,0)&"/100; Personality "&ROUND($J20,0)&"/100. Campaign Fit "&ROUND($M20,0)&"/100." -> Brand 67/100; Audience 83/100; Style 45/100; Personality 70/100. Campaign Fit 65/100.
A21: =Campaign_Profile!$B$5 -> CAMP-A | B21: =Campaign_Profile!$B$6 -> BRAND-A | C21: =KOL_Database!$A$21 -> KOL-17 | D21: =KOL_Database!$B$21 -> Sinta Maharani | E21: =KOL_Database!$D$21 -> Instagram | F21: =KOL_Database!$E$21 -> Travel | G21: =IFERROR(INDEX(Matching_Engine!$AY$6:$AY$95,MATCH($B21&"|"&$C21,Matching_Engine!$AZ$6:$AZ$95,0)),0) -> 42 | H21: =IFERROR(INDEX(Matching_Engine!$S$6:$S$95,MATCH($B21&"|"&$C21,Matching_Engine!$AZ$6:$AZ$95,0)),0) -> 49 | I21: =IFERROR(INDEX(Matching_Engine!$W$6:$W$95,MATCH($B21&"|"&$C21,Matching_Engine!$AZ$6:$AZ$95,0)),0) -> 45 | J21: =IFERROR(INDEX(Matching_Engine!$Y$6:$Y$95,MATCH($B21&"|"&$C21,Matching_Engine!$AZ$6:$AZ$95,0)),0) -> 60 | K21: =IFERROR(INDEX(Matching_Engine!$Z$6:$Z$95,MATCH($B21&"|"&$C21,Matching_Engine!$AZ$6:$AZ$95,0)),0) -> 50 | L21: =IFERROR(INDEX(Matching_Engine!$AB$6:$AB$95,MATCH($B21&"|"&$C21,Matching_Engine!$AZ$6:$AZ$95,0)),0) -> 45 | M21: =ROUND($H21*0.3+$I21*0.3+$J21*0.25+$L21*0.15,1) -> 50 | N21: =ROUND($G21*0.7+$M21*0.3,1) -> 44.4 | O21: =IF($N21>=85,"Excellent Match",IF($N21>=70,"Strong Match",IF($N21>=55,"Good Match","Weak Match"))) -> Weak Match | P21: ="Brand "&ROUND($G21,0)&"/100; Audience "&ROUND($H21,0)&"/100; Style "&ROUND($I21,0)&"/100; Personality "&ROUND($J21,0)&"/100. Campaign Fit "&ROUND($M21,0)&"/100." -> Brand 42/100; Audience 49/100; Style 45/100; Personality 60/100. Campaign Fit 50/100.
A22: =Campaign_Profile!$B$5 -> CAMP-A | B22: =Campaign_Profile!$B$6 -> BRAND-A | C22: =KOL_Database!$A$22 -> KOL-18 | D22: =KOL_Database!$B$22 -> Reza Fadillah | E22: =KOL_Database!$D$22 -> TikTok | F22: =KOL_Database!$E$22 -> Travel | G22: =IFERROR(INDEX(Matching_Engine!$AY$6:$AY$95,MATCH($B22&"|"&$C22,Matching_Engine!$AZ$6:$AZ$95,0)),0) -> 48 | H22: =IFERROR(INDEX(Matching_Engine!$S$6:$S$95,MATCH($B22&"|"&$C22,Matching_Engine!$AZ$6:$AZ$95,0)),0) -> 57 | I22: =IFERROR(INDEX(Matching_Engine!$W$6:$W$95,MATCH($B22&"|"&$C22,Matching_Engine!$AZ$6:$AZ$95,0)),0) -> 45 | J22: =IFERROR(INDEX(Matching_Engine!$Y$6:$Y$95,MATCH($B22&"|"&$C22,Matching_Engine!$AZ$6:$AZ$95,0)),0) -> 40 | K22: =IFERROR(INDEX(Matching_Engine!$Z$6:$Z$95,MATCH($B22&"|"&$C22,Matching_Engine!$AZ$6:$AZ$95,0)),0) -> 55 | L22: =IFERROR(INDEX(Matching_Engine!$AB$6:$AB$95,MATCH($B22&"|"&$C22,Matching_Engine!$AZ$6:$AZ$95,0)),0) -> 50 | M22: =ROUND($H22*0.3+$I22*0.3+$J22*0.25+$L22*0.15,1) -> 48.1 | N22: =ROUND($G22*0.7+$M22*0.3,1) -> 48 | O22: =IF($N22>=85,"Excellent Match",IF($N22>=70,"Strong Match",IF($N22>=55,"Good Match","Weak Match"))) -> Weak Match | P22: ="Brand "&ROUND($G22,0)&"/100; Audience "&ROUND($H22,0)&"/100; Style "&ROUND($I22,0)&"/100; Personality "&ROUND($J22,0)&"/100. Campaign Fit "&ROUND($M22,0)&"/100." -> Brand 48/100; Audience 57/100; Style 45/100; Personality 40/100. Campaign Fit 48/100.
A23: =Campaign_Profile!$B$5 -> CAMP-A | B23: =Campaign_Profile!$B$6 -> BRAND-A | C23: =KOL_Database!$A$23 -> KOL-19 | D23: =KOL_Database!$B$23 -> Putri Amanda | E23: =KOL_Database!$D$23 -> Instagram | F23: =KOL_Database!$E$23 -> Parenting | G23: =IFERROR(INDEX(Matching_Engine!$AY$6:$AY$95,MATCH($B23&"|"&$C23,Matching_Engine!$AZ$6:$AZ$95,0)),0) -> 41 | H23: =IFERROR(INDEX(Matching_Engine!$S$6:$S$95,MATCH($B23&"|"&$C23,Matching_Engine!$AZ$6:$AZ$95,0)),0) -> 49 | I23: =IFERROR(INDEX(Matching_Engine!$W$6:$W$95,MATCH($B23&"|"&$C23,Matching_Engine!$AZ$6:$AZ$95,0)),0) -> 45 | J23: =IFERROR(INDEX(Matching_Engine!$Y$6:$Y$95,MATCH($B23&"|"&$C23,Matching_Engine!$AZ$6:$AZ$95,0)),0) -> 50 | K23: =IFERROR(INDEX(Matching_Engine!$Z$6:$Z$95,MATCH($B23&"|"&$C23,Matching_Engine!$AZ$6:$AZ$95,0)),0) -> 65 | L23: =IFERROR(INDEX(Matching_Engine!$AB$6:$AB$95,MATCH($B23&"|"&$C23,Matching_Engine!$AZ$6:$AZ$95,0)),0) -> 60 | M23: =ROUND($H23*0.3+$I23*0.3+$J23*0.25+$L23*0.15,1) -> 49.7 | N23: =ROUND($G23*0.7+$M23*0.3,1) -> 43.6 | O23: =IF($N23>=85,"Excellent Match",IF($N23>=70,"Strong Match",IF($N23>=55,"Good Match","Weak Match"))) -> Weak Match | P23: ="Brand "&ROUND($G23,0)&"/100; Audience "&ROUND($H23,0)&"/100; Style "&ROUND($I23,0)&"/100; Personality "&ROUND($J23,0)&"/100. Campaign Fit "&ROUND($M23,0)&"/100." -> Brand 41/100; Audience 49/100; Style 45/100; Personality 50/100. Campaign Fit 50/100.
A24: =Campaign_Profile!$B$5 -> CAMP-A | B24: =Campaign_Profile!$B$6 -> BRAND-A | C24: =KOL_Database!$A$24 -> KOL-20 | D24: =KOL_Database!$B$24 -> Hendra Wijoyo | E24: =KOL_Database!$D$24 -> TikTok | F24: =KOL_Database!$E$24 -> Parenting | G24: =IFERROR(INDEX(Matching_Engine!$AY$6:$AY$95,MATCH($B24&"|"&$C24,Matching_Engine!$AZ$6:$AZ$95,0)),0) -> 45 | H24: =IFERROR(INDEX(Matching_Engine!$S$6:$S$95,MATCH($B24&"|"&$C24,Matching_Engine!$AZ$6:$AZ$95,0)),0) -> 57 | I24: =IFERROR(INDEX(Matching_Engine!$W$6:$W$95,MATCH($B24&"|"&$C24,Matching_Engine!$AZ$6:$AZ$95,0)),0) -> 45 | J24: =IFERROR(INDEX(Matching_Engine!$Y$6:$Y$95,MATCH($B24&"|"&$C24,Matching_Engine!$AZ$6:$AZ$95,0)),0) -> 30 | K24: =IFERROR(INDEX(Matching_Engine!$Z$6:$Z$95,MATCH($B24&"|"&$C24,Matching_Engine!$AZ$6:$AZ$95,0)),0) -> 40 | L24: =IFERROR(INDEX(Matching_Engine!$AB$6:$AB$95,MATCH($B24&"|"&$C24,Matching_Engine!$AZ$6:$AZ$95,0)),0) -> 40 | M24: =ROUND($H24*0.3+$I24*0.3+$J24*0.25+$L24*0.15,1) -> 44.1 | N24: =ROUND($G24*0.7+$M24*0.3,1) -> 44.7 | O24: =IF($N24>=85,"Excellent Match",IF($N24>=70,"Strong Match",IF($N24>=55,"Good Match","Weak Match"))) -> Weak Match | P24: ="Brand "&ROUND($G24,0)&"/100; Audience "&ROUND($H24,0)&"/100; Style "&ROUND($I24,0)&"/100; Personality "&ROUND($J24,0)&"/100. Campaign Fit "&ROUND($M24,0)&"/100." -> Brand 45/100; Audience 57/100; Style 45/100; Personality 30/100. Campaign Fit 44/100.
A25: =Campaign_Profile!$B$5 -> CAMP-A | B25: =Campaign_Profile!$B$6 -> BRAND-A | C25: =KOL_Database!$A$25 -> KOL-21 | D25: =KOL_Database!$B$25 -> Bagas Setiawan | E25: =KOL_Database!$D$25 -> TikTok | F25: =KOL_Database!$E$25 -> Entertainment | G25: =IFERROR(INDEX(Matching_Engine!$AY$6:$AY$95,MATCH($B25&"|"&$C25,Matching_Engine!$AZ$6:$AZ$95,0)),0) | H25: =IFERROR(INDEX(Matching_Engine!$S$6:$S$95,MATCH($B25&"|"&$C25,Matching_Engine!$AZ$6:$AZ$95,0)),0) -> 49 | I25: =IFERROR(INDEX(Matching_Engine!$W$6:$W$95,MATCH($B25&"|"&$C25,Matching_Engine!$AZ$6:$AZ$95,0)),0) -> 45 | J25: =IFERROR(INDEX(Matching_Engine!$Y$6:$Y$95,MATCH($B25&"|"&$C25,Matching_Engine!$AZ$6:$AZ$95,0)),0) -> 30 | K25: =IFERROR(INDEX(Matching_Engine!$Z$6:$Z$95,MATCH($B25&"|"&$C25,Matching_Engine!$AZ$6:$AZ$95,0)),0) -> 30 | L25: =IFERROR(INDEX(Matching_Engine!$AB$6:$AB$95,MATCH($B25&"|"&$C25,Matching_Engine!$AZ$6:$AZ$95,0)),0) -> 30 | M25: =ROUND($H25*0.3+$I25*0.3+$J25*0.25+$L25*0.15,1) -> 40.2 | N25: =ROUND($G25*0.7+$M25*0.3,1) -> #VALUE! | O25: =IF($N25>=85,"Excellent Match",IF($N25>=70,"Strong Match",IF($N25>=55,"Good Match","Weak Match"))) -> #VALUE! | P25: ="Brand "&ROUND($G25,0)&"/100; Audience "&ROUND($H25,0)&"/100; Style "&ROUND($I25,0)&"/100; Personality "&ROUND($J25,0)&"/100. Campaign Fit "&ROUND($M25,0)&"/100." -> #VALUE!
A26: =Campaign_Profile!$B$5 -> CAMP-A | B26: =Campaign_Profile!$B$6 -> BRAND-A | C26: =KOL_Database!$A$26 -> KOL-22 | D26: =KOL_Database!$B$26 -> Nabila Kirana | E26: =KOL_Database!$D$26 -> Instagram | F26: =KOL_Database!$E$26 -> Entertainment | G26: =IFERROR(INDEX(Matching_Engine!$AY$6:$AY$95,MATCH($B26&"|"&$C26,Matching_Engine!$AZ$6:$AZ$95,0)),0) | H26: =IFERROR(INDEX(Matching_Engine!$S$6:$S$95,MATCH($B26&"|"&$C26,Matching_Engine!$AZ$6:$AZ$95,0)),0) -> 54 | I26: =IFERROR(INDEX(Matching_Engine!$W$6:$W$95,MATCH($B26&"|"&$C26,Matching_Engine!$AZ$6:$AZ$95,0)),0) -> 45 | J26: =IFERROR(INDEX(Matching_Engine!$Y$6:$Y$95,MATCH($B26&"|"&$C26,Matching_Engine!$AZ$6:$AZ$95,0)),0) -> 95 | K26: =IFERROR(INDEX(Matching_Engine!$Z$6:$Z$95,MATCH($B26&"|"&$C26,Matching_Engine!$AZ$6:$AZ$95,0)),0) -> 50 | L26: =IFERROR(INDEX(Matching_Engine!$AB$6:$AB$95,MATCH($B26&"|"&$C26,Matching_Engine!$AZ$6:$AZ$95,0)),0) -> 45 | M26: =ROUND($H26*0.3+$I26*0.3+$J26*0.25+$L26*0.15,1) -> 60.2 | N26: =ROUND($G26*0.7+$M26*0.3,1) -> #VALUE! | O26: =IF($N26>=85,"Excellent Match",IF($N26>=70,"Strong Match",IF($N26>=55,"Good Match","Weak Match"))) -> #VALUE! | P26: ="Brand "&ROUND($G26,0)&"/100; Audience "&ROUND($H26,0)&"/100; Style "&ROUND($I26,0)&"/100; Personality "&ROUND($J26,0)&"/100. Campaign Fit "&ROUND($M26,0)&"/100." -> #VALUE!
A27: =Campaign_Profile!$B$5 -> CAMP-A | B27: =Campaign_Profile!$B$6 -> BRAND-A | C27: =KOL_Database!$A$27 -> KOL-23 | D27: =KOL_Database!$B$27 -> Arya Mahendra | E27: =KOL_Database!$D$27 -> TikTok | F27: =KOL_Database!$E$27 -> Gaming | G27: =IFERROR(INDEX(Matching_Engine!$AY$6:$AY$95,MATCH($B27&"|"&$C27,Matching_Engine!$AZ$6:$AZ$95,0)),0) -> 57 | H27: =IFERROR(INDEX(Matching_Engine!$S$6:$S$95,MATCH($B27&"|"&$C27,Matching_Engine!$AZ$6:$AZ$95,0)),0) -> 57 | I27: =IFERROR(INDEX(Matching_Engine!$W$6:$W$95,MATCH($B27&"|"&$C27,Matching_Engine!$AZ$6:$AZ$95,0)),0) -> 45 | J27: =IFERROR(INDEX(Matching_Engine!$Y$6:$Y$95,MATCH($B27&"|"&$C27,Matching_Engine!$AZ$6:$AZ$95,0)),0) -> 45 | K27: =IFERROR(INDEX(Matching_Engine!$Z$6:$Z$95,MATCH($B27&"|"&$C27,Matching_Engine!$AZ$6:$AZ$95,0)),0) -> 40 | L27: =IFERROR(INDEX(Matching_Engine!$AB$6:$AB$95,MATCH($B27&"|"&$C27,Matching_Engine!$AZ$6:$AZ$95,0)),0) -> 40 | M27: =ROUND($H27*0.3+$I27*0.3+$J27*0.25+$L27*0.15,1) -> 47.9 | N27: =ROUND($G27*0.7+$M27*0.3,1) -> 54.3 | O27: =IF($N27>=85,"Excellent Match",IF($N27>=70,"Strong Match",IF($N27>=55,"Good Match","Weak Match"))) -> Weak Match | P27: ="Brand "&ROUND($G27,0)&"/100; Audience "&ROUND($H27,0)&"/100; Style "&ROUND($I27,0)&"/100; Personality "&ROUND($J27,0)&"/100. Campaign Fit "&ROUND($M27,0)&"/100." -> Brand 57/100; Audience 57/100; Style 45/100; Personality 45/100. Campaign Fit 48/100.
A28: =Campaign_Profile!$B$5 -> CAMP-A | B28: =Campaign_Profile!$B$6 -> BRAND-A | C28: =KOL_Database!$A$28 -> KOL-24 | D28: =KOL_Database!$B$28 -> Rio Saputra | E28: =KOL_Database!$D$28 -> Instagram | F28: =KOL_Database!$E$28 -> Gaming | G28: =IFERROR(INDEX(Matching_Engine!$AY$6:$AY$95,MATCH($B28&"|"&$C28,Matching_Engine!$AZ$6:$AZ$95,0)),0) -> 66 | H28: =IFERROR(INDEX(Matching_Engine!$S$6:$S$95,MATCH($B28&"|"&$C28,Matching_Engine!$AZ$6:$AZ$95,0)),0) -> 68 | I28: =IFERROR(INDEX(Matching_Engine!$W$6:$W$95,MATCH($B28&"|"&$C28,Matching_Engine!$AZ$6:$AZ$95,0)),0) -> 80 | J28: =IFERROR(INDEX(Matching_Engine!$Y$6:$Y$95,MATCH($B28&"|"&$C28,Matching_Engine!$AZ$6:$AZ$95,0)),0) -> 100 | K28: =IFERROR(INDEX(Matching_Engine!$Z$6:$Z$95,MATCH($B28&"|"&$C28,Matching_Engine!$AZ$6:$AZ$95,0)),0) -> 85 | L28: =IFERROR(INDEX(Matching_Engine!$AB$6:$AB$95,MATCH($B28&"|"&$C28,Matching_Engine!$AZ$6:$AZ$95,0)),0) -> 80 | M28: =ROUND($H28*0.3+$I28*0.3+$J28*0.25+$L28*0.15,1) -> 81.4 | N28: =ROUND($G28*0.7+$M28*0.3,1) -> 70.6 | O28: =IF($N28>=85,"Excellent Match",IF($N28>=70,"Strong Match",IF($N28>=55,"Good Match","Weak Match"))) -> Strong Match | P28: ="Brand "&ROUND($G28,0)&"/100; Audience "&ROUND($H28,0)&"/100; Style "&ROUND($I28,0)&"/100; Personality "&ROUND($J28,0)&"/100. Campaign Fit "&ROUND($M28,0)&"/100." -> Brand 66/100; Audience 68/100; Style 80/100; Personality 100/100. Campaign Fit 81/100.
A29: =Campaign_Profile!$B$5 -> CAMP-A | B29: =Campaign_Profile!$B$6 -> BRAND-A | C29: =KOL_Database!$A$29 -> KOL-25 | D29: =KOL_Database!$B$29 -> Denny Kurniawan | E29: =KOL_Database!$D$29 -> TikTok | F29: =KOL_Database!$E$29 -> Automotive | G29: =IFERROR(INDEX(Matching_Engine!$AY$6:$AY$95,MATCH($B29&"|"&$C29,Matching_Engine!$AZ$6:$AZ$95,0)),0) -> 54 | H29: =IFERROR(INDEX(Matching_Engine!$S$6:$S$95,MATCH($B29&"|"&$C29,Matching_Engine!$AZ$6:$AZ$95,0)),0) -> 57 | I29: =IFERROR(INDEX(Matching_Engine!$W$6:$W$95,MATCH($B29&"|"&$C29,Matching_Engine!$AZ$6:$AZ$95,0)),0) -> 45 | J29: =IFERROR(INDEX(Matching_Engine!$Y$6:$Y$95,MATCH($B29&"|"&$C29,Matching_Engine!$AZ$6:$AZ$95,0)),0) -> 40 | K29: =IFERROR(INDEX(Matching_Engine!$Z$6:$Z$95,MATCH($B29&"|"&$C29,Matching_Engine!$AZ$6:$AZ$95,0)),0) -> 55 | L29: =IFERROR(INDEX(Matching_Engine!$AB$6:$AB$95,MATCH($B29&"|"&$C29,Matching_Engine!$AZ$6:$AZ$95,0)),0) -> 50 | M29: =ROUND($H29*0.3+$I29*0.3+$J29*0.25+$L29*0.15,1) -> 48.1 | N29: =ROUND($G29*0.7+$M29*0.3,1) -> 52.2 | O29: =IF($N29>=85,"Excellent Match",IF($N29>=70,"Strong Match",IF($N29>=55,"Good Match","Weak Match"))) -> Weak Match | P29: ="Brand "&ROUND($G29,0)&"/100; Audience "&ROUND($H29,0)&"/100; Style "&ROUND($I29,0)&"/100; Personality "&ROUND($J29,0)&"/100. Campaign Fit "&ROUND($M29,0)&"/100." -> Brand 54/100; Audience 57/100; Style 45/100; Personality 40/100. Campaign Fit 48/100.
A30: =Campaign_Profile!$B$5 -> CAMP-A | B30: =Campaign_Profile!$B$6 -> BRAND-A | C30: =KOL_Database!$A$30 -> KOL-26 | D30: =KOL_Database!$B$30 -> Wisnu Adi | E30: =KOL_Database!$D$30 -> Instagram | F30: =KOL_Database!$E$30 -> Automotive | G30: =IFERROR(INDEX(Matching_Engine!$AY$6:$AY$95,MATCH($B30&"|"&$C30,Matching_Engine!$AZ$6:$AZ$95,0)),0) | H30: =IFERROR(INDEX(Matching_Engine!$S$6:$S$95,MATCH($B30&"|"&$C30,Matching_Engine!$AZ$6:$AZ$95,0)),0) -> 83 | I30: =IFERROR(INDEX(Matching_Engine!$W$6:$W$95,MATCH($B30&"|"&$C30,Matching_Engine!$AZ$6:$AZ$95,0)),0) -> 80 | J30: =IFERROR(INDEX(Matching_Engine!$Y$6:$Y$95,MATCH($B30&"|"&$C30,Matching_Engine!$AZ$6:$AZ$95,0)),0) -> 70 | K30: =IFERROR(INDEX(Matching_Engine!$Z$6:$Z$95,MATCH($B30&"|"&$C30,Matching_Engine!$AZ$6:$AZ$95,0)),0) -> 90 | L30: =IFERROR(INDEX(Matching_Engine!$AB$6:$AB$95,MATCH($B30&"|"&$C30,Matching_Engine!$AZ$6:$AZ$95,0)),0) -> 70 | M30: =ROUND($H30*0.3+$I30*0.3+$J30*0.25+$L30*0.15,1) -> 76.9 | N30: =ROUND($G30*0.7+$M30*0.3,1) -> #VALUE! | O30: =IF($N30>=85,"Excellent Match",IF($N30>=70,"Strong Match",IF($N30>=55,"Good Match","Weak Match"))) -> #VALUE! | P30: ="Brand "&ROUND($G30,0)&"/100; Audience "&ROUND($H30,0)&"/100; Style "&ROUND($I30,0)&"/100; Personality "&ROUND($J30,0)&"/100. Campaign Fit "&ROUND($M30,0)&"/100." -> #VALUE!
A31: =Campaign_Profile!$B$5 -> CAMP-A | B31: =Campaign_Profile!$B$6 -> BRAND-A | C31: =KOL_Database!$A$31 -> KOL-27 | D31: =KOL_Database!$B$31 -> Laras Ayu | E31: =KOL_Database!$D$31 -> Instagram | F31: =KOL_Database!$E$31 -> Home & Living | G31: =IFERROR(INDEX(Matching_Engine!$AY$6:$AY$95,MATCH($B31&"|"&$C31,Matching_Engine!$AZ$6:$AZ$95,0)),0) -> 42 | H31: =IFERROR(INDEX(Matching_Engine!$S$6:$S$95,MATCH($B31&"|"&$C31,Matching_Engine!$AZ$6:$AZ$95,0)),0) -> 49 | I31: =IFERROR(INDEX(Matching_Engine!$W$6:$W$95,MATCH($B31&"|"&$C31,Matching_Engine!$AZ$6:$AZ$95,0)),0) -> 45 | J31: =IFERROR(INDEX(Matching_Engine!$Y$6:$Y$95,MATCH($B31&"|"&$C31,Matching_Engine!$AZ$6:$AZ$95,0)),0) -> 60 | K31: =IFERROR(INDEX(Matching_Engine!$Z$6:$Z$95,MATCH($B31&"|"&$C31,Matching_Engine!$AZ$6:$AZ$95,0)),0) -> 50 | L31: =IFERROR(INDEX(Matching_Engine!$AB$6:$AB$95,MATCH($B31&"|"&$C31,Matching_Engine!$AZ$6:$AZ$95,0)),0) -> 45 | M31: =ROUND($H31*0.3+$I31*0.3+$J31*0.25+$L31*0.15,1) -> 50 | N31: =ROUND($G31*0.7+$M31*0.3,1) -> 44.4 | O31: =IF($N31>=85,"Excellent Match",IF($N31>=70,"Strong Match",IF($N31>=55,"Good Match","Weak Match"))) -> Weak Match | P31: ="Brand "&ROUND($G31,0)&"/100; Audience "&ROUND($H31,0)&"/100; Style "&ROUND($I31,0)&"/100; Personality "&ROUND($J31,0)&"/100. Campaign Fit "&ROUND($M31,0)&"/100." -> Brand 42/100; Audience 49/100; Style 45/100; Personality 60/100. Campaign Fit 50/100.
A32: =Campaign_Profile!$B$5 -> CAMP-A | B32: =Campaign_Profile!$B$6 -> BRAND-A | C32: =KOL_Database!$A$32 -> KOL-28 | D32: =KOL_Database!$B$32 -> Tiara Nisrina | E32: =KOL_Database!$D$32 -> TikTok | F32: =KOL_Database!$E$32 -> Home & Living | G32: =IFERROR(INDEX(Matching_Engine!$AY$6:$AY$95,MATCH($B32&"|"&$C32,Matching_Engine!$AZ$6:$AZ$95,0)),0) -> 55 | H32: =IFERROR(INDEX(Matching_Engine!$S$6:$S$95,MATCH($B32&"|"&$C32,Matching_Engine!$AZ$6:$AZ$95,0)),0) -> 66 | I32: =IFERROR(INDEX(Matching_Engine!$W$6:$W$95,MATCH($B32&"|"&$C32,Matching_Engine!$AZ$6:$AZ$95,0)),0) -> 80 | J32: =IFERROR(INDEX(Matching_Engine!$Y$6:$Y$95,MATCH($B32&"|"&$C32,Matching_Engine!$AZ$6:$AZ$95,0)),0) -> 50 | K32: =IFERROR(INDEX(Matching_Engine!$Z$6:$Z$95,MATCH($B32&"|"&$C32,Matching_Engine!$AZ$6:$AZ$95,0)),0) -> 95 | L32: =IFERROR(INDEX(Matching_Engine!$AB$6:$AB$95,MATCH($B32&"|"&$C32,Matching_Engine!$AZ$6:$AZ$95,0)),0) -> 95 | M32: =ROUND($H32*0.3+$I32*0.3+$J32*0.25+$L32*0.15,1) -> 70.6 | N32: =ROUND($G32*0.7+$M32*0.3,1) -> 59.7 | O32: =IF($N32>=85,"Excellent Match",IF($N32>=70,"Strong Match",IF($N32>=55,"Good Match","Weak Match"))) -> Good Match | P32: ="Brand "&ROUND($G32,0)&"/100; Audience "&ROUND($H32,0)&"/100; Style "&ROUND($I32,0)&"/100; Personality "&ROUND($J32,0)&"/100. Campaign Fit "&ROUND($M32,0)&"/100." -> Brand 55/100; Audience 66/100; Style 80/100; Personality 50/100. Campaign Fit 71/100.
A33: =Campaign_Profile!$B$5 -> CAMP-A | B33: =Campaign_Profile!$B$6 -> BRAND-A | C33: =KOL_Database!$A$33 -> KOL-29 | D33: =KOL_Database!$B$33 -> Sekar Ayu | E33: =KOL_Database!$D$33 -> TikTok | F33: =KOL_Database!$E$33 -> Beauty | G33: =IFERROR(INDEX(Matching_Engine!$AY$6:$AY$95,MATCH($B33&"|"&$C33,Matching_Engine!$AZ$6:$AZ$95,0)),0) -> 47 | H33: =IFERROR(INDEX(Matching_Engine!$S$6:$S$95,MATCH($B33&"|"&$C33,Matching_Engine!$AZ$6:$AZ$95,0)),0) -> 49 | I33: =IFERROR(INDEX(Matching_Engine!$W$6:$W$95,MATCH($B33&"|"&$C33,Matching_Engine!$AZ$6:$AZ$95,0)),0) -> 80 | J33: =IFERROR(INDEX(Matching_Engine!$Y$6:$Y$95,MATCH($B33&"|"&$C33,Matching_Engine!$AZ$6:$AZ$95,0)),0) -> 50 | K33: =IFERROR(INDEX(Matching_Engine!$Z$6:$Z$95,MATCH($B33&"|"&$C33,Matching_Engine!$AZ$6:$AZ$95,0)),0) -> 90 | L33: =IFERROR(INDEX(Matching_Engine!$AB$6:$AB$95,MATCH($B33&"|"&$C33,Matching_Engine!$AZ$6:$AZ$95,0)),0) -> 70 | M33: =ROUND($H33*0.3+$I33*0.3+$J33*0.25+$L33*0.15,1) -> 61.7 | N33: =ROUND($G33*0.7+$M33*0.3,1) -> 51.4 | O33: =IF($N33>=85,"Excellent Match",IF($N33>=70,"Strong Match",IF($N33>=55,"Good Match","Weak Match"))) -> Weak Match | P33: ="Brand "&ROUND($G33,0)&"/100; Audience "&ROUND($H33,0)&"/100; Style "&ROUND($I33,0)&"/100; Personality "&ROUND($J33,0)&"/100. Campaign Fit "&ROUND($M33,0)&"/100." -> Brand 47/100; Audience 49/100; Style 80/100; Personality 50/100. Campaign Fit 62/100.
A34: =Campaign_Profile!$B$5 -> CAMP-A | B34: =Campaign_Profile!$B$6 -> BRAND-A | C34: =KOL_Database!$A$34 -> KOL-30 | D34: =KOL_Database!$B$34 -> Ibnu Faisal | E34: =KOL_Database!$D$34 -> Instagram | F34: =KOL_Database!$E$34 -> Finance | G34: =IFERROR(INDEX(Matching_Engine!$AY$6:$AY$95,MATCH($B34&"|"&$C34,Matching_Engine!$AZ$6:$AZ$95,0)),0) -> 82 | H34: =IFERROR(INDEX(Matching_Engine!$S$6:$S$95,MATCH($B34&"|"&$C34,Matching_Engine!$AZ$6:$AZ$95,0)),0) -> 99 | I34: =IFERROR(INDEX(Matching_Engine!$W$6:$W$95,MATCH($B34&"|"&$C34,Matching_Engine!$AZ$6:$AZ$95,0)),0) -> 80 | J34: =IFERROR(INDEX(Matching_Engine!$Y$6:$Y$95,MATCH($B34&"|"&$C34,Matching_Engine!$AZ$6:$AZ$95,0)),0) -> 70 | K34: =IFERROR(INDEX(Matching_Engine!$Z$6:$Z$95,MATCH($B34&"|"&$C34,Matching_Engine!$AZ$6:$AZ$95,0)),0) -> 80 | L34: =IFERROR(INDEX(Matching_Engine!$AB$6:$AB$95,MATCH($B34&"|"&$C34,Matching_Engine!$AZ$6:$AZ$95,0)),0) -> 75 | M34: =ROUND($H34*0.3+$I34*0.3+$J34*0.25+$L34*0.15,1) -> 82.5 | N34: =ROUND($G34*0.7+$M34*0.3,1) -> 82.2 | O34: =IF($N34>=85,"Excellent Match",IF($N34>=70,"Strong Match",IF($N34>=55,"Good Match","Weak Match"))) -> Strong Match | P34: ="Brand "&ROUND($G34,0)&"/100; Audience "&ROUND($H34,0)&"/100; Style "&ROUND($I34,0)&"/100; Personality "&ROUND($J34,0)&"/100. Campaign Fit "&ROUND($M34,0)&"/100." -> Brand 82/100; Audience 99/100; Style 80/100; Personality 70/100. Campaign Fit 83/100.
A35: =Campaign_Profile!$C$5 -> CAMP-B | B35: =Campaign_Profile!$C$6 -> BRAND-B | C35: =KOL_Database!$A$5 -> KOL-01 | D35: =KOL_Database!$B$5 -> Ardi Nugraha | E35: =KOL_Database!$D$5 -> Instagram | F35: =KOL_Database!$E$5 -> Tech | G35: =IFERROR(INDEX(Matching_Engine!$AY$6:$AY$95,MATCH($B35&"|"&$C35,Matching_Engine!$AZ$6:$AZ$95,0)),0) | H35: =IFERROR(INDEX(Matching_Engine!$S$6:$S$95,MATCH($B35&"|"&$C35,Matching_Engine!$AZ$6:$AZ$95,0)),0) -> 60 | I35: =IFERROR(INDEX(Matching_Engine!$W$6:$W$95,MATCH($B35&"|"&$C35,Matching_Engine!$AZ$6:$AZ$95,0)),0) -> 100 | J35: =IFERROR(INDEX(Matching_Engine!$Y$6:$Y$95,MATCH($B35&"|"&$C35,Matching_Engine!$AZ$6:$AZ$95,0)),0) -> 95 | K35: =IFERROR(INDEX(Matching_Engine!$Z$6:$Z$95,MATCH($B35&"|"&$C35,Matching_Engine!$AZ$6:$AZ$95,0)),0) -> 70 | L35: =IFERROR(INDEX(Matching_Engine!$AB$6:$AB$95,MATCH($B35&"|"&$C35,Matching_Engine!$AZ$6:$AZ$95,0)),0) -> 65 | M35: =ROUND($H35*0.3+$I35*0.3+$J35*0.25+$L35*0.15,1) -> 81.5 | N35: =ROUND($G35*0.7+$M35*0.3,1) -> #VALUE! | O35: =IF($N35>=85,"Excellent Match",IF($N35>=70,"Strong Match",IF($N35>=55,"Good Match","Weak Match"))) -> #VALUE! | P35: ="Brand "&ROUND($G35,0)&"/100; Audience "&ROUND($H35,0)&"/100; Style "&ROUND($I35,0)&"/100; Personality "&ROUND($J35,0)&"/100. Campaign Fit "&ROUND($M35,0)&"/100." -> #VALUE!
A36: =Campaign_Profile!$C$5 -> CAMP-B | B36: =Campaign_Profile!$C$6 -> BRAND-B | C36: =KOL_Database!$A$6 -> KOL-02 | D36: =KOL_Database!$B$6 -> Rifqi Pratama | E36: =KOL_Database!$D$6 -> TikTok | F36: =KOL_Database!$E$6 -> Tech | G36: =IFERROR(INDEX(Matching_Engine!$AY$6:$AY$95,MATCH($B36&"|"&$C36,Matching_Engine!$AZ$6:$AZ$95,0)),0) -> 45 | H36: =IFERROR(INDEX(Matching_Engine!$S$6:$S$95,MATCH($B36&"|"&$C36,Matching_Engine!$AZ$6:$AZ$95,0)),0) -> 53 | I36: =IFERROR(INDEX(Matching_Engine!$W$6:$W$95,MATCH($B36&"|"&$C36,Matching_Engine!$AZ$6:$AZ$95,0)),0) -> 80 | J36: =IFERROR(INDEX(Matching_Engine!$Y$6:$Y$95,MATCH($B36&"|"&$C36,Matching_Engine!$AZ$6:$AZ$95,0)),0) -> 55 | K36: =IFERROR(INDEX(Matching_Engine!$Z$6:$Z$95,MATCH($B36&"|"&$C36,Matching_Engine!$AZ$6:$AZ$95,0)),0) -> 65 | L36: =IFERROR(INDEX(Matching_Engine!$AB$6:$AB$95,MATCH($B36&"|"&$C36,Matching_Engine!$AZ$6:$AZ$95,0)),0) -> 55 | M36: =ROUND($H36*0.3+$I36*0.3+$J36*0.25+$L36*0.15,1) -> 61.9 | N36: =ROUND($G36*0.7+$M36*0.3,1) -> 50.1 | O36: =IF($N36>=85,"Excellent Match",IF($N36>=70,"Strong Match",IF($N36>=55,"Good Match","Weak Match"))) -> Weak Match | P36: ="Brand "&ROUND($G36,0)&"/100; Audience "&ROUND($H36,0)&"/100; Style "&ROUND($I36,0)&"/100; Personality "&ROUND($J36,0)&"/100. Campaign Fit "&ROUND($M36,0)&"/100." -> Brand 45/100; Audience 53/100; Style 80/100; Personality 55/100. Campaign Fit 62/100.
A37: =Campaign_Profile!$C$5 -> CAMP-B | B37: =Campaign_Profile!$C$6 -> BRAND-B | C37: =KOL_Database!$A$7 -> KOL-03 | D37: =KOL_Database!$B$7 -> Salsa Aulia | E37: =KOL_Database!$D$7 -> Instagram | F37: =KOL_Database!$E$7 -> Beauty | G37: =IFERROR(INDEX(Matching_Engine!$AY$6:$AY$95,MATCH($B37&"|"&$C37,Matching_Engine!$AZ$6:$AZ$95,0)),0) | H37: =IFERROR(INDEX(Matching_Engine!$S$6:$S$95,MATCH($B37&"|"&$C37,Matching_Engine!$AZ$6:$AZ$95,0)),0) -> 95 | I37: =IFERROR(INDEX(Matching_Engine!$W$6:$W$95,MATCH($B37&"|"&$C37,Matching_Engine!$AZ$6:$AZ$95,0)),0) -> 100 | J37: =IFERROR(INDEX(Matching_Engine!$Y$6:$Y$95,MATCH($B37&"|"&$C37,Matching_Engine!$AZ$6:$AZ$95,0)),0) -> 95 | K37: =IFERROR(INDEX(Matching_Engine!$Z$6:$Z$95,MATCH($B37&"|"&$C37,Matching_Engine!$AZ$6:$AZ$95,0)),0) -> 70 | L37: =IFERROR(INDEX(Matching_Engine!$AB$6:$AB$95,MATCH($B37&"|"&$C37,Matching_Engine!$AZ$6:$AZ$95,0)),0) -> 65 | M37: =ROUND($H37*0.3+$I37*0.3+$J37*0.25+$L37*0.15,1) -> 92 | N37: =ROUND($G37*0.7+$M37*0.3,1) -> #VALUE! | O37: =IF($N37>=85,"Excellent Match",IF($N37>=70,"Strong Match",IF($N37>=55,"Good Match","Weak Match"))) -> #VALUE! | P37: ="Brand "&ROUND($G37,0)&"/100; Audience "&ROUND($H37,0)&"/100; Style "&ROUND($I37,0)&"/100; Personality "&ROUND($J37,0)&"/100. Campaign Fit "&ROUND($M37,0)&"/100." -> #VALUE!
A38: =Campaign_Profile!$C$5 -> CAMP-B | B38: =Campaign_Profile!$C$6 -> BRAND-B | C38: =KOL_Database!$A$8 -> KOL-04 | D38: =KOL_Database!$B$8 -> Nadia Puspa | E38: =KOL_Database!$D$8 -> TikTok | F38: =KOL_Database!$E$8 -> Beauty | G38: =IFERROR(INDEX(Matching_Engine!$AY$6:$AY$95,MATCH($B38&"|"&$C38,Matching_Engine!$AZ$6:$AZ$95,0)),0) | H38: =IFERROR(INDEX(Matching_Engine!$S$6:$S$95,MATCH($B38&"|"&$C38,Matching_Engine!$AZ$6:$AZ$95,0)),0) -> 90 | I38: =IFERROR(INDEX(Matching_Engine!$W$6:$W$95,MATCH($B38&"|"&$C38,Matching_Engine!$AZ$6:$AZ$95,0)),0) -> 80 | J38: =IFERROR(INDEX(Matching_Engine!$Y$6:$Y$95,MATCH($B38&"|"&$C38,Matching_Engine!$AZ$6:$AZ$95,0)),0) -> 65 | K38: =IFERROR(INDEX(Matching_Engine!$Z$6:$Z$95,MATCH($B38&"|"&$C38,Matching_Engine!$AZ$6:$AZ$95,0)),0) -> 65 | L38: =IFERROR(INDEX(Matching_Engine!$AB$6:$AB$95,MATCH($B38&"|"&$C38,Matching_Engine!$AZ$6:$AZ$95,0)),0) -> 70 | M38: =ROUND($H38*0.3+$I38*0.3+$J38*0.25+$L38*0.15,1) -> 77.8 | N38: =ROUND($G38*0.7+$M38*0.3,1) -> #VALUE! | O38: =IF($N38>=85,"Excellent Match",IF($N38>=70,"Strong Match",IF($N38>=55,"Good Match","Weak Match"))) -> #VALUE! | P38: ="Brand "&ROUND($G38,0)&"/100; Audience "&ROUND($H38,0)&"/100; Style "&ROUND($I38,0)&"/100; Personality "&ROUND($J38,0)&"/100. Campaign Fit "&ROUND($M38,0)&"/100." -> #VALUE!
A39: =Campaign_Profile!$C$5 -> CAMP-B | B39: =Campaign_Profile!$C$6 -> BRAND-B | C39: =KOL_Database!$A$9 -> KOL-05 | D39: =KOL_Database!$B$9 -> Bimo Saputra | E39: =KOL_Database!$D$9 -> TikTok | F39: =KOL_Database!$E$9 -> Food | G39: =IFERROR(INDEX(Matching_Engine!$AY$6:$AY$95,MATCH($B39&"|"&$C39,Matching_Engine!$AZ$6:$AZ$95,0)),0) | H39: =IFERROR(INDEX(Matching_Engine!$S$6:$S$95,MATCH($B39&"|"&$C39,Matching_Engine!$AZ$6:$AZ$95,0)),0) -> 72 | I39: =IFERROR(INDEX(Matching_Engine!$W$6:$W$95,MATCH($B39&"|"&$C39,Matching_Engine!$AZ$6:$AZ$95,0)),0) -> 100 | J39: =IFERROR(INDEX(Matching_Engine!$Y$6:$Y$95,MATCH($B39&"|"&$C39,Matching_Engine!$AZ$6:$AZ$95,0)),0) -> 35 | K39: =IFERROR(INDEX(Matching_Engine!$Z$6:$Z$95,MATCH($B39&"|"&$C39,Matching_Engine!$AZ$6:$AZ$95,0)),0) -> 70 | L39: =IFERROR(INDEX(Matching_Engine!$AB$6:$AB$95,MATCH($B39&"|"&$C39,Matching_Engine!$AZ$6:$AZ$95,0)),0) -> 65 | M39: =ROUND($H39*0.3+$I39*0.3+$J39*0.25+$L39*0.15,1) -> 70.1 | N39: =ROUND($G39*0.7+$M39*0.3,1) -> #VALUE! | O39: =IF($N39>=85,"Excellent Match",IF($N39>=70,"Strong Match",IF($N39>=55,"Good Match","Weak Match"))) -> #VALUE! | P39: ="Brand "&ROUND($G39,0)&"/100; Audience "&ROUND($H39,0)&"/100; Style "&ROUND($I39,0)&"/100; Personality "&ROUND($J39,0)&"/100. Campaign Fit "&ROUND($M39,0)&"/100." -> #VALUE!
A40: =Campaign_Profile!$C$5 -> CAMP-B | B40: =Campaign_Profile!$C$6 -> BRAND-B | C40: =KOL_Database!$A$10 -> KOL-06 | D40: =KOL_Database!$B$10 -> Ayu Lestari | E40: =KOL_Database!$D$10 -> Instagram | F40: =KOL_Database!$E$10 -> Food | G40: =IFERROR(INDEX(Matching_Engine!$AY$6:$AY$95,MATCH($B40&"|"&$C40,Matching_Engine!$AZ$6:$AZ$95,0)),0) -> 56 | H40: =IFERROR(INDEX(Matching_Engine!$S$6:$S$95,MATCH($B40&"|"&$C40,Matching_Engine!$AZ$6:$AZ$95,0)),0) -> 69 | I40: =IFERROR(INDEX(Matching_Engine!$W$6:$W$95,MATCH($B40&"|"&$C40,Matching_Engine!$AZ$6:$AZ$95,0)),0) -> 80 | J40: =IFERROR(INDEX(Matching_Engine!$Y$6:$Y$95,MATCH($B40&"|"&$C40,Matching_Engine!$AZ$6:$AZ$95,0)),0) -> 35 | K40: =IFERROR(INDEX(Matching_Engine!$Z$6:$Z$95,MATCH($B40&"|"&$C40,Matching_Engine!$AZ$6:$AZ$95,0)),0) -> 65 | L40: =IFERROR(INDEX(Matching_Engine!$AB$6:$AB$95,MATCH($B40&"|"&$C40,Matching_Engine!$AZ$6:$AZ$95,0)),0) -> 70 | M40: =ROUND($H40*0.3+$I40*0.3+$J40*0.25+$L40*0.15,1) -> 64 | N40: =ROUND($G40*0.7+$M40*0.3,1) -> 58.4 | O40: =IF($N40>=85,"Excellent Match",IF($N40>=70,"Strong Match",IF($N40>=55,"Good Match","Weak Match"))) -> Good Match | P40: ="Brand "&ROUND($G40,0)&"/100; Audience "&ROUND($H40,0)&"/100; Style "&ROUND($I40,0)&"/100; Personality "&ROUND($J40,0)&"/100. Campaign Fit "&ROUND($M40,0)&"/100." -> Brand 56/100; Audience 69/100; Style 80/100; Personality 35/100. Campaign Fit 64/100.
A41: =Campaign_Profile!$C$5 -> CAMP-B | B41: =Campaign_Profile!$C$6 -> BRAND-B | C41: =KOL_Database!$A$11 -> KOL-07 | D41: =KOL_Database!$B$11 -> Fajar Ramadhan | E41: =KOL_Database!$D$11 -> Instagram | F41: =KOL_Database!$E$11 -> Finance | G41: =IFERROR(INDEX(Matching_Engine!$AY$6:$AY$95,MATCH($B41&"|"&$C41,Matching_Engine!$AZ$6:$AZ$95,0)),0) | H41: =IFERROR(INDEX(Matching_Engine!$S$6:$S$95,MATCH($B41&"|"&$C41,Matching_Engine!$AZ$6:$AZ$95,0)),0) -> 55 | I41: =IFERROR(INDEX(Matching_Engine!$W$6:$W$95,MATCH($B41&"|"&$C41,Matching_Engine!$AZ$6:$AZ$95,0)),0) -> 80 | J41: =IFERROR(INDEX(Matching_Engine!$Y$6:$Y$95,MATCH($B41&"|"&$C41,Matching_Engine!$AZ$6:$AZ$95,0)),0) -> 85 | K41: =IFERROR(INDEX(Matching_Engine!$Z$6:$Z$95,MATCH($B41&"|"&$C41,Matching_Engine!$AZ$6:$AZ$95,0)),0) -> 65 | L41: =IFERROR(INDEX(Matching_Engine!$AB$6:$AB$95,MATCH($B41&"|"&$C41,Matching_Engine!$AZ$6:$AZ$95,0)),0) -> 55 | M41: =ROUND($H41*0.3+$I41*0.3+$J41*0.25+$L41*0.15,1) -> 70 | N41: =ROUND($G41*0.7+$M41*0.3,1) -> #VALUE! | O41: =IF($N41>=85,"Excellent Match",IF($N41>=70,"Strong Match",IF($N41>=55,"Good Match","Weak Match"))) -> #VALUE! | P41: ="Brand "&ROUND($G41,0)&"/100; Audience "&ROUND($H41,0)&"/100; Style "&ROUND($I41,0)&"/100; Personality "&ROUND($J41,0)&"/100. Campaign Fit "&ROUND($M41,0)&"/100." -> #VALUE!
A42: =Campaign_Profile!$C$5 -> CAMP-B | B42: =Campaign_Profile!$C$6 -> BRAND-B | C42: =KOL_Database!$A$12 -> KOL-08 | D42: =KOL_Database!$B$12 -> Tania Wijaya | E42: =KOL_Database!$D$12 -> TikTok | F42: =KOL_Database!$E$12 -> Finance | G42: =IFERROR(INDEX(Matching_Engine!$AY$6:$AY$95,MATCH($B42&"|"&$C42,Matching_Engine!$AZ$6:$AZ$95,0)),0) | H42: =IFERROR(INDEX(Matching_Engine!$S$6:$S$95,MATCH($B42&"|"&$C42,Matching_Engine!$AZ$6:$AZ$95,0)),0) -> 79 | I42: =IFERROR(INDEX(Matching_Engine!$W$6:$W$95,MATCH($B42&"|"&$C42,Matching_Engine!$AZ$6:$AZ$95,0)),0) -> 80 | J42: =IFERROR(INDEX(Matching_Engine!$Y$6:$Y$95,MATCH($B42&"|"&$C42,Matching_Engine!$AZ$6:$AZ$95,0)),0) -> 55 | K42: =IFERROR(INDEX(Matching_Engine!$Z$6:$Z$95,MATCH($B42&"|"&$C42,Matching_Engine!$AZ$6:$AZ$95,0)),0) -> 65 | L42: =IFERROR(INDEX(Matching_Engine!$AB$6:$AB$95,MATCH($B42&"|"&$C42,Matching_Engine!$AZ$6:$AZ$95,0)),0) -> 55 | M42: =ROUND($H42*0.3+$I42*0.3+$J42*0.25+$L42*0.15,1) -> 69.7 | N42: =ROUND($G42*0.7+$M42*0.3,1) -> #VALUE! | O42: =IF($N42>=85,"Excellent Match",IF($N42>=70,"Strong Match",IF($N42>=55,"Good Match","Weak Match"))) -> #VALUE! | P42: ="Brand "&ROUND($G42,0)&"/100; Audience "&ROUND($H42,0)&"/100; Style "&ROUND($I42,0)&"/100; Personality "&ROUND($J42,0)&"/100. Campaign Fit "&ROUND($M42,0)&"/100." -> #VALUE!
A43: =Campaign_Profile!$C$5 -> CAMP-B | B43: =Campaign_Profile!$C$6 -> BRAND-B | C43: =KOL_Database!$A$13 -> KOL-09 | D43: =KOL_Database!$B$13 -> Gilang Prakoso | E43: =KOL_Database!$D$13 -> TikTok | F43: =KOL_Database!$E$13 -> Education | G43: =IFERROR(INDEX(Matching_Engine!$AY$6:$AY$95,MATCH($B43&"|"&$C43,Matching_Engine!$AZ$6:$AZ$95,0)),0) | H43: =IFERROR(INDEX(Matching_Engine!$S$6:$S$95,MATCH($B43&"|"&$C43,Matching_Engine!$AZ$6:$AZ$95,0)),0) -> 63 | I43: =IFERROR(INDEX(Matching_Engine!$W$6:$W$95,MATCH($B43&"|"&$C43,Matching_Engine!$AZ$6:$AZ$95,0)),0) -> 80 | J43: =IFERROR(INDEX(Matching_Engine!$Y$6:$Y$95,MATCH($B43&"|"&$C43,Matching_Engine!$AZ$6:$AZ$95,0)),0) -> 55 | K43: =IFERROR(INDEX(Matching_Engine!$Z$6:$Z$95,MATCH($B43&"|"&$C43,Matching_Engine!$AZ$6:$AZ$95,0)),0) -> 65 | L43: =IFERROR(INDEX(Matching_Engine!$AB$6:$AB$95,MATCH($B43&"|"&$C43,Matching_Engine!$AZ$6:$AZ$95,0)),0) -> 55 | M43: =ROUND($H43*0.3+$I43*0.3+$J43*0.25+$L43*0.15,1) -> 64.9 | N43: =ROUND($G43*0.7+$M43*0.3,1) -> #VALUE! | O43: =IF($N43>=85,"Excellent Match",IF($N43>=70,"Strong Match",IF($N43>=55,"Good Match","Weak Match"))) -> #VALUE! | P43: ="Brand "&ROUND($G43,0)&"/100; Audience "&ROUND($H43,0)&"/100; Style "&ROUND($I43,0)&"/100; Personality "&ROUND($J43,0)&"/100. Campaign Fit "&ROUND($M43,0)&"/100." -> #VALUE!
A44: =Campaign_Profile!$C$5 -> CAMP-B | B44: =Campaign_Profile!$C$6 -> BRAND-B | C44: =KOL_Database!$A$14 -> KOL-10 | D44: =KOL_Database!$B$14 -> Mira Handayani | E44: =KOL_Database!$D$14 -> Instagram | F44: =KOL_Database!$E$14 -> Education | G44: =IFERROR(INDEX(Matching_Engine!$AY$6:$AY$95,MATCH($B44&"|"&$C44,Matching_Engine!$AZ$6:$AZ$95,0)),0) -> 50 | H44: =IFERROR(INDEX(Matching_Engine!$S$6:$S$95,MATCH($B44&"|"&$C44,Matching_Engine!$AZ$6:$AZ$95,0)),0) -> 69 | I44: =IFERROR(INDEX(Matching_Engine!$W$6:$W$95,MATCH($B44&"|"&$C44,Matching_Engine!$AZ$6:$AZ$95,0)),0) -> 80 | J44: =IFERROR(INDEX(Matching_Engine!$Y$6:$Y$95,MATCH($B44&"|"&$C44,Matching_Engine!$AZ$6:$AZ$95,0)),0) -> 55 | K44: =IFERROR(INDEX(Matching_Engine!$Z$6:$Z$95,MATCH($B44&"|"&$C44,Matching_Engine!$AZ$6:$AZ$95,0)),0) -> 65 | L44: =IFERROR(INDEX(Matching_Engine!$AB$6:$AB$95,MATCH($B44&"|"&$C44,Matching_Engine!$AZ$6:$AZ$95,0)),0) -> 70 | M44: =ROUND($H44*0.3+$I44*0.3+$J44*0.25+$L44*0.15,1) -> 69 | N44: =ROUND($G44*0.7+$M44*0.3,1) -> 55.7 | O44: =IF($N44>=85,"Excellent Match",IF($N44>=70,"Strong Match",IF($N44>=55,"Good Match","Weak Match"))) -> Good Match | P44: ="Brand "&ROUND($G44,0)&"/100; Audience "&ROUND($H44,0)&"/100; Style "&ROUND($I44,0)&"/100; Personality "&ROUND($J44,0)&"/100. Campaign Fit "&ROUND($M44,0)&"/100." -> Brand 50/100; Audience 69/100; Style 80/100; Personality 55/100. Campaign Fit 69/100.
A45: =Campaign_Profile!$C$5 -> CAMP-B | B45: =Campaign_Profile!$C$6 -> BRAND-B | C45: =KOL_Database!$A$15 -> KOL-11 | D45: =KOL_Database!$B$15 -> Dimas Anggara | E45: =KOL_Database!$D$15 -> Instagram | F45: =KOL_Database!$E$15 -> Fitness | G45: =IFERROR(INDEX(Matching_Engine!$AY$6:$AY$95,MATCH($B45&"|"&$C45,Matching_Engine!$AZ$6:$AZ$95,0)),0) | H45: =IFERROR(INDEX(Matching_Engine!$S$6:$S$95,MATCH($B45&"|"&$C45,Matching_Engine!$AZ$6:$AZ$95,0)),0) -> 69 | I45: =IFERROR(INDEX(Matching_Engine!$W$6:$W$95,MATCH($B45&"|"&$C45,Matching_Engine!$AZ$6:$AZ$95,0)),0) -> 80 | J45: =IFERROR(INDEX(Matching_Engine!$Y$6:$Y$95,MATCH($B45&"|"&$C45,Matching_Engine!$AZ$6:$AZ$95,0)),0) -> 85 | K45: =IFERROR(INDEX(Matching_Engine!$Z$6:$Z$95,MATCH($B45&"|"&$C45,Matching_Engine!$AZ$6:$AZ$95,0)),0) -> 60 | L45: =IFERROR(INDEX(Matching_Engine!$AB$6:$AB$95,MATCH($B45&"|"&$C45,Matching_Engine!$AZ$6:$AZ$95,0)),0) -> 75 | M45: =ROUND($H45*0.3+$I45*0.3+$J45*0.25+$L45*0.15,1) -> 77.2 | N45: =ROUND($G45*0.7+$M45*0.3,1) -> #VALUE! | O45: =IF($N45>=85,"Excellent Match",IF($N45>=70,"Strong Match",IF($N45>=55,"Good Match","Weak Match"))) -> #VALUE! | P45: ="Brand "&ROUND($G45,0)&"/100; Audience "&ROUND($H45,0)&"/100; Style "&ROUND($I45,0)&"/100; Personality "&ROUND($J45,0)&"/100. Campaign Fit "&ROUND($M45,0)&"/100." -> #VALUE!
A46: =Campaign_Profile!$C$5 -> CAMP-B | B46: =Campaign_Profile!$C$6 -> BRAND-B | C46: =KOL_Database!$A$16 -> KOL-12 | D46: =KOL_Database!$B$16 -> Rani Kusuma | E46: =KOL_Database!$D$16 -> TikTok | F46: =KOL_Database!$E$16 -> Fitness | G46: =IFERROR(INDEX(Matching_Engine!$AY$6:$AY$95,MATCH($B46&"|"&$C46,Matching_Engine!$AZ$6:$AZ$95,0)),0) | H46: =IFERROR(INDEX(Matching_Engine!$S$6:$S$95,MATCH($B46&"|"&$C46,Matching_Engine!$AZ$6:$AZ$95,0)),0) -> 74 | I46: =IFERROR(INDEX(Matching_Engine!$W$6:$W$95,MATCH($B46&"|"&$C46,Matching_Engine!$AZ$6:$AZ$95,0)),0) -> 80 | J46: =IFERROR(INDEX(Matching_Engine!$Y$6:$Y$95,MATCH($B46&"|"&$C46,Matching_Engine!$AZ$6:$AZ$95,0)),0) -> 65 | K46: =IFERROR(INDEX(Matching_Engine!$Z$6:$Z$95,MATCH($B46&"|"&$C46,Matching_Engine!$AZ$6:$AZ$95,0)),0) -> 65 | L46: =IFERROR(INDEX(Matching_Engine!$AB$6:$AB$95,MATCH($B46&"|"&$C46,Matching_Engine!$AZ$6:$AZ$95,0)),0) -> 70 | M46: =ROUND($H46*0.3+$I46*0.3+$J46*0.25+$L46*0.15,1) -> 73 | N46: =ROUND($G46*0.7+$M46*0.3,1) -> #VALUE! | O46: =IF($N46>=85,"Excellent Match",IF($N46>=70,"Strong Match",IF($N46>=55,"Good Match","Weak Match"))) -> #VALUE! | P46: ="Brand "&ROUND($G46,0)&"/100; Audience "&ROUND($H46,0)&"/100; Style "&ROUND($I46,0)&"/100; Personality "&ROUND($J46,0)&"/100. Campaign Fit "&ROUND($M46,0)&"/100." -> #VALUE!
A47: =Campaign_Profile!$C$5 -> CAMP-B | B47: =Campaign_Profile!$C$6 -> BRAND-B | C47: =KOL_Database!$A$17 -> KOL-13 | D47: =KOL_Database!$B$17 -> Kevin Halim | E47: =KOL_Database!$D$17 -> Instagram | F47: =KOL_Database!$E$17 -> Fashion | G47: =IFERROR(INDEX(Matching_Engine!$AY$6:$AY$95,MATCH($B47&"|"&$C47,Matching_Engine!$AZ$6:$AZ$95,0)),0) -> 69 | H47: =IFERROR(INDEX(Matching_Engine!$S$6:$S$95,MATCH($B47&"|"&$C47,Matching_Engine!$AZ$6:$AZ$95,0)),0) -> 76 | I47: =IFERROR(INDEX(Matching_Engine!$W$6:$W$95,MATCH($B47&"|"&$C47,Matching_Engine!$AZ$6:$AZ$95,0)),0) -> 45 | J47: =IFERROR(INDEX(Matching_Engine!$Y$6:$Y$95,MATCH($B47&"|"&$C47,Matching_Engine!$AZ$6:$AZ$95,0)),0) -> 65 | K47: =IFERROR(INDEX(Matching_Engine!$Z$6:$Z$95,MATCH($B47&"|"&$C47,Matching_Engine!$AZ$6:$AZ$95,0)),0) -> 95 | L47: =IFERROR(INDEX(Matching_Engine!$AB$6:$AB$95,MATCH($B47&"|"&$C47,Matching_Engine!$AZ$6:$AZ$95,0)),0) -> 100 | M47: =ROUND($H47*0.3+$I47*0.3+$J47*0.25+$L47*0.15,1) -> 67.6 | N47: =ROUND($G47*0.7+$M47*0.3,1) -> 68.6 | O47: =IF($N47>=85,"Excellent Match",IF($N47>=70,"Strong Match",IF($N47>=55,"Good Match","Weak Match"))) -> Good Match | P47: ="Brand "&ROUND($G47,0)&"/100; Audience "&ROUND($H47,0)&"/100; Style "&ROUND($I47,0)&"/100; Personality "&ROUND($J47,0)&"/100. Campaign Fit "&ROUND($M47,0)&"/100." -> Brand 69/100; Audience 76/100; Style 45/100; Personality 65/100. Campaign Fit 68/100.
A48: =Campaign_Profile!$C$5 -> CAMP-B | B48: =Campaign_Profile!$C$6 -> BRAND-B | C48: =KOL_Database!$A$18 -> KOL-14 | D48: =KOL_Database!$B$18 -> Zahra Amelia | E48: =KOL_Database!$D$18 -> Instagram | F48: =KOL_Database!$E$18 -> Fashion | G48: =IFERROR(INDEX(Matching_Engine!$AY$6:$AY$95,MATCH($B48&"|"&$C48,Matching_Engine!$AZ$6:$AZ$95,0)),0) | H48: =IFERROR(INDEX(Matching_Engine!$S$6:$S$95,MATCH($B48&"|"&$C48,Matching_Engine!$AZ$6:$AZ$95,0)),0) -> 90 | I48: =IFERROR(INDEX(Matching_Engine!$W$6:$W$95,MATCH($B48&"|"&$C48,Matching_Engine!$AZ$6:$AZ$95,0)),0) -> 45 | J48: =IFERROR(INDEX(Matching_Engine!$Y$6:$Y$95,MATCH($B48&"|"&$C48,Matching_Engine!$AZ$6:$AZ$95,0)),0) -> 100 | K48: =IFERROR(INDEX(Matching_Engine!$Z$6:$Z$95,MATCH($B48&"|"&$C48,Matching_Engine!$AZ$6:$AZ$95,0)),0) -> 95 | L48: =IFERROR(INDEX(Matching_Engine!$AB$6:$AB$95,MATCH($B48&"|"&$C48,Matching_Engine!$AZ$6:$AZ$95,0)),0) -> 100 | M48: =ROUND($H48*0.3+$I48*0.3+$J48*0.25+$L48*0.15,1) -> 80.5 | N48: =ROUND($G48*0.7+$M48*0.3,1) -> #VALUE! | O48: =IF($N48>=85,"Excellent Match",IF($N48>=70,"Strong Match",IF($N48>=55,"Good Match","Weak Match"))) -> #VALUE! | P48: ="Brand "&ROUND($G48,0)&"/100; Audience "&ROUND($H48,0)&"/100; Style "&ROUND($I48,0)&"/100; Personality "&ROUND($J48,0)&"/100. Campaign Fit "&ROUND($M48,0)&"/100." -> #VALUE!
A49: =Campaign_Profile!$C$5 -> CAMP-B | B49: =Campaign_Profile!$C$6 -> BRAND-B | C49: =KOL_Database!$A$19 -> KOL-15 | D49: =KOL_Database!$B$19 -> Andini Rahma | E49: =KOL_Database!$D$19 -> Instagram | F49: =KOL_Database!$E$19 -> Lifestyle | G49: =IFERROR(INDEX(Matching_Engine!$AY$6:$AY$95,MATCH($B49&"|"&$C49,Matching_Engine!$AZ$6:$AZ$95,0)),0) -> 71 | H49: =IFERROR(INDEX(Matching_Engine!$S$6:$S$95,MATCH($B49&"|"&$C49,Matching_Engine!$AZ$6:$AZ$95,0)),0) -> 90 | I49: =IFERROR(INDEX(Matching_Engine!$W$6:$W$95,MATCH($B49&"|"&$C49,Matching_Engine!$AZ$6:$AZ$95,0)),0) -> 45 | J49: =IFERROR(INDEX(Matching_Engine!$Y$6:$Y$95,MATCH($B49&"|"&$C49,Matching_Engine!$AZ$6:$AZ$95,0)),0) -> 35 | K49: =IFERROR(INDEX(Matching_Engine!$Z$6:$Z$95,MATCH($B49&"|"&$C49,Matching_Engine!$AZ$6:$AZ$95,0)),0) -> 75 | L49: =IFERROR(INDEX(Matching_Engine!$AB$6:$AB$95,MATCH($B49&"|"&$C49,Matching_Engine!$AZ$6:$AZ$95,0)),0) -> 85 | M49: =ROUND($H49*0.3+$I49*0.3+$J49*0.25+$L49*0.15,1) -> 62 | N49: =ROUND($G49*0.7+$M49*0.3,1) -> 68.3 | O49: =IF($N49>=85,"Excellent Match",IF($N49>=70,"Strong Match",IF($N49>=55,"Good Match","Weak Match"))) -> Good Match | P49: ="Brand "&ROUND($G49,0)&"/100; Audience "&ROUND($H49,0)&"/100; Style "&ROUND($I49,0)&"/100; Personality "&ROUND($J49,0)&"/100. Campaign Fit "&ROUND($M49,0)&"/100." -> Brand 71/100; Audience 90/100; Style 45/100; Personality 35/100. Campaign Fit 62/100.
A50: =Campaign_Profile!$C$5 -> CAMP-B | B50: =Campaign_Profile!$C$6 -> BRAND-B | C50: =KOL_Database!$A$20 -> KOL-16 | D50: =KOL_Database!$B$20 -> Yoga Pratama | E50: =KOL_Database!$D$20 -> TikTok | F50: =KOL_Database!$E$20 -> Lifestyle | G50: =IFERROR(INDEX(Matching_Engine!$AY$6:$AY$95,MATCH($B50&"|"&$C50,Matching_Engine!$AZ$6:$AZ$95,0)),0) | H50: =IFERROR(INDEX(Matching_Engine!$S$6:$S$95,MATCH($B50&"|"&$C50,Matching_Engine!$AZ$6:$AZ$95,0)),0) -> 63 | I50: =IFERROR(INDEX(Matching_Engine!$W$6:$W$95,MATCH($B50&"|"&$C50,Matching_Engine!$AZ$6:$AZ$95,0)),0) -> 45 | J50: =IFERROR(INDEX(Matching_Engine!$Y$6:$Y$95,MATCH($B50&"|"&$C50,Matching_Engine!$AZ$6:$AZ$95,0)),0) -> 65 | K50: =IFERROR(INDEX(Matching_Engine!$Z$6:$Z$95,MATCH($B50&"|"&$C50,Matching_Engine!$AZ$6:$AZ$95,0)),0) -> 85 | L50: =IFERROR(INDEX(Matching_Engine!$AB$6:$AB$95,MATCH($B50&"|"&$C50,Matching_Engine!$AZ$6:$AZ$95,0)),0) -> 70 | M50: =ROUND($H50*0.3+$I50*0.3+$J50*0.25+$L50*0.15,1) -> 59.2 | N50: =ROUND($G50*0.7+$M50*0.3,1) -> #VALUE! | O50: =IF($N50>=85,"Excellent Match",IF($N50>=70,"Strong Match",IF($N50>=55,"Good Match","Weak Match"))) -> #VALUE! | P50: ="Brand "&ROUND($G50,0)&"/100; Audience "&ROUND($H50,0)&"/100; Style "&ROUND($I50,0)&"/100; Personality "&ROUND($J50,0)&"/100. Campaign Fit "&ROUND($M50,0)&"/100." -> #VALUE!
A51: =Campaign_Profile!$C$5 -> CAMP-B | B51: =Campaign_Profile!$C$6 -> BRAND-B | C51: =KOL_Database!$A$21 -> KOL-17 | D51: =KOL_Database!$B$21 -> Sinta Maharani | E51: =KOL_Database!$D$21 -> Instagram | F51: =KOL_Database!$E$21 -> Travel | G51: =IFERROR(INDEX(Matching_Engine!$AY$6:$AY$95,MATCH($B51&"|"&$C51,Matching_Engine!$AZ$6:$AZ$95,0)),0) | H51: =IFERROR(INDEX(Matching_Engine!$S$6:$S$95,MATCH($B51&"|"&$C51,Matching_Engine!$AZ$6:$AZ$95,0)),0) -> 79 | I51: =IFERROR(INDEX(Matching_Engine!$W$6:$W$95,MATCH($B51&"|"&$C51,Matching_Engine!$AZ$6:$AZ$95,0)),0) -> 45 | J51: =IFERROR(INDEX(Matching_Engine!$Y$6:$Y$95,MATCH($B51&"|"&$C51,Matching_Engine!$AZ$6:$AZ$95,0)),0) -> 100 | K51: =IFERROR(INDEX(Matching_Engine!$Z$6:$Z$95,MATCH($B51&"|"&$C51,Matching_Engine!$AZ$6:$AZ$95,0)),0) -> 95 | L51: =IFERROR(INDEX(Matching_Engine!$AB$6:$AB$95,MATCH($B51&"|"&$C51,Matching_Engine!$AZ$6:$AZ$95,0)),0) -> 100 | M51: =ROUND($H51*0.3+$I51*0.3+$J51*0.25+$L51*0.15,1) -> 77.2 | N51: =ROUND($G51*0.7+$M51*0.3,1) -> #VALUE! | O51: =IF($N51>=85,"Excellent Match",IF($N51>=70,"Strong Match",IF($N51>=55,"Good Match","Weak Match"))) -> #VALUE! | P51: ="Brand "&ROUND($G51,0)&"/100; Audience "&ROUND($H51,0)&"/100; Style "&ROUND($I51,0)&"/100; Personality "&ROUND($J51,0)&"/100. Campaign Fit "&ROUND($M51,0)&"/100." -> #VALUE!
A52: =Campaign_Profile!$C$5 -> CAMP-B | B52: =Campaign_Profile!$C$6 -> BRAND-B | C52: =KOL_Database!$A$22 -> KOL-18 | D52: =KOL_Database!$B$22 -> Reza Fadillah | E52: =KOL_Database!$D$22 -> TikTok | F52: =KOL_Database!$E$22 -> Travel | G52: =IFERROR(INDEX(Matching_Engine!$AY$6:$AY$95,MATCH($B52&"|"&$C52,Matching_Engine!$AZ$6:$AZ$95,0)),0) -> 56 | H52: =IFERROR(INDEX(Matching_Engine!$S$6:$S$95,MATCH($B52&"|"&$C52,Matching_Engine!$AZ$6:$AZ$95,0)),0) -> 66 | I52: =IFERROR(INDEX(Matching_Engine!$W$6:$W$95,MATCH($B52&"|"&$C52,Matching_Engine!$AZ$6:$AZ$95,0)),0) -> 45 | J52: =IFERROR(INDEX(Matching_Engine!$Y$6:$Y$95,MATCH($B52&"|"&$C52,Matching_Engine!$AZ$6:$AZ$95,0)),0) -> 25 | K52: =IFERROR(INDEX(Matching_Engine!$Z$6:$Z$95,MATCH($B52&"|"&$C52,Matching_Engine!$AZ$6:$AZ$95,0)),0) -> 75 | L52: =IFERROR(INDEX(Matching_Engine!$AB$6:$AB$95,MATCH($B52&"|"&$C52,Matching_Engine!$AZ$6:$AZ$95,0)),0) -> 85 | M52: =ROUND($H52*0.3+$I52*0.3+$J52*0.25+$L52*0.15,1) -> 52.3 | N52: =ROUND($G52*0.7+$M52*0.3,1) -> 54.9 | O52: =IF($N52>=85,"Excellent Match",IF($N52>=70,"Strong Match",IF($N52>=55,"Good Match","Weak Match"))) -> Weak Match | P52: ="Brand "&ROUND($G52,0)&"/100; Audience "&ROUND($H52,0)&"/100; Style "&ROUND($I52,0)&"/100; Personality "&ROUND($J52,0)&"/100. Campaign Fit "&ROUND($M52,0)&"/100." -> Brand 56/100; Audience 66/100; Style 45/100; Personality 25/100. Campaign Fit 52/100.
A53: =Campaign_Profile!$C$5 -> CAMP-B | B53: =Campaign_Profile!$C$6 -> BRAND-B | C53: =KOL_Database!$A$23 -> KOL-19 | D53: =KOL_Database!$B$23 -> Putri Amanda | E53: =KOL_Database!$D$23 -> Instagram | F53: =KOL_Database!$E$23 -> Parenting | G53: =IFERROR(INDEX(Matching_Engine!$AY$6:$AY$95,MATCH($B53&"|"&$C53,Matching_Engine!$AZ$6:$AZ$95,0)),0) | H53: =IFERROR(INDEX(Matching_Engine!$S$6:$S$95,MATCH($B53&"|"&$C53,Matching_Engine!$AZ$6:$AZ$95,0)),0) -> 74 | I53: =IFERROR(INDEX(Matching_Engine!$W$6:$W$95,MATCH($B53&"|"&$C53,Matching_Engine!$AZ$6:$AZ$95,0)),0) -> 45 | J53: =IFERROR(INDEX(Matching_Engine!$Y$6:$Y$95,MATCH($B53&"|"&$C53,Matching_Engine!$AZ$6:$AZ$95,0)),0) -> 35 | K53: =IFERROR(INDEX(Matching_Engine!$Z$6:$Z$95,MATCH($B53&"|"&$C53,Matching_Engine!$AZ$6:$AZ$95,0)),0) -> 85 | L53: =IFERROR(INDEX(Matching_Engine!$AB$6:$AB$95,MATCH($B53&"|"&$C53,Matching_Engine!$AZ$6:$AZ$95,0)),0) -> 70 | M53: =ROUND($H53*0.3+$I53*0.3+$J53*0.25+$L53*0.15,1) -> 55 | N53: =ROUND($G53*0.7+$M53*0.3,1) -> #VALUE! | O53: =IF($N53>=85,"Excellent Match",IF($N53>=70,"Strong Match",IF($N53>=55,"Good Match","Weak Match"))) -> #VALUE! | P53: ="Brand "&ROUND($G53,0)&"/100; Audience "&ROUND($H53,0)&"/100; Style "&ROUND($I53,0)&"/100; Personality "&ROUND($J53,0)&"/100. Campaign Fit "&ROUND($M53,0)&"/100." -> #VALUE!
A54: =Campaign_Profile!$C$5 -> CAMP-B | B54: =Campaign_Profile!$C$6 -> BRAND-B | C54: =KOL_Database!$A$24 -> KOL-20 | D54: =KOL_Database!$B$24 -> Hendra Wijoyo | E54: =KOL_Database!$D$24 -> TikTok | F54: =KOL_Database!$E$24 -> Parenting | G54: =IFERROR(INDEX(Matching_Engine!$AY$6:$AY$95,MATCH($B54&"|"&$C54,Matching_Engine!$AZ$6:$AZ$95,0)),0) -> 52 | H54: =IFERROR(INDEX(Matching_Engine!$S$6:$S$95,MATCH($B54&"|"&$C54,Matching_Engine!$AZ$6:$AZ$95,0)),0) -> 58 | I54: =IFERROR(INDEX(Matching_Engine!$W$6:$W$95,MATCH($B54&"|"&$C54,Matching_Engine!$AZ$6:$AZ$95,0)),0) -> 45 | J54: =IFERROR(INDEX(Matching_Engine!$Y$6:$Y$95,MATCH($B54&"|"&$C54,Matching_Engine!$AZ$6:$AZ$95,0)),0) -> 20 | K54: =IFERROR(INDEX(Matching_Engine!$Z$6:$Z$95,MATCH($B54&"|"&$C54,Matching_Engine!$AZ$6:$AZ$95,0)),0) -> 60 | L54: =IFERROR(INDEX(Matching_Engine!$AB$6:$AB$95,MATCH($B54&"|"&$C54,Matching_Engine!$AZ$6:$AZ$95,0)),0) -> 70 | M54: =ROUND($H54*0.3+$I54*0.3+$J54*0.25+$L54*0.15,1) -> 46.4 | N54: =ROUND($G54*0.7+$M54*0.3,1) -> 50.3 | O54: =IF($N54>=85,"Excellent Match",IF($N54>=70,"Strong Match",IF($N54>=55,"Good Match","Weak Match"))) -> Weak Match | P54: ="Brand "&ROUND($G54,0)&"/100; Audience "&ROUND($H54,0)&"/100; Style "&ROUND($I54,0)&"/100; Personality "&ROUND($J54,0)&"/100. Campaign Fit "&ROUND($M54,0)&"/100." -> Brand 52/100; Audience 58/100; Style 45/100; Personality 20/100. Campaign Fit 46/100.
A55: =Campaign_Profile!$C$5 -> CAMP-B | B55: =Campaign_Profile!$C$6 -> BRAND-B | C55: =KOL_Database!$A$25 -> KOL-21 | D55: =KOL_Database!$B$25 -> Bagas Setiawan | E55: =KOL_Database!$D$25 -> TikTok | F55: =KOL_Database!$E$25 -> Entertainment | G55: =IFERROR(INDEX(Matching_Engine!$AY$6:$AY$95,MATCH($B55&"|"&$C55,Matching_Engine!$AZ$6:$AZ$95,0)),0) | H55: =IFERROR(INDEX(Matching_Engine!$S$6:$S$95,MATCH($B55&"|"&$C55,Matching_Engine!$AZ$6:$AZ$95,0)),0) -> 69 | I55: =IFERROR(INDEX(Matching_Engine!$W$6:$W$95,MATCH($B55&"|"&$C55,Matching_Engine!$AZ$6:$AZ$95,0)),0) -> 45 | J55: =IFERROR(INDEX(Matching_Engine!$Y$6:$Y$95,MATCH($B55&"|"&$C55,Matching_Engine!$AZ$6:$AZ$95,0)),0) -> 20 | K55: =IFERROR(INDEX(Matching_Engine!$Z$6:$Z$95,MATCH($B55&"|"&$C55,Matching_Engine!$AZ$6:$AZ$95,0)),0) -> 35 | L55: =IFERROR(INDEX(Matching_Engine!$AB$6:$AB$95,MATCH($B55&"|"&$C55,Matching_Engine!$AZ$6:$AZ$95,0)),0) -> 55 | M55: =ROUND($H55*0.3+$I55*0.3+$J55*0.25+$L55*0.15,1) -> 47.5 | N55: =ROUND($G55*0.7+$M55*0.3,1) -> #VALUE! | O55: =IF($N55>=85,"Excellent Match",IF($N55>=70,"Strong Match",IF($N55>=55,"Good Match","Weak Match"))) -> #VALUE! | P55: ="Brand "&ROUND($G55,0)&"/100; Audience "&ROUND($H55,0)&"/100; Style "&ROUND($I55,0)&"/100; Personality "&ROUND($J55,0)&"/100. Campaign Fit "&ROUND($M55,0)&"/100." -> #VALUE!
A56: =Campaign_Profile!$C$5 -> CAMP-B | B56: =Campaign_Profile!$C$6 -> BRAND-B | C56: =KOL_Database!$A$26 -> KOL-22 | D56: =KOL_Database!$B$26 -> Nabila Kirana | E56: =KOL_Database!$D$26 -> Instagram | F56: =KOL_Database!$E$26 -> Entertainment | G56: =IFERROR(INDEX(Matching_Engine!$AY$6:$AY$95,MATCH($B56&"|"&$C56,Matching_Engine!$AZ$6:$AZ$95,0)),0) | H56: =IFERROR(INDEX(Matching_Engine!$S$6:$S$95,MATCH($B56&"|"&$C56,Matching_Engine!$AZ$6:$AZ$95,0)),0) -> 90 | I56: =IFERROR(INDEX(Matching_Engine!$W$6:$W$95,MATCH($B56&"|"&$C56,Matching_Engine!$AZ$6:$AZ$95,0)),0) -> 45 | J56: =IFERROR(INDEX(Matching_Engine!$Y$6:$Y$95,MATCH($B56&"|"&$C56,Matching_Engine!$AZ$6:$AZ$95,0)),0) -> 65 | K56: =IFERROR(INDEX(Matching_Engine!$Z$6:$Z$95,MATCH($B56&"|"&$C56,Matching_Engine!$AZ$6:$AZ$95,0)),0) -> 95 | L56: =IFERROR(INDEX(Matching_Engine!$AB$6:$AB$95,MATCH($B56&"|"&$C56,Matching_Engine!$AZ$6:$AZ$95,0)),0) -> 100 | M56: =ROUND($H56*0.3+$I56*0.3+$J56*0.25+$L56*0.15,1) -> 71.8 | N56: =ROUND($G56*0.7+$M56*0.3,1) -> #VALUE! | O56: =IF($N56>=85,"Excellent Match",IF($N56>=70,"Strong Match",IF($N56>=55,"Good Match","Weak Match"))) -> #VALUE! | P56: ="Brand "&ROUND($G56,0)&"/100; Audience "&ROUND($H56,0)&"/100; Style "&ROUND($I56,0)&"/100; Personality "&ROUND($J56,0)&"/100. Campaign Fit "&ROUND($M56,0)&"/100." -> #VALUE!
A57: =Campaign_Profile!$C$5 -> CAMP-B | B57: =Campaign_Profile!$C$6 -> BRAND-B | C57: =KOL_Database!$A$27 -> KOL-23 | D57: =KOL_Database!$B$27 -> Arya Mahendra | E57: =KOL_Database!$D$27 -> TikTok | F57: =KOL_Database!$E$27 -> Gaming | G57: =IFERROR(INDEX(Matching_Engine!$AY$6:$AY$95,MATCH($B57&"|"&$C57,Matching_Engine!$AZ$6:$AZ$95,0)),0) | H57: =IFERROR(INDEX(Matching_Engine!$S$6:$S$95,MATCH($B57&"|"&$C57,Matching_Engine!$AZ$6:$AZ$95,0)),0) -> 61 | I57: =IFERROR(INDEX(Matching_Engine!$W$6:$W$95,MATCH($B57&"|"&$C57,Matching_Engine!$AZ$6:$AZ$95,0)),0) -> 45 | J57: =IFERROR(INDEX(Matching_Engine!$Y$6:$Y$95,MATCH($B57&"|"&$C57,Matching_Engine!$AZ$6:$AZ$95,0)),0) -> 30 | K57: =IFERROR(INDEX(Matching_Engine!$Z$6:$Z$95,MATCH($B57&"|"&$C57,Matching_Engine!$AZ$6:$AZ$95,0)),0) -> 60 | L57: =IFERROR(INDEX(Matching_Engine!$AB$6:$AB$95,MATCH($B57&"|"&$C57,Matching_Engine!$AZ$6:$AZ$95,0)),0) -> 70 | M57: =ROUND($H57*0.3+$I57*0.3+$J57*0.25+$L57*0.15,1) -> 49.8 | N57: =ROUND($G57*0.7+$M57*0.3,1) -> #VALUE! | O57: =IF($N57>=85,"Excellent Match",IF($N57>=70,"Strong Match",IF($N57>=55,"Good Match","Weak Match"))) -> #VALUE! | P57: ="Brand "&ROUND($G57,0)&"/100; Audience "&ROUND($H57,0)&"/100; Style "&ROUND($I57,0)&"/100; Personality "&ROUND($J57,0)&"/100. Campaign Fit "&ROUND($M57,0)&"/100." -> #VALUE!
A58: =Campaign_Profile!$C$5 -> CAMP-B | B58: =Campaign_Profile!$C$6 -> BRAND-B | C58: =KOL_Database!$A$28 -> KOL-24 | D58: =KOL_Database!$B$28 -> Rio Saputra | E58: =KOL_Database!$D$28 -> Instagram | F58: =KOL_Database!$E$28 -> Gaming | G58: =IFERROR(INDEX(Matching_Engine!$AY$6:$AY$95,MATCH($B58&"|"&$C58,Matching_Engine!$AZ$6:$AZ$95,0)),0) -> 49 | H58: =IFERROR(INDEX(Matching_Engine!$S$6:$S$95,MATCH($B58&"|"&$C58,Matching_Engine!$AZ$6:$AZ$95,0)),0) -> 61 | I58: =IFERROR(INDEX(Matching_Engine!$W$6:$W$95,MATCH($B58&"|"&$C58,Matching_Engine!$AZ$6:$AZ$95,0)),0) -> 80 | J58: =IFERROR(INDEX(Matching_Engine!$Y$6:$Y$95,MATCH($B58&"|"&$C58,Matching_Engine!$AZ$6:$AZ$95,0)),0) -> 50 | K58: =IFERROR(INDEX(Matching_Engine!$Z$6:$Z$95,MATCH($B58&"|"&$C58,Matching_Engine!$AZ$6:$AZ$95,0)),0) -> 60 | L58: =IFERROR(INDEX(Matching_Engine!$AB$6:$AB$95,MATCH($B58&"|"&$C58,Matching_Engine!$AZ$6:$AZ$95,0)),0) -> 75 | M58: =ROUND($H58*0.3+$I58*0.3+$J58*0.25+$L58*0.15,1) -> 66.1 | N58: =ROUND($G58*0.7+$M58*0.3,1) -> 54.1 | O58: =IF($N58>=85,"Excellent Match",IF($N58>=70,"Strong Match",IF($N58>=55,"Good Match","Weak Match"))) -> Weak Match | P58: ="Brand "&ROUND($G58,0)&"/100; Audience "&ROUND($H58,0)&"/100; Style "&ROUND($I58,0)&"/100; Personality "&ROUND($J58,0)&"/100. Campaign Fit "&ROUND($M58,0)&"/100." -> Brand 49/100; Audience 61/100; Style 80/100; Personality 50/100. Campaign Fit 66/100.
A59: =Campaign_Profile!$C$5 -> CAMP-B | B59: =Campaign_Profile!$C$6 -> BRAND-B | C59: =KOL_Database!$A$29 -> KOL-25 | D59: =KOL_Database!$B$29 -> Denny Kurniawan | E59: =KOL_Database!$D$29 -> TikTok | F59: =KOL_Database!$E$29 -> Automotive | G59: =IFERROR(INDEX(Matching_Engine!$AY$6:$AY$95,MATCH($B59&"|"&$C59,Matching_Engine!$AZ$6:$AZ$95,0)),0) | H59: =IFERROR(INDEX(Matching_Engine!$S$6:$S$95,MATCH($B59&"|"&$C59,Matching_Engine!$AZ$6:$AZ$95,0)),0) -> 56 | I59: =IFERROR(INDEX(Matching_Engine!$W$6:$W$95,MATCH($B59&"|"&$C59,Matching_Engine!$AZ$6:$AZ$95,0)),0) -> 45 | J59: =IFERROR(INDEX(Matching_Engine!$Y$6:$Y$95,MATCH($B59&"|"&$C59,Matching_Engine!$AZ$6:$AZ$95,0)),0) -> 25 | K59: =IFERROR(INDEX(Matching_Engine!$Z$6:$Z$95,MATCH($B59&"|"&$C59,Matching_Engine!$AZ$6:$AZ$95,0)),0) -> 75 | L59: =IFERROR(INDEX(Matching_Engine!$AB$6:$AB$95,MATCH($B59&"|"&$C59,Matching_Engine!$AZ$6:$AZ$95,0)),0) -> 85 | M59: =ROUND($H59*0.3+$I59*0.3+$J59*0.25+$L59*0.15,1) -> 49.3 | N59: =ROUND($G59*0.7+$M59*0.3,1) -> #VALUE! | O59: =IF($N59>=85,"Excellent Match",IF($N59>=70,"Strong Match",IF($N59>=55,"Good Match","Weak Match"))) -> #VALUE! | P59: ="Brand "&ROUND($G59,0)&"/100; Audience "&ROUND($H59,0)&"/100; Style "&ROUND($I59,0)&"/100; Personality "&ROUND($J59,0)&"/100. Campaign Fit "&ROUND($M59,0)&"/100." -> #VALUE!
A60: =Campaign_Profile!$C$5 -> CAMP-B | B60: =Campaign_Profile!$C$6 -> BRAND-B | C60: =KOL_Database!$A$30 -> KOL-26 | D60: =KOL_Database!$B$30 -> Wisnu Adi | E60: =KOL_Database!$D$30 -> Instagram | F60: =KOL_Database!$E$30 -> Automotive | G60: =IFERROR(INDEX(Matching_Engine!$AY$6:$AY$95,MATCH($B60&"|"&$C60,Matching_Engine!$AZ$6:$AZ$95,0)),0) | H60: =IFERROR(INDEX(Matching_Engine!$S$6:$S$95,MATCH($B60&"|"&$C60,Matching_Engine!$AZ$6:$AZ$95,0)),0) -> 54 | I60: =IFERROR(INDEX(Matching_Engine!$W$6:$W$95,MATCH($B60&"|"&$C60,Matching_Engine!$AZ$6:$AZ$95,0)),0) -> 100 | J60: =IFERROR(INDEX(Matching_Engine!$Y$6:$Y$95,MATCH($B60&"|"&$C60,Matching_Engine!$AZ$6:$AZ$95,0)),0) -> 85 | K60: =IFERROR(INDEX(Matching_Engine!$Z$6:$Z$95,MATCH($B60&"|"&$C60,Matching_Engine!$AZ$6:$AZ$95,0)),0) -> 70 | L60: =IFERROR(INDEX(Matching_Engine!$AB$6:$AB$95,MATCH($B60&"|"&$C60,Matching_Engine!$AZ$6:$AZ$95,0)),0) -> 65 | M60: =ROUND($H60*0.3+$I60*0.3+$J60*0.25+$L60*0.15,1) -> 77.2 | N60: =ROUND($G60*0.7+$M60*0.3,1) -> #VALUE! | O60: =IF($N60>=85,"Excellent Match",IF($N60>=70,"Strong Match",IF($N60>=55,"Good Match","Weak Match"))) -> #VALUE! | P60: ="Brand "&ROUND($G60,0)&"/100; Audience "&ROUND($H60,0)&"/100; Style "&ROUND($I60,0)&"/100; Personality "&ROUND($J60,0)&"/100. Campaign Fit "&ROUND($M60,0)&"/100." -> #VALUE!
A61: =Campaign_Profile!$C$5 -> CAMP-B | B61: =Campaign_Profile!$C$6 -> BRAND-B | C61: =KOL_Database!$A$31 -> KOL-27 | D61: =KOL_Database!$B$31 -> Laras Ayu | E61: =KOL_Database!$D$31 -> Instagram | F61: =KOL_Database!$E$31 -> Home & Living | G61: =IFERROR(INDEX(Matching_Engine!$AY$6:$AY$95,MATCH($B61&"|"&$C61,Matching_Engine!$AZ$6:$AZ$95,0)),0) -> 62 | H61: =IFERROR(INDEX(Matching_Engine!$S$6:$S$95,MATCH($B61&"|"&$C61,Matching_Engine!$AZ$6:$AZ$95,0)),0) -> 79 | I61: =IFERROR(INDEX(Matching_Engine!$W$6:$W$95,MATCH($B61&"|"&$C61,Matching_Engine!$AZ$6:$AZ$95,0)),0) -> 45 | J61: =IFERROR(INDEX(Matching_Engine!$Y$6:$Y$95,MATCH($B61&"|"&$C61,Matching_Engine!$AZ$6:$AZ$95,0)),0) -> 100 | K61: =IFERROR(INDEX(Matching_Engine!$Z$6:$Z$95,MATCH($B61&"|"&$C61,Matching_Engine!$AZ$6:$AZ$95,0)),0) -> 95 | L61: =IFERROR(INDEX(Matching_Engine!$AB$6:$AB$95,MATCH($B61&"|"&$C61,Matching_Engine!$AZ$6:$AZ$95,0)),0) -> 100 | M61: =ROUND($H61*0.3+$I61*0.3+$J61*0.25+$L61*0.15,1) -> 77.2 | N61: =ROUND($G61*0.7+$M61*0.3,1) -> 66.6 | O61: =IF($N61>=85,"Excellent Match",IF($N61>=70,"Strong Match",IF($N61>=55,"Good Match","Weak Match"))) -> Good Match | P61: ="Brand "&ROUND($G61,0)&"/100; Audience "&ROUND($H61,0)&"/100; Style "&ROUND($I61,0)&"/100; Personality "&ROUND($J61,0)&"/100. Campaign Fit "&ROUND($M61,0)&"/100." -> Brand 62/100; Audience 79/100; Style 45/100; Personality 100/100. Campaign Fit 77/100.
A62: =Campaign_Profile!$C$5 -> CAMP-B | B62: =Campaign_Profile!$C$6 -> BRAND-B | C62: =KOL_Database!$A$32 -> KOL-28 | D62: =KOL_Database!$B$32 -> Tiara Nisrina | E62: =KOL_Database!$D$32 -> TikTok | F62: =KOL_Database!$E$32 -> Home & Living | G62: =IFERROR(INDEX(Matching_Engine!$AY$6:$AY$95,MATCH($B62&"|"&$C62,Matching_Engine!$AZ$6:$AZ$95,0)),0) | H62: =IFERROR(INDEX(Matching_Engine!$S$6:$S$95,MATCH($B62&"|"&$C62,Matching_Engine!$AZ$6:$AZ$95,0)),0) -> 79 | I62: =IFERROR(INDEX(Matching_Engine!$W$6:$W$95,MATCH($B62&"|"&$C62,Matching_Engine!$AZ$6:$AZ$95,0)),0) -> 80 | J62: =IFERROR(INDEX(Matching_Engine!$Y$6:$Y$95,MATCH($B62&"|"&$C62,Matching_Engine!$AZ$6:$AZ$95,0)),0) -> 35 | K62: =IFERROR(INDEX(Matching_Engine!$Z$6:$Z$95,MATCH($B62&"|"&$C62,Matching_Engine!$AZ$6:$AZ$95,0)),0) -> 65 | L62: =IFERROR(INDEX(Matching_Engine!$AB$6:$AB$95,MATCH($B62&"|"&$C62,Matching_Engine!$AZ$6:$AZ$95,0)),0) -> 70 | M62: =ROUND($H62*0.3+$I62*0.3+$J62*0.25+$L62*0.15,1) -> 67 | N62: =ROUND($G62*0.7+$M62*0.3,1) -> #VALUE! | O62: =IF($N62>=85,"Excellent Match",IF($N62>=70,"Strong Match",IF($N62>=55,"Good Match","Weak Match"))) -> #VALUE! | P62: ="Brand "&ROUND($G62,0)&"/100; Audience "&ROUND($H62,0)&"/100; Style "&ROUND($I62,0)&"/100; Personality "&ROUND($J62,0)&"/100. Campaign Fit "&ROUND($M62,0)&"/100." -> #VALUE!
A63: =Campaign_Profile!$C$5 -> CAMP-B | B63: =Campaign_Profile!$C$6 -> BRAND-B | C63: =KOL_Database!$A$33 -> KOL-29 | D63: =KOL_Database!$B$33 -> Sekar Ayu | E63: =KOL_Database!$D$33 -> TikTok | F63: =KOL_Database!$E$33 -> Beauty | G63: =IFERROR(INDEX(Matching_Engine!$AY$6:$AY$95,MATCH($B63&"|"&$C63,Matching_Engine!$AZ$6:$AZ$95,0)),0) -> 91 | H63: =IFERROR(INDEX(Matching_Engine!$S$6:$S$95,MATCH($B63&"|"&$C63,Matching_Engine!$AZ$6:$AZ$95,0)),0) -> 90 | I63: =IFERROR(INDEX(Matching_Engine!$W$6:$W$95,MATCH($B63&"|"&$C63,Matching_Engine!$AZ$6:$AZ$95,0)),0) -> 100 | J63: =IFERROR(INDEX(Matching_Engine!$Y$6:$Y$95,MATCH($B63&"|"&$C63,Matching_Engine!$AZ$6:$AZ$95,0)),0) -> 35 | K63: =IFERROR(INDEX(Matching_Engine!$Z$6:$Z$95,MATCH($B63&"|"&$C63,Matching_Engine!$AZ$6:$AZ$95,0)),0) -> 70 | L63: =IFERROR(INDEX(Matching_Engine!$AB$6:$AB$95,MATCH($B63&"|"&$C63,Matching_Engine!$AZ$6:$AZ$95,0)),0) -> 65 | M63: =ROUND($H63*0.3+$I63*0.3+$J63*0.25+$L63*0.15,1) -> 75.5 | N63: =ROUND($G63*0.7+$M63*0.3,1) -> 86.4 | O63: =IF($N63>=85,"Excellent Match",IF($N63>=70,"Strong Match",IF($N63>=55,"Good Match","Weak Match"))) -> Excellent Match | P63: ="Brand "&ROUND($G63,0)&"/100; Audience "&ROUND($H63,0)&"/100; Style "&ROUND($I63,0)&"/100; Personality "&ROUND($J63,0)&"/100. Campaign Fit "&ROUND($M63,0)&"/100." -> Brand 91/100; Audience 90/100; Style 100/100; Personality 35/100. Campaign Fit 76/100.
A64: =Campaign_Profile!$C$5 -> CAMP-B | B64: =Campaign_Profile!$C$6 -> BRAND-B | C64: =KOL_Database!$A$34 -> KOL-30 | D64: =KOL_Database!$B$34 -> Ibnu Faisal | E64: =KOL_Database!$D$34 -> Instagram | F64: =KOL_Database!$E$34 -> Finance | G64: =IFERROR(INDEX(Matching_Engine!$AY$6:$AY$95,MATCH($B64&"|"&$C64,Matching_Engine!$AZ$6:$AZ$95,0)),0) | H64: =IFERROR(INDEX(Matching_Engine!$S$6:$S$95,MATCH($B64&"|"&$C64,Matching_Engine!$AZ$6:$AZ$95,0)),0) -> 50 | I64: =IFERROR(INDEX(Matching_Engine!$W$6:$W$95,MATCH($B64&"|"&$C64,Matching_Engine!$AZ$6:$AZ$95,0)),0) -> 80 | J64: =IFERROR(INDEX(Matching_Engine!$Y$6:$Y$95,MATCH($B64&"|"&$C64,Matching_Engine!$AZ$6:$AZ$95,0)),0) -> 85 | K64: =IFERROR(INDEX(Matching_Engine!$Z$6:$Z$95,MATCH($B64&"|"&$C64,Matching_Engine!$AZ$6:$AZ$95,0)),0) -> 60 | L64: =IFERROR(INDEX(Matching_Engine!$AB$6:$AB$95,MATCH($B64&"|"&$C64,Matching_Engine!$AZ$6:$AZ$95,0)),0) -> 50 | M64: =ROUND($H64*0.3+$I64*0.3+$J64*0.25+$L64*0.15,1) -> 67.8 | N64: =ROUND($G64*0.7+$M64*0.3,1) -> #VALUE! | O64: =IF($N64>=85,"Excellent Match",IF($N64>=70,"Strong Match",IF($N64>=55,"Good Match","Weak Match"))) -> #VALUE! | P64: ="Brand "&ROUND($G64,0)&"/100; Audience "&ROUND($H64,0)&"/100; Style "&ROUND($I64,0)&"/100; Personality "&ROUND($J64,0)&"/100. Campaign Fit "&ROUND($M64,0)&"/100." -> #VALUE!
A65: =Campaign_Profile!$D$5 -> CAMP-C | B65: =Campaign_Profile!$D$6 -> BRAND-C | C65: =KOL_Database!$A$5 -> KOL-01 | D65: =KOL_Database!$B$5 -> Ardi Nugraha | E65: =KOL_Database!$D$5 -> Instagram | F65: =KOL_Database!$E$5 -> Tech | G65: =IFERROR(INDEX(Matching_Engine!$AY$6:$AY$95,MATCH($B65&"|"&$C65,Matching_Engine!$AZ$6:$AZ$95,0)),0) | H65: =IFERROR(INDEX(Matching_Engine!$S$6:$S$95,MATCH($B65&"|"&$C65,Matching_Engine!$AZ$6:$AZ$95,0)),0) -> 67 | I65: =IFERROR(INDEX(Matching_Engine!$W$6:$W$95,MATCH($B65&"|"&$C65,Matching_Engine!$AZ$6:$AZ$95,0)),0) -> 45 | J65: =IFERROR(INDEX(Matching_Engine!$Y$6:$Y$95,MATCH($B65&"|"&$C65,Matching_Engine!$AZ$6:$AZ$95,0)),0) -> 60 | K65: =IFERROR(INDEX(Matching_Engine!$Z$6:$Z$95,MATCH($B65&"|"&$C65,Matching_Engine!$AZ$6:$AZ$95,0)),0) -> 65 | L65: =IFERROR(INDEX(Matching_Engine!$AB$6:$AB$95,MATCH($B65&"|"&$C65,Matching_Engine!$AZ$6:$AZ$95,0)),0) -> 60 | M65: =ROUND($H65*0.3+$I65*0.3+$J65*0.25+$L65*0.15,1) -> 57.6 | N65: =ROUND($G65*0.7+$M65*0.3,1) -> #VALUE! | O65: =IF($N65>=85,"Excellent Match",IF($N65>=70,"Strong Match",IF($N65>=55,"Good Match","Weak Match"))) -> #VALUE! | P65: ="Brand "&ROUND($G65,0)&"/100; Audience "&ROUND($H65,0)&"/100; Style "&ROUND($I65,0)&"/100; Personality "&ROUND($J65,0)&"/100. Campaign Fit "&ROUND($M65,0)&"/100." -> #VALUE!
A66: =Campaign_Profile!$D$5 -> CAMP-C | B66: =Campaign_Profile!$D$6 -> BRAND-C | C66: =KOL_Database!$A$6 -> KOL-02 | D66: =KOL_Database!$B$6 -> Rifqi Pratama | E66: =KOL_Database!$D$6 -> TikTok | F66: =KOL_Database!$E$6 -> Tech | G66: =IFERROR(INDEX(Matching_Engine!$AY$6:$AY$95,MATCH($B66&"|"&$C66,Matching_Engine!$AZ$6:$AZ$95,0)),0) -> 47 | H66: =IFERROR(INDEX(Matching_Engine!$S$6:$S$95,MATCH($B66&"|"&$C66,Matching_Engine!$AZ$6:$AZ$95,0)),0) -> 64 | I66: =IFERROR(INDEX(Matching_Engine!$W$6:$W$95,MATCH($B66&"|"&$C66,Matching_Engine!$AZ$6:$AZ$95,0)),0) -> 45 | J66: =IFERROR(INDEX(Matching_Engine!$Y$6:$Y$95,MATCH($B66&"|"&$C66,Matching_Engine!$AZ$6:$AZ$95,0)),0) -> 60 | K66: =IFERROR(INDEX(Matching_Engine!$Z$6:$Z$95,MATCH($B66&"|"&$C66,Matching_Engine!$AZ$6:$AZ$95,0)),0) -> 60 | L66: =IFERROR(INDEX(Matching_Engine!$AB$6:$AB$95,MATCH($B66&"|"&$C66,Matching_Engine!$AZ$6:$AZ$95,0)),0) -> 60 | M66: =ROUND($H66*0.3+$I66*0.3+$J66*0.25+$L66*0.15,1) -> 56.7 | N66: =ROUND($G66*0.7+$M66*0.3,1) -> 49.9 | O66: =IF($N66>=85,"Excellent Match",IF($N66>=70,"Strong Match",IF($N66>=55,"Good Match","Weak Match"))) -> Weak Match | P66: ="Brand "&ROUND($G66,0)&"/100; Audience "&ROUND($H66,0)&"/100; Style "&ROUND($I66,0)&"/100; Personality "&ROUND($J66,0)&"/100. Campaign Fit "&ROUND($M66,0)&"/100." -> Brand 47/100; Audience 64/100; Style 45/100; Personality 60/100. Campaign Fit 57/100.
A67: =Campaign_Profile!$D$5 -> CAMP-C | B67: =Campaign_Profile!$D$6 -> BRAND-C | C67: =KOL_Database!$A$7 -> KOL-03 | D67: =KOL_Database!$B$7 -> Salsa Aulia | E67: =KOL_Database!$D$7 -> Instagram | F67: =KOL_Database!$E$7 -> Beauty | G67: =IFERROR(INDEX(Matching_Engine!$AY$6:$AY$95,MATCH($B67&"|"&$C67,Matching_Engine!$AZ$6:$AZ$95,0)),0) | H67: =IFERROR(INDEX(Matching_Engine!$S$6:$S$95,MATCH($B67&"|"&$C67,Matching_Engine!$AZ$6:$AZ$95,0)),0) -> 63 | I67: =IFERROR(INDEX(Matching_Engine!$W$6:$W$95,MATCH($B67&"|"&$C67,Matching_Engine!$AZ$6:$AZ$95,0)),0) -> 45 | J67: =IFERROR(INDEX(Matching_Engine!$Y$6:$Y$95,MATCH($B67&"|"&$C67,Matching_Engine!$AZ$6:$AZ$95,0)),0) -> 60 | K67: =IFERROR(INDEX(Matching_Engine!$Z$6:$Z$95,MATCH($B67&"|"&$C67,Matching_Engine!$AZ$6:$AZ$95,0)),0) -> 65 | L67: =IFERROR(INDEX(Matching_Engine!$AB$6:$AB$95,MATCH($B67&"|"&$C67,Matching_Engine!$AZ$6:$AZ$95,0)),0) -> 60 | M67: =ROUND($H67*0.3+$I67*0.3+$J67*0.25+$L67*0.15,1) -> 56.4 | N67: =ROUND($G67*0.7+$M67*0.3,1) -> #VALUE! | O67: =IF($N67>=85,"Excellent Match",IF($N67>=70,"Strong Match",IF($N67>=55,"Good Match","Weak Match"))) -> #VALUE! | P67: ="Brand "&ROUND($G67,0)&"/100; Audience "&ROUND($H67,0)&"/100; Style "&ROUND($I67,0)&"/100; Personality "&ROUND($J67,0)&"/100. Campaign Fit "&ROUND($M67,0)&"/100." -> #VALUE!
A68: =Campaign_Profile!$D$5 -> CAMP-C | B68: =Campaign_Profile!$D$6 -> BRAND-C | C68: =KOL_Database!$A$8 -> KOL-04 | D68: =KOL_Database!$B$8 -> Nadia Puspa | E68: =KOL_Database!$D$8 -> TikTok | F68: =KOL_Database!$E$8 -> Beauty | G68: =IFERROR(INDEX(Matching_Engine!$AY$6:$AY$95,MATCH($B68&"|"&$C68,Matching_Engine!$AZ$6:$AZ$95,0)),0) | H68: =IFERROR(INDEX(Matching_Engine!$S$6:$S$95,MATCH($B68&"|"&$C68,Matching_Engine!$AZ$6:$AZ$95,0)),0) -> 64 | I68: =IFERROR(INDEX(Matching_Engine!$W$6:$W$95,MATCH($B68&"|"&$C68,Matching_Engine!$AZ$6:$AZ$95,0)),0) -> 45 | J68: =IFERROR(INDEX(Matching_Engine!$Y$6:$Y$95,MATCH($B68&"|"&$C68,Matching_Engine!$AZ$6:$AZ$95,0)),0) -> 60 | K68: =IFERROR(INDEX(Matching_Engine!$Z$6:$Z$95,MATCH($B68&"|"&$C68,Matching_Engine!$AZ$6:$AZ$95,0)),0) -> 70 | L68: =IFERROR(INDEX(Matching_Engine!$AB$6:$AB$95,MATCH($B68&"|"&$C68,Matching_Engine!$AZ$6:$AZ$95,0)),0) -> 55 | M68: =ROUND($H68*0.3+$I68*0.3+$J68*0.25+$L68*0.15,1) -> 56 | N68: =ROUND($G68*0.7+$M68*0.3,1) -> #VALUE! | O68: =IF($N68>=85,"Excellent Match",IF($N68>=70,"Strong Match",IF($N68>=55,"Good Match","Weak Match"))) -> #VALUE! | P68: ="Brand "&ROUND($G68,0)&"/100; Audience "&ROUND($H68,0)&"/100; Style "&ROUND($I68,0)&"/100; Personality "&ROUND($J68,0)&"/100. Campaign Fit "&ROUND($M68,0)&"/100." -> #VALUE!
A69: =Campaign_Profile!$D$5 -> CAMP-C | B69: =Campaign_Profile!$D$6 -> BRAND-C | C69: =KOL_Database!$A$9 -> KOL-05 | D69: =KOL_Database!$B$9 -> Bimo Saputra | E69: =KOL_Database!$D$9 -> TikTok | F69: =KOL_Database!$E$9 -> Food | G69: =IFERROR(INDEX(Matching_Engine!$AY$6:$AY$95,MATCH($B69&"|"&$C69,Matching_Engine!$AZ$6:$AZ$95,0)),0) | H69: =IFERROR(INDEX(Matching_Engine!$S$6:$S$95,MATCH($B69&"|"&$C69,Matching_Engine!$AZ$6:$AZ$95,0)),0) -> 91 | I69: =IFERROR(INDEX(Matching_Engine!$W$6:$W$95,MATCH($B69&"|"&$C69,Matching_Engine!$AZ$6:$AZ$95,0)),0) -> 45 | J69: =IFERROR(INDEX(Matching_Engine!$Y$6:$Y$95,MATCH($B69&"|"&$C69,Matching_Engine!$AZ$6:$AZ$95,0)),0) -> 100 | K69: =IFERROR(INDEX(Matching_Engine!$Z$6:$Z$95,MATCH($B69&"|"&$C69,Matching_Engine!$AZ$6:$AZ$95,0)),0) -> 65 | L69: =IFERROR(INDEX(Matching_Engine!$AB$6:$AB$95,MATCH($B69&"|"&$C69,Matching_Engine!$AZ$6:$AZ$95,0)),0) -> 60 | M69: =ROUND($H69*0.3+$I69*0.3+$J69*0.25+$L69*0.15,1) -> 74.8 | N69: =ROUND($G69*0.7+$M69*0.3,1) -> #VALUE! | O69: =IF($N69>=85,"Excellent Match",IF($N69>=70,"Strong Match",IF($N69>=55,"Good Match","Weak Match"))) -> #VALUE! | P69: ="Brand "&ROUND($G69,0)&"/100; Audience "&ROUND($H69,0)&"/100; Style "&ROUND($I69,0)&"/100; Personality "&ROUND($J69,0)&"/100. Campaign Fit "&ROUND($M69,0)&"/100." -> #VALUE!
A70: =Campaign_Profile!$D$5 -> CAMP-C | B70: =Campaign_Profile!$D$6 -> BRAND-C | C70: =KOL_Database!$A$10 -> KOL-06 | D70: =KOL_Database!$B$10 -> Ayu Lestari | E70: =KOL_Database!$D$10 -> Instagram | F70: =KOL_Database!$E$10 -> Food | G70: =IFERROR(INDEX(Matching_Engine!$AY$6:$AY$95,MATCH($B70&"|"&$C70,Matching_Engine!$AZ$6:$AZ$95,0)),0) -> 74 | H70: =IFERROR(INDEX(Matching_Engine!$S$6:$S$95,MATCH($B70&"|"&$C70,Matching_Engine!$AZ$6:$AZ$95,0)),0) -> 76 | I70: =IFERROR(INDEX(Matching_Engine!$W$6:$W$95,MATCH($B70&"|"&$C70,Matching_Engine!$AZ$6:$AZ$95,0)),0) -> 45 | J70: =IFERROR(INDEX(Matching_Engine!$Y$6:$Y$95,MATCH($B70&"|"&$C70,Matching_Engine!$AZ$6:$AZ$95,0)),0) -> 100 | K70: =IFERROR(INDEX(Matching_Engine!$Z$6:$Z$95,MATCH($B70&"|"&$C70,Matching_Engine!$AZ$6:$AZ$95,0)),0) -> 70 | L70: =IFERROR(INDEX(Matching_Engine!$AB$6:$AB$95,MATCH($B70&"|"&$C70,Matching_Engine!$AZ$6:$AZ$95,0)),0) -> 55 | M70: =ROUND($H70*0.3+$I70*0.3+$J70*0.25+$L70*0.15,1) -> 69.6 | N70: =ROUND($G70*0.7+$M70*0.3,1) -> 72.7 | O70: =IF($N70>=85,"Excellent Match",IF($N70>=70,"Strong Match",IF($N70>=55,"Good Match","Weak Match"))) -> Strong Match | P70: ="Brand "&ROUND($G70,0)&"/100; Audience "&ROUND($H70,0)&"/100; Style "&ROUND($I70,0)&"/100; Personality "&ROUND($J70,0)&"/100. Campaign Fit "&ROUND($M70,0)&"/100." -> Brand 74/100; Audience 76/100; Style 45/100; Personality 100/100. Campaign Fit 70/100.
A71: =Campaign_Profile!$D$5 -> CAMP-C | B71: =Campaign_Profile!$D$6 -> BRAND-C | C71: =KOL_Database!$A$11 -> KOL-07 | D71: =KOL_Database!$B$11 -> Fajar Ramadhan | E71: =KOL_Database!$D$11 -> Instagram | F71: =KOL_Database!$E$11 -> Finance | G71: =IFERROR(INDEX(Matching_Engine!$AY$6:$AY$95,MATCH($B71&"|"&$C71,Matching_Engine!$AZ$6:$AZ$95,0)),0) | H71: =IFERROR(INDEX(Matching_Engine!$S$6:$S$95,MATCH($B71&"|"&$C71,Matching_Engine!$AZ$6:$AZ$95,0)),0) -> 68 | I71: =IFERROR(INDEX(Matching_Engine!$W$6:$W$95,MATCH($B71&"|"&$C71,Matching_Engine!$AZ$6:$AZ$95,0)),0) -> 45 | J71: =IFERROR(INDEX(Matching_Engine!$Y$6:$Y$95,MATCH($B71&"|"&$C71,Matching_Engine!$AZ$6:$AZ$95,0)),0) -> 45 | K71: =IFERROR(INDEX(Matching_Engine!$Z$6:$Z$95,MATCH($B71&"|"&$C71,Matching_Engine!$AZ$6:$AZ$95,0)),0) -> 60 | L71: =IFERROR(INDEX(Matching_Engine!$AB$6:$AB$95,MATCH($B71&"|"&$C71,Matching_Engine!$AZ$6:$AZ$95,0)),0) -> 60 | M71: =ROUND($H71*0.3+$I71*0.3+$J71*0.25+$L71*0.15,1) -> 54.2 | N71: =ROUND($G71*0.7+$M71*0.3,1) -> #VALUE! | O71: =IF($N71>=85,"Excellent Match",IF($N71>=70,"Strong Match",IF($N71>=55,"Good Match","Weak Match"))) -> #VALUE! | P71: ="Brand "&ROUND($G71,0)&"/100; Audience "&ROUND($H71,0)&"/100; Style "&ROUND($I71,0)&"/100; Personality "&ROUND($J71,0)&"/100. Campaign Fit "&ROUND($M71,0)&"/100." -> #VALUE!
A72: =Campaign_Profile!$D$5 -> CAMP-C | B72: =Campaign_Profile!$D$6 -> BRAND-C | C72: =KOL_Database!$A$12 -> KOL-08 | D72: =KOL_Database!$B$12 -> Tania Wijaya | E72: =KOL_Database!$D$12 -> TikTok | F72: =KOL_Database!$E$12 -> Finance | G72: =IFERROR(INDEX(Matching_Engine!$AY$6:$AY$95,MATCH($B72&"|"&$C72,Matching_Engine!$AZ$6:$AZ$95,0)),0) -> 47 | H72: =IFERROR(INDEX(Matching_Engine!$S$6:$S$95,MATCH($B72&"|"&$C72,Matching_Engine!$AZ$6:$AZ$95,0)),0) -> 66 | I72: =IFERROR(INDEX(Matching_Engine!$W$6:$W$95,MATCH($B72&"|"&$C72,Matching_Engine!$AZ$6:$AZ$95,0)),0) -> 45 | J72: =IFERROR(INDEX(Matching_Engine!$Y$6:$Y$95,MATCH($B72&"|"&$C72,Matching_Engine!$AZ$6:$AZ$95,0)),0) -> 60 | K72: =IFERROR(INDEX(Matching_Engine!$Z$6:$Z$95,MATCH($B72&"|"&$C72,Matching_Engine!$AZ$6:$AZ$95,0)),0) -> 60 | L72: =IFERROR(INDEX(Matching_Engine!$AB$6:$AB$95,MATCH($B72&"|"&$C72,Matching_Engine!$AZ$6:$AZ$95,0)),0) -> 60 | M72: =ROUND($H72*0.3+$I72*0.3+$J72*0.25+$L72*0.15,1) -> 57.3 | N72: =ROUND($G72*0.7+$M72*0.3,1) -> 50.1 | O72: =IF($N72>=85,"Excellent Match",IF($N72>=70,"Strong Match",IF($N72>=55,"Good Match","Weak Match"))) -> Weak Match | P72: ="Brand "&ROUND($G72,0)&"/100; Audience "&ROUND($H72,0)&"/100; Style "&ROUND($I72,0)&"/100; Personality "&ROUND($J72,0)&"/100. Campaign Fit "&ROUND($M72,0)&"/100." -> Brand 47/100; Audience 66/100; Style 45/100; Personality 60/100. Campaign Fit 57/100.
A73: =Campaign_Profile!$D$5 -> CAMP-C | B73: =Campaign_Profile!$D$6 -> BRAND-C | C73: =KOL_Database!$A$13 -> KOL-09 | D73: =KOL_Database!$B$13 -> Gilang Prakoso | E73: =KOL_Database!$D$13 -> TikTok | F73: =KOL_Database!$E$13 -> Education | G73: =IFERROR(INDEX(Matching_Engine!$AY$6:$AY$95,MATCH($B73&"|"&$C73,Matching_Engine!$AZ$6:$AZ$95,0)),0) | H73: =IFERROR(INDEX(Matching_Engine!$S$6:$S$95,MATCH($B73&"|"&$C73,Matching_Engine!$AZ$6:$AZ$95,0)),0) -> 71 | I73: =IFERROR(INDEX(Matching_Engine!$W$6:$W$95,MATCH($B73&"|"&$C73,Matching_Engine!$AZ$6:$AZ$95,0)),0) -> 45 | J73: =IFERROR(INDEX(Matching_Engine!$Y$6:$Y$95,MATCH($B73&"|"&$C73,Matching_Engine!$AZ$6:$AZ$95,0)),0) -> 60 | K73: =IFERROR(INDEX(Matching_Engine!$Z$6:$Z$95,MATCH($B73&"|"&$C73,Matching_Engine!$AZ$6:$AZ$95,0)),0) -> 60 | L73: =IFERROR(INDEX(Matching_Engine!$AB$6:$AB$95,MATCH($B73&"|"&$C73,Matching_Engine!$AZ$6:$AZ$95,0)),0) -> 60 | M73: =ROUND($H73*0.3+$I73*0.3+$J73*0.25+$L73*0.15,1) -> 58.8 | N73: =ROUND($G73*0.7+$M73*0.3,1) -> #VALUE! | O73: =IF($N73>=85,"Excellent Match",IF($N73>=70,"Strong Match",IF($N73>=55,"Good Match","Weak Match"))) -> #VALUE! | P73: ="Brand "&ROUND($G73,0)&"/100; Audience "&ROUND($H73,0)&"/100; Style "&ROUND($I73,0)&"/100; Personality "&ROUND($J73,0)&"/100. Campaign Fit "&ROUND($M73,0)&"/100." -> #VALUE!
A74: =Campaign_Profile!$D$5 -> CAMP-C | B74: =Campaign_Profile!$D$6 -> BRAND-C | C74: =KOL_Database!$A$14 -> KOL-10 | D74: =KOL_Database!$B$14 -> Mira Handayani | E74: =KOL_Database!$D$14 -> Instagram | F74: =KOL_Database!$E$14 -> Education | G74: =IFERROR(INDEX(Matching_Engine!$AY$6:$AY$95,MATCH($B74&"|"&$C74,Matching_Engine!$AZ$6:$AZ$95,0)),0) -> 56 | H74: =IFERROR(INDEX(Matching_Engine!$S$6:$S$95,MATCH($B74&"|"&$C74,Matching_Engine!$AZ$6:$AZ$95,0)),0) -> 78 | I74: =IFERROR(INDEX(Matching_Engine!$W$6:$W$95,MATCH($B74&"|"&$C74,Matching_Engine!$AZ$6:$AZ$95,0)),0) -> 45 | J74: =IFERROR(INDEX(Matching_Engine!$Y$6:$Y$95,MATCH($B74&"|"&$C74,Matching_Engine!$AZ$6:$AZ$95,0)),0) -> 60 | K74: =IFERROR(INDEX(Matching_Engine!$Z$6:$Z$95,MATCH($B74&"|"&$C74,Matching_Engine!$AZ$6:$AZ$95,0)),0) -> 70 | L74: =IFERROR(INDEX(Matching_Engine!$AB$6:$AB$95,MATCH($B74&"|"&$C74,Matching_Engine!$AZ$6:$AZ$95,0)),0) -> 55 | M74: =ROUND($H74*0.3+$I74*0.3+$J74*0.25+$L74*0.15,1) -> 60.2 | N74: =ROUND($G74*0.7+$M74*0.3,1) -> 57.3 | O74: =IF($N74>=85,"Excellent Match",IF($N74>=70,"Strong Match",IF($N74>=55,"Good Match","Weak Match"))) -> Good Match | P74: ="Brand "&ROUND($G74,0)&"/100; Audience "&ROUND($H74,0)&"/100; Style "&ROUND($I74,0)&"/100; Personality "&ROUND($J74,0)&"/100. Campaign Fit "&ROUND($M74,0)&"/100." -> Brand 56/100; Audience 78/100; Style 45/100; Personality 60/100. Campaign Fit 60/100.
A75: =Campaign_Profile!$D$5 -> CAMP-C | B75: =Campaign_Profile!$D$6 -> BRAND-C | C75: =KOL_Database!$A$15 -> KOL-11 | D75: =KOL_Database!$B$15 -> Dimas Anggara | E75: =KOL_Database!$D$15 -> Instagram | F75: =KOL_Database!$E$15 -> Fitness | G75: =IFERROR(INDEX(Matching_Engine!$AY$6:$AY$95,MATCH($B75&"|"&$C75,Matching_Engine!$AZ$6:$AZ$95,0)),0) | H75: =IFERROR(INDEX(Matching_Engine!$S$6:$S$95,MATCH($B75&"|"&$C75,Matching_Engine!$AZ$6:$AZ$95,0)),0) -> 74 | I75: =IFERROR(INDEX(Matching_Engine!$W$6:$W$95,MATCH($B75&"|"&$C75,Matching_Engine!$AZ$6:$AZ$95,0)),0) -> 45 | J75: =IFERROR(INDEX(Matching_Engine!$Y$6:$Y$95,MATCH($B75&"|"&$C75,Matching_Engine!$AZ$6:$AZ$95,0)),0) -> 45 | K75: =IFERROR(INDEX(Matching_Engine!$Z$6:$Z$95,MATCH($B75&"|"&$C75,Matching_Engine!$AZ$6:$AZ$95,0)),0) -> 55 | L75: =IFERROR(INDEX(Matching_Engine!$AB$6:$AB$95,MATCH($B75&"|"&$C75,Matching_Engine!$AZ$6:$AZ$95,0)),0) -> 45 | M75: =ROUND($H75*0.3+$I75*0.3+$J75*0.25+$L75*0.15,1) -> 53.7 | N75: =ROUND($G75*0.7+$M75*0.3,1) -> #VALUE! | O75: =IF($N75>=85,"Excellent Match",IF($N75>=70,"Strong Match",IF($N75>=55,"Good Match","Weak Match"))) -> #VALUE! | P75: ="Brand "&ROUND($G75,0)&"/100; Audience "&ROUND($H75,0)&"/100; Style "&ROUND($I75,0)&"/100; Personality "&ROUND($J75,0)&"/100. Campaign Fit "&ROUND($M75,0)&"/100." -> #VALUE!
A76: =Campaign_Profile!$D$5 -> CAMP-C | B76: =Campaign_Profile!$D$6 -> BRAND-C | C76: =KOL_Database!$A$16 -> KOL-12 | D76: =KOL_Database!$B$16 -> Rani Kusuma | E76: =KOL_Database!$D$16 -> TikTok | F76: =KOL_Database!$E$16 -> Fitness | G76: =IFERROR(INDEX(Matching_Engine!$AY$6:$AY$95,MATCH($B76&"|"&$C76,Matching_Engine!$AZ$6:$AZ$95,0)),0) | H76: =IFERROR(INDEX(Matching_Engine!$S$6:$S$95,MATCH($B76&"|"&$C76,Matching_Engine!$AZ$6:$AZ$95,0)),0) -> 72 | I76: =IFERROR(INDEX(Matching_Engine!$W$6:$W$95,MATCH($B76&"|"&$C76,Matching_Engine!$AZ$6:$AZ$95,0)),0) -> 45 | J76: =IFERROR(INDEX(Matching_Engine!$Y$6:$Y$95,MATCH($B76&"|"&$C76,Matching_Engine!$AZ$6:$AZ$95,0)),0) -> 65 | K76: =IFERROR(INDEX(Matching_Engine!$Z$6:$Z$95,MATCH($B76&"|"&$C76,Matching_Engine!$AZ$6:$AZ$95,0)),0) -> 70 | L76: =IFERROR(INDEX(Matching_Engine!$AB$6:$AB$95,MATCH($B76&"|"&$C76,Matching_Engine!$AZ$6:$AZ$95,0)),0) -> 55 | M76: =ROUND($H76*0.3+$I76*0.3+$J76*0.25+$L76*0.15,1) -> 59.6 | N76: =ROUND($G76*0.7+$M76*0.3,1) -> #VALUE! | O76: =IF($N76>=85,"Excellent Match",IF($N76>=70,"Strong Match",IF($N76>=55,"Good Match","Weak Match"))) -> #VALUE! | P76: ="Brand "&ROUND($G76,0)&"/100; Audience "&ROUND($H76,0)&"/100; Style "&ROUND($I76,0)&"/100; Personality "&ROUND($J76,0)&"/100. Campaign Fit "&ROUND($M76,0)&"/100." -> #VALUE!
A77: =Campaign_Profile!$D$5 -> CAMP-C | B77: =Campaign_Profile!$D$6 -> BRAND-C | C77: =KOL_Database!$A$17 -> KOL-13 | D77: =KOL_Database!$B$17 -> Kevin Halim | E77: =KOL_Database!$D$17 -> Instagram | F77: =KOL_Database!$E$17 -> Fashion | G77: =IFERROR(INDEX(Matching_Engine!$AY$6:$AY$95,MATCH($B77&"|"&$C77,Matching_Engine!$AZ$6:$AZ$95,0)),0) | H77: =IFERROR(INDEX(Matching_Engine!$S$6:$S$95,MATCH($B77&"|"&$C77,Matching_Engine!$AZ$6:$AZ$95,0)),0) -> 67 | I77: =IFERROR(INDEX(Matching_Engine!$W$6:$W$95,MATCH($B77&"|"&$C77,Matching_Engine!$AZ$6:$AZ$95,0)),0) -> 45 | J77: =IFERROR(INDEX(Matching_Engine!$Y$6:$Y$95,MATCH($B77&"|"&$C77,Matching_Engine!$AZ$6:$AZ$95,0)),0) -> 60 | K77: =IFERROR(INDEX(Matching_Engine!$Z$6:$Z$95,MATCH($B77&"|"&$C77,Matching_Engine!$AZ$6:$AZ$95,0)),0) -> 65 | L77: =IFERROR(INDEX(Matching_Engine!$AB$6:$AB$95,MATCH($B77&"|"&$C77,Matching_Engine!$AZ$6:$AZ$95,0)),0) -> 70 | M77: =ROUND($H77*0.3+$I77*0.3+$J77*0.25+$L77*0.15,1) -> 59.1 | N77: =ROUND($G77*0.7+$M77*0.3,1) -> #VALUE! | O77: =IF($N77>=85,"Excellent Match",IF($N77>=70,"Strong Match",IF($N77>=55,"Good Match","Weak Match"))) -> #VALUE! | P77: ="Brand "&ROUND($G77,0)&"/100; Audience "&ROUND($H77,0)&"/100; Style "&ROUND($I77,0)&"/100; Personality "&ROUND($J77,0)&"/100. Campaign Fit "&ROUND($M77,0)&"/100." -> #VALUE!
A78: =Campaign_Profile!$D$5 -> CAMP-C | B78: =Campaign_Profile!$D$6 -> BRAND-C | C78: =KOL_Database!$A$18 -> KOL-14 | D78: =KOL_Database!$B$18 -> Zahra Amelia | E78: =KOL_Database!$D$18 -> Instagram | F78: =KOL_Database!$E$18 -> Fashion | G78: =IFERROR(INDEX(Matching_Engine!$AY$6:$AY$95,MATCH($B78&"|"&$C78,Matching_Engine!$AZ$6:$AZ$95,0)),0) | H78: =IFERROR(INDEX(Matching_Engine!$S$6:$S$95,MATCH($B78&"|"&$C78,Matching_Engine!$AZ$6:$AZ$95,0)),0) -> 69 | I78: =IFERROR(INDEX(Matching_Engine!$W$6:$W$95,MATCH($B78&"|"&$C78,Matching_Engine!$AZ$6:$AZ$95,0)),0) -> 45 | J78: =IFERROR(INDEX(Matching_Engine!$Y$6:$Y$95,MATCH($B78&"|"&$C78,Matching_Engine!$AZ$6:$AZ$95,0)),0) -> 35 | K78: =IFERROR(INDEX(Matching_Engine!$Z$6:$Z$95,MATCH($B78&"|"&$C78,Matching_Engine!$AZ$6:$AZ$95,0)),0) -> 65 | L78: =IFERROR(INDEX(Matching_Engine!$AB$6:$AB$95,MATCH($B78&"|"&$C78,Matching_Engine!$AZ$6:$AZ$95,0)),0) -> 70 | M78: =ROUND($H78*0.3+$I78*0.3+$J78*0.25+$L78*0.15,1) -> 53.5 | N78: =ROUND($G78*0.7+$M78*0.3,1) -> #VALUE! | O78: =IF($N78>=85,"Excellent Match",IF($N78>=70,"Strong Match",IF($N78>=55,"Good Match","Weak Match"))) -> #VALUE! | P78: ="Brand "&ROUND($G78,0)&"/100; Audience "&ROUND($H78,0)&"/100; Style "&ROUND($I78,0)&"/100; Personality "&ROUND($J78,0)&"/100. Campaign Fit "&ROUND($M78,0)&"/100." -> #VALUE!
A79: =Campaign_Profile!$D$5 -> CAMP-C | B79: =Campaign_Profile!$D$6 -> BRAND-C | C79: =KOL_Database!$A$19 -> KOL-15 | D79: =KOL_Database!$B$19 -> Andini Rahma | E79: =KOL_Database!$D$19 -> Instagram | F79: =KOL_Database!$E$19 -> Lifestyle | G79: =IFERROR(INDEX(Matching_Engine!$AY$6:$AY$95,MATCH($B79&"|"&$C79,Matching_Engine!$AZ$6:$AZ$95,0)),0) -> 72 | H79: =IFERROR(INDEX(Matching_Engine!$S$6:$S$95,MATCH($B79&"|"&$C79,Matching_Engine!$AZ$6:$AZ$95,0)),0) -> 76 | I79: =IFERROR(INDEX(Matching_Engine!$W$6:$W$95,MATCH($B79&"|"&$C79,Matching_Engine!$AZ$6:$AZ$95,0)),0) -> 80 | J79: =IFERROR(INDEX(Matching_Engine!$Y$6:$Y$95,MATCH($B79&"|"&$C79,Matching_Engine!$AZ$6:$AZ$95,0)),0) -> 100 | K79: =IFERROR(INDEX(Matching_Engine!$Z$6:$Z$95,MATCH($B79&"|"&$C79,Matching_Engine!$AZ$6:$AZ$95,0)),0) -> 90 | L79: =IFERROR(INDEX(Matching_Engine!$AB$6:$AB$95,MATCH($B79&"|"&$C79,Matching_Engine!$AZ$6:$AZ$95,0)),0) -> 90 | M79: =ROUND($H79*0.3+$I79*0.3+$J79*0.25+$L79*0.15,1) -> 85.3 | N79: =ROUND($G79*0.7+$M79*0.3,1) -> 76 | O79: =IF($N79>=85,"Excellent Match",IF($N79>=70,"Strong Match",IF($N79>=55,"Good Match","Weak Match"))) -> Strong Match | P79: ="Brand "&ROUND($G79,0)&"/100; Audience "&ROUND($H79,0)&"/100; Style "&ROUND($I79,0)&"/100; Personality "&ROUND($J79,0)&"/100. Campaign Fit "&ROUND($M79,0)&"/100." -> Brand 72/100; Audience 76/100; Style 80/100; Personality 100/100. Campaign Fit 85/100.
A80: =Campaign_Profile!$D$5 -> CAMP-C | B80: =Campaign_Profile!$D$6 -> BRAND-C | C80: =KOL_Database!$A$20 -> KOL-16 | D80: =KOL_Database!$B$20 -> Yoga Pratama | E80: =KOL_Database!$D$20 -> TikTok | F80: =KOL_Database!$E$20 -> Lifestyle | G80: =IFERROR(INDEX(Matching_Engine!$AY$6:$AY$95,MATCH($B80&"|"&$C80,Matching_Engine!$AZ$6:$AZ$95,0)),0) | H80: =IFERROR(INDEX(Matching_Engine!$S$6:$S$95,MATCH($B80&"|"&$C80,Matching_Engine!$AZ$6:$AZ$95,0)),0) -> 70 | I80: =IFERROR(INDEX(Matching_Engine!$W$6:$W$95,MATCH($B80&"|"&$C80,Matching_Engine!$AZ$6:$AZ$95,0)),0) -> 100 | J80: =IFERROR(INDEX(Matching_Engine!$Y$6:$Y$95,MATCH($B80&"|"&$C80,Matching_Engine!$AZ$6:$AZ$95,0)),0) -> 65 | K80: =IFERROR(INDEX(Matching_Engine!$Z$6:$Z$95,MATCH($B80&"|"&$C80,Matching_Engine!$AZ$6:$AZ$95,0)),0) -> 95 | L80: =IFERROR(INDEX(Matching_Engine!$AB$6:$AB$95,MATCH($B80&"|"&$C80,Matching_Engine!$AZ$6:$AZ$95,0)),0) -> 100 | M80: =ROUND($H80*0.3+$I80*0.3+$J80*0.25+$L80*0.15,1) -> 82.3 | N80: =ROUND($G80*0.7+$M80*0.3,1) -> #VALUE! | O80: =IF($N80>=85,"Excellent Match",IF($N80>=70,"Strong Match",IF($N80>=55,"Good Match","Weak Match"))) -> #VALUE! | P80: ="Brand "&ROUND($G80,0)&"/100; Audience "&ROUND($H80,0)&"/100; Style "&ROUND($I80,0)&"/100; Personality "&ROUND($J80,0)&"/100. Campaign Fit "&ROUND($M80,0)&"/100." -> #VALUE!
A81: =Campaign_Profile!$D$5 -> CAMP-C | B81: =Campaign_Profile!$D$6 -> BRAND-C | C81: =KOL_Database!$A$21 -> KOL-17 | D81: =KOL_Database!$B$21 -> Sinta Maharani | E81: =KOL_Database!$D$21 -> Instagram | F81: =KOL_Database!$E$21 -> Travel | G81: =IFERROR(INDEX(Matching_Engine!$AY$6:$AY$95,MATCH($B81&"|"&$C81,Matching_Engine!$AZ$6:$AZ$95,0)),0) | H81: =IFERROR(INDEX(Matching_Engine!$S$6:$S$95,MATCH($B81&"|"&$C81,Matching_Engine!$AZ$6:$AZ$95,0)),0) -> 86 | I81: =IFERROR(INDEX(Matching_Engine!$W$6:$W$95,MATCH($B81&"|"&$C81,Matching_Engine!$AZ$6:$AZ$95,0)),0) -> 45 | J81: =IFERROR(INDEX(Matching_Engine!$Y$6:$Y$95,MATCH($B81&"|"&$C81,Matching_Engine!$AZ$6:$AZ$95,0)),0) -> 35 | K81: =IFERROR(INDEX(Matching_Engine!$Z$6:$Z$95,MATCH($B81&"|"&$C81,Matching_Engine!$AZ$6:$AZ$95,0)),0) -> 65 | L81: =IFERROR(INDEX(Matching_Engine!$AB$6:$AB$95,MATCH($B81&"|"&$C81,Matching_Engine!$AZ$6:$AZ$95,0)),0) -> 70 | M81: =ROUND($H81*0.3+$I81*0.3+$J81*0.25+$L81*0.15,1) -> 58.6 | N81: =ROUND($G81*0.7+$M81*0.3,1) -> #VALUE! | O81: =IF($N81>=85,"Excellent Match",IF($N81>=70,"Strong Match",IF($N81>=55,"Good Match","Weak Match"))) -> #VALUE! | P81: ="Brand "&ROUND($G81,0)&"/100; Audience "&ROUND($H81,0)&"/100; Style "&ROUND($I81,0)&"/100; Personality "&ROUND($J81,0)&"/100. Campaign Fit "&ROUND($M81,0)&"/100." -> #VALUE!
A82: =Campaign_Profile!$D$5 -> CAMP-C | B82: =Campaign_Profile!$D$6 -> BRAND-C | C82: =KOL_Database!$A$22 -> KOL-18 | D82: =KOL_Database!$B$22 -> Reza Fadillah | E82: =KOL_Database!$D$22 -> TikTok | F82: =KOL_Database!$E$22 -> Travel | G82: =IFERROR(INDEX(Matching_Engine!$AY$6:$AY$95,MATCH($B82&"|"&$C82,Matching_Engine!$AZ$6:$AZ$95,0)),0) -> 78 | H82: =IFERROR(INDEX(Matching_Engine!$S$6:$S$95,MATCH($B82&"|"&$C82,Matching_Engine!$AZ$6:$AZ$95,0)),0) -> 85 | I82: =IFERROR(INDEX(Matching_Engine!$W$6:$W$95,MATCH($B82&"|"&$C82,Matching_Engine!$AZ$6:$AZ$95,0)),0) -> 80 | J82: =IFERROR(INDEX(Matching_Engine!$Y$6:$Y$95,MATCH($B82&"|"&$C82,Matching_Engine!$AZ$6:$AZ$95,0)),0) -> 95 | K82: =IFERROR(INDEX(Matching_Engine!$Z$6:$Z$95,MATCH($B82&"|"&$C82,Matching_Engine!$AZ$6:$AZ$95,0)),0) -> 90 | L82: =IFERROR(INDEX(Matching_Engine!$AB$6:$AB$95,MATCH($B82&"|"&$C82,Matching_Engine!$AZ$6:$AZ$95,0)),0) -> 90 | M82: =ROUND($H82*0.3+$I82*0.3+$J82*0.25+$L82*0.15,1) -> 86.8 | N82: =ROUND($G82*0.7+$M82*0.3,1) -> 80.6 | O82: =IF($N82>=85,"Excellent Match",IF($N82>=70,"Strong Match",IF($N82>=55,"Good Match","Weak Match"))) -> Strong Match | P82: ="Brand "&ROUND($G82,0)&"/100; Audience "&ROUND($H82,0)&"/100; Style "&ROUND($I82,0)&"/100; Personality "&ROUND($J82,0)&"/100. Campaign Fit "&ROUND($M82,0)&"/100." -> Brand 78/100; Audience 85/100; Style 80/100; Personality 95/100. Campaign Fit 87/100.
A83: =Campaign_Profile!$D$5 -> CAMP-C | B83: =Campaign_Profile!$D$6 -> BRAND-C | C83: =KOL_Database!$A$23 -> KOL-19 | D83: =KOL_Database!$B$23 -> Putri Amanda | E83: =KOL_Database!$D$23 -> Instagram | F83: =KOL_Database!$E$23 -> Parenting | G83: =IFERROR(INDEX(Matching_Engine!$AY$6:$AY$95,MATCH($B83&"|"&$C83,Matching_Engine!$AZ$6:$AZ$95,0)),0) | H83: =IFERROR(INDEX(Matching_Engine!$S$6:$S$95,MATCH($B83&"|"&$C83,Matching_Engine!$AZ$6:$AZ$95,0)),0) -> 74 | I83: =IFERROR(INDEX(Matching_Engine!$W$6:$W$95,MATCH($B83&"|"&$C83,Matching_Engine!$AZ$6:$AZ$95,0)),0) -> 100 | J83: =IFERROR(INDEX(Matching_Engine!$Y$6:$Y$95,MATCH($B83&"|"&$C83,Matching_Engine!$AZ$6:$AZ$95,0)),0) -> 100 | K83: =IFERROR(INDEX(Matching_Engine!$Z$6:$Z$95,MATCH($B83&"|"&$C83,Matching_Engine!$AZ$6:$AZ$95,0)),0) -> 95 | L83: =IFERROR(INDEX(Matching_Engine!$AB$6:$AB$95,MATCH($B83&"|"&$C83,Matching_Engine!$AZ$6:$AZ$95,0)),0) -> 100 | M83: =ROUND($H83*0.3+$I83*0.3+$J83*0.25+$L83*0.15,1) -> 92.2 | N83: =ROUND($G83*0.7+$M83*0.3,1) -> #VALUE! | O83: =IF($N83>=85,"Excellent Match",IF($N83>=70,"Strong Match",IF($N83>=55,"Good Match","Weak Match"))) -> #VALUE! | P83: ="Brand "&ROUND($G83,0)&"/100; Audience "&ROUND($H83,0)&"/100; Style "&ROUND($I83,0)&"/100; Personality "&ROUND($J83,0)&"/100. Campaign Fit "&ROUND($M83,0)&"/100." -> #VALUE!
A84: =Campaign_Profile!$D$5 -> CAMP-C | B84: =Campaign_Profile!$D$6 -> BRAND-C | C84: =KOL_Database!$A$24 -> KOL-20 | D84: =KOL_Database!$B$24 -> Hendra Wijoyo | E84: =KOL_Database!$D$24 -> TikTok | F84: =KOL_Database!$E$24 -> Parenting | G84: =IFERROR(INDEX(Matching_Engine!$AY$6:$AY$95,MATCH($B84&"|"&$C84,Matching_Engine!$AZ$6:$AZ$95,0)),0) -> 67 | H84: =IFERROR(INDEX(Matching_Engine!$S$6:$S$95,MATCH($B84&"|"&$C84,Matching_Engine!$AZ$6:$AZ$95,0)),0) -> 84 | I84: =IFERROR(INDEX(Matching_Engine!$W$6:$W$95,MATCH($B84&"|"&$C84,Matching_Engine!$AZ$6:$AZ$95,0)),0) -> 45 | J84: =IFERROR(INDEX(Matching_Engine!$Y$6:$Y$95,MATCH($B84&"|"&$C84,Matching_Engine!$AZ$6:$AZ$95,0)),0) -> 70 | K84: =IFERROR(INDEX(Matching_Engine!$Z$6:$Z$95,MATCH($B84&"|"&$C84,Matching_Engine!$AZ$6:$AZ$95,0)),0) -> 70 | L84: =IFERROR(INDEX(Matching_Engine!$AB$6:$AB$95,MATCH($B84&"|"&$C84,Matching_Engine!$AZ$6:$AZ$95,0)),0) -> 70 | M84: =ROUND($H84*0.3+$I84*0.3+$J84*0.25+$L84*0.15,1) -> 66.7 | N84: =ROUND($G84*0.7+$M84*0.3,1) -> 66.9 | O84: =IF($N84>=85,"Excellent Match",IF($N84>=70,"Strong Match",IF($N84>=55,"Good Match","Weak Match"))) -> Good Match | P84: ="Brand "&ROUND($G84,0)&"/100; Audience "&ROUND($H84,0)&"/100; Style "&ROUND($I84,0)&"/100; Personality "&ROUND($J84,0)&"/100. Campaign Fit "&ROUND($M84,0)&"/100." -> Brand 67/100; Audience 84/100; Style 45/100; Personality 70/100. Campaign Fit 67/100.
A85: =Campaign_Profile!$D$5 -> CAMP-C | B85: =Campaign_Profile!$D$6 -> BRAND-C | C85: =KOL_Database!$A$25 -> KOL-21 | D85: =KOL_Database!$B$25 -> Bagas Setiawan | E85: =KOL_Database!$D$25 -> TikTok | F85: =KOL_Database!$E$25 -> Entertainment | G85: =IFERROR(INDEX(Matching_Engine!$AY$6:$AY$95,MATCH($B85&"|"&$C85,Matching_Engine!$AZ$6:$AZ$95,0)),0) | H85: =IFERROR(INDEX(Matching_Engine!$S$6:$S$95,MATCH($B85&"|"&$C85,Matching_Engine!$AZ$6:$AZ$95,0)),0) -> 75 | I85: =IFERROR(INDEX(Matching_Engine!$W$6:$W$95,MATCH($B85&"|"&$C85,Matching_Engine!$AZ$6:$AZ$95,0)),0) -> 45 | J85: =IFERROR(INDEX(Matching_Engine!$Y$6:$Y$95,MATCH($B85&"|"&$C85,Matching_Engine!$AZ$6:$AZ$95,0)),0) -> 70 | K85: =IFERROR(INDEX(Matching_Engine!$Z$6:$Z$95,MATCH($B85&"|"&$C85,Matching_Engine!$AZ$6:$AZ$95,0)),0) -> 60 | L85: =IFERROR(INDEX(Matching_Engine!$AB$6:$AB$95,MATCH($B85&"|"&$C85,Matching_Engine!$AZ$6:$AZ$95,0)),0) -> 60 | M85: =ROUND($H85*0.3+$I85*0.3+$J85*0.25+$L85*0.15,1) -> 62.5 | N85: =ROUND($G85*0.7+$M85*0.3,1) -> #VALUE! | O85: =IF($N85>=85,"Excellent Match",IF($N85>=70,"Strong Match",IF($N85>=55,"Good Match","Weak Match"))) -> #VALUE! | P85: ="Brand "&ROUND($G85,0)&"/100; Audience "&ROUND($H85,0)&"/100; Style "&ROUND($I85,0)&"/100; Personality "&ROUND($J85,0)&"/100. Campaign Fit "&ROUND($M85,0)&"/100." -> #VALUE!
A86: =Campaign_Profile!$D$5 -> CAMP-C | B86: =Campaign_Profile!$D$6 -> BRAND-C | C86: =KOL_Database!$A$26 -> KOL-22 | D86: =KOL_Database!$B$26 -> Nabila Kirana | E86: =KOL_Database!$D$26 -> Instagram | F86: =KOL_Database!$E$26 -> Entertainment | G86: =IFERROR(INDEX(Matching_Engine!$AY$6:$AY$95,MATCH($B86&"|"&$C86,Matching_Engine!$AZ$6:$AZ$95,0)),0) | H86: =IFERROR(INDEX(Matching_Engine!$S$6:$S$95,MATCH($B86&"|"&$C86,Matching_Engine!$AZ$6:$AZ$95,0)),0) -> 68 | I86: =IFERROR(INDEX(Matching_Engine!$W$6:$W$95,MATCH($B86&"|"&$C86,Matching_Engine!$AZ$6:$AZ$95,0)),0) -> 45 | J86: =IFERROR(INDEX(Matching_Engine!$Y$6:$Y$95,MATCH($B86&"|"&$C86,Matching_Engine!$AZ$6:$AZ$95,0)),0) -> 60 | K86: =IFERROR(INDEX(Matching_Engine!$Z$6:$Z$95,MATCH($B86&"|"&$C86,Matching_Engine!$AZ$6:$AZ$95,0)),0) -> 65 | L86: =IFERROR(INDEX(Matching_Engine!$AB$6:$AB$95,MATCH($B86&"|"&$C86,Matching_Engine!$AZ$6:$AZ$95,0)),0) -> 70 | M86: =ROUND($H86*0.3+$I86*0.3+$J86*0.25+$L86*0.15,1) -> 59.4 | N86: =ROUND($G86*0.7+$M86*0.3,1) -> #VALUE! | O86: =IF($N86>=85,"Excellent Match",IF($N86>=70,"Strong Match",IF($N86>=55,"Good Match","Weak Match"))) -> #VALUE! | P86: ="Brand "&ROUND($G86,0)&"/100; Audience "&ROUND($H86,0)&"/100; Style "&ROUND($I86,0)&"/100; Personality "&ROUND($J86,0)&"/100. Campaign Fit "&ROUND($M86,0)&"/100." -> #VALUE!
A87: =Campaign_Profile!$D$5 -> CAMP-C | B87: =Campaign_Profile!$D$6 -> BRAND-C | C87: =KOL_Database!$A$27 -> KOL-23 | D87: =KOL_Database!$B$27 -> Arya Mahendra | E87: =KOL_Database!$D$27 -> TikTok | F87: =KOL_Database!$E$27 -> Gaming | G87: =IFERROR(INDEX(Matching_Engine!$AY$6:$AY$95,MATCH($B87&"|"&$C87,Matching_Engine!$AZ$6:$AZ$95,0)),0) | H87: =IFERROR(INDEX(Matching_Engine!$S$6:$S$95,MATCH($B87&"|"&$C87,Matching_Engine!$AZ$6:$AZ$95,0)),0) -> 66 | I87: =IFERROR(INDEX(Matching_Engine!$W$6:$W$95,MATCH($B87&"|"&$C87,Matching_Engine!$AZ$6:$AZ$95,0)),0) -> 45 | J87: =IFERROR(INDEX(Matching_Engine!$Y$6:$Y$95,MATCH($B87&"|"&$C87,Matching_Engine!$AZ$6:$AZ$95,0)),0) -> 75 | K87: =IFERROR(INDEX(Matching_Engine!$Z$6:$Z$95,MATCH($B87&"|"&$C87,Matching_Engine!$AZ$6:$AZ$95,0)),0) -> 70 | L87: =IFERROR(INDEX(Matching_Engine!$AB$6:$AB$95,MATCH($B87&"|"&$C87,Matching_Engine!$AZ$6:$AZ$95,0)),0) -> 70 | M87: =ROUND($H87*0.3+$I87*0.3+$J87*0.25+$L87*0.15,1) -> 62.6 | N87: =ROUND($G87*0.7+$M87*0.3,1) -> #VALUE! | O87: =IF($N87>=85,"Excellent Match",IF($N87>=70,"Strong Match",IF($N87>=55,"Good Match","Weak Match"))) -> #VALUE! | P87: ="Brand "&ROUND($G87,0)&"/100; Audience "&ROUND($H87,0)&"/100; Style "&ROUND($I87,0)&"/100; Personality "&ROUND($J87,0)&"/100. Campaign Fit "&ROUND($M87,0)&"/100." -> #VALUE!
A88: =Campaign_Profile!$D$5 -> CAMP-C | B88: =Campaign_Profile!$D$6 -> BRAND-C | C88: =KOL_Database!$A$28 -> KOL-24 | D88: =KOL_Database!$B$28 -> Rio Saputra | E88: =KOL_Database!$D$28 -> Instagram | F88: =KOL_Database!$E$28 -> Gaming | G88: =IFERROR(INDEX(Matching_Engine!$AY$6:$AY$95,MATCH($B88&"|"&$C88,Matching_Engine!$AZ$6:$AZ$95,0)),0) -> 50 | H88: =IFERROR(INDEX(Matching_Engine!$S$6:$S$95,MATCH($B88&"|"&$C88,Matching_Engine!$AZ$6:$AZ$95,0)),0) -> 71 | I88: =IFERROR(INDEX(Matching_Engine!$W$6:$W$95,MATCH($B88&"|"&$C88,Matching_Engine!$AZ$6:$AZ$95,0)),0) -> 45 | J88: =IFERROR(INDEX(Matching_Engine!$Y$6:$Y$95,MATCH($B88&"|"&$C88,Matching_Engine!$AZ$6:$AZ$95,0)),0) -> 45 | K88: =IFERROR(INDEX(Matching_Engine!$Z$6:$Z$95,MATCH($B88&"|"&$C88,Matching_Engine!$AZ$6:$AZ$95,0)),0) -> 55 | L88: =IFERROR(INDEX(Matching_Engine!$AB$6:$AB$95,MATCH($B88&"|"&$C88,Matching_Engine!$AZ$6:$AZ$95,0)),0) -> 45 | M88: =ROUND($H88*0.3+$I88*0.3+$J88*0.25+$L88*0.15,1) -> 52.8 | N88: =ROUND($G88*0.7+$M88*0.3,1) -> 50.8 | O88: =IF($N88>=85,"Excellent Match",IF($N88>=70,"Strong Match",IF($N88>=55,"Good Match","Weak Match"))) -> Weak Match | P88: ="Brand "&ROUND($G88,0)&"/100; Audience "&ROUND($H88,0)&"/100; Style "&ROUND($I88,0)&"/100; Personality "&ROUND($J88,0)&"/100. Campaign Fit "&ROUND($M88,0)&"/100." -> Brand 50/100; Audience 71/100; Style 45/100; Personality 45/100. Campaign Fit 53/100.
A89: =Campaign_Profile!$D$5 -> CAMP-C | B89: =Campaign_Profile!$D$6 -> BRAND-C | C89: =KOL_Database!$A$29 -> KOL-25 | D89: =KOL_Database!$B$29 -> Denny Kurniawan | E89: =KOL_Database!$D$29 -> TikTok | F89: =KOL_Database!$E$29 -> Automotive | G89: =IFERROR(INDEX(Matching_Engine!$AY$6:$AY$95,MATCH($B89&"|"&$C89,Matching_Engine!$AZ$6:$AZ$95,0)),0) | H89: =IFERROR(INDEX(Matching_Engine!$S$6:$S$95,MATCH($B89&"|"&$C89,Matching_Engine!$AZ$6:$AZ$95,0)),0) -> 77 | I89: =IFERROR(INDEX(Matching_Engine!$W$6:$W$95,MATCH($B89&"|"&$C89,Matching_Engine!$AZ$6:$AZ$95,0)),0) -> 80 | J89: =IFERROR(INDEX(Matching_Engine!$Y$6:$Y$95,MATCH($B89&"|"&$C89,Matching_Engine!$AZ$6:$AZ$95,0)),0) -> 95 | K89: =IFERROR(INDEX(Matching_Engine!$Z$6:$Z$95,MATCH($B89&"|"&$C89,Matching_Engine!$AZ$6:$AZ$95,0)),0) -> 90 | L89: =IFERROR(INDEX(Matching_Engine!$AB$6:$AB$95,MATCH($B89&"|"&$C89,Matching_Engine!$AZ$6:$AZ$95,0)),0) -> 90 | M89: =ROUND($H89*0.3+$I89*0.3+$J89*0.25+$L89*0.15,1) -> 84.4 | N89: =ROUND($G89*0.7+$M89*0.3,1) -> #VALUE! | O89: =IF($N89>=85,"Excellent Match",IF($N89>=70,"Strong Match",IF($N89>=55,"Good Match","Weak Match"))) -> #VALUE! | P89: ="Brand "&ROUND($G89,0)&"/100; Audience "&ROUND($H89,0)&"/100; Style "&ROUND($I89,0)&"/100; Personality "&ROUND($J89,0)&"/100. Campaign Fit "&ROUND($M89,0)&"/100." -> #VALUE!
A90: =Campaign_Profile!$D$5 -> CAMP-C | B90: =Campaign_Profile!$D$6 -> BRAND-C | C90: =KOL_Database!$A$30 -> KOL-26 | D90: =KOL_Database!$B$30 -> Wisnu Adi | E90: =KOL_Database!$D$30 -> Instagram | F90: =KOL_Database!$E$30 -> Automotive | G90: =IFERROR(INDEX(Matching_Engine!$AY$6:$AY$95,MATCH($B90&"|"&$C90,Matching_Engine!$AZ$6:$AZ$95,0)),0) | H90: =IFERROR(INDEX(Matching_Engine!$S$6:$S$95,MATCH($B90&"|"&$C90,Matching_Engine!$AZ$6:$AZ$95,0)),0) -> 75 | I90: =IFERROR(INDEX(Matching_Engine!$W$6:$W$95,MATCH($B90&"|"&$C90,Matching_Engine!$AZ$6:$AZ$95,0)),0) -> 45 | J90: =IFERROR(INDEX(Matching_Engine!$Y$6:$Y$95,MATCH($B90&"|"&$C90,Matching_Engine!$AZ$6:$AZ$95,0)),0) -> 45 | K90: =IFERROR(INDEX(Matching_Engine!$Z$6:$Z$95,MATCH($B90&"|"&$C90,Matching_Engine!$AZ$6:$AZ$95,0)),0) -> 65 | L90: =IFERROR(INDEX(Matching_Engine!$AB$6:$AB$95,MATCH($B90&"|"&$C90,Matching_Engine!$AZ$6:$AZ$95,0)),0) -> 60 | M90: =ROUND($H90*0.3+$I90*0.3+$J90*0.25+$L90*0.15,1) -> 56.3 | N90: =ROUND($G90*0.7+$M90*0.3,1) -> #VALUE! | O90: =IF($N90>=85,"Excellent Match",IF($N90>=70,"Strong Match",IF($N90>=55,"Good Match","Weak Match"))) -> #VALUE! | P90: ="Brand "&ROUND($G90,0)&"/100; Audience "&ROUND($H90,0)&"/100; Style "&ROUND($I90,0)&"/100; Personality "&ROUND($J90,0)&"/100. Campaign Fit "&ROUND($M90,0)&"/100." -> #VALUE!
A91: =Campaign_Profile!$D$5 -> CAMP-C | B91: =Campaign_Profile!$D$6 -> BRAND-C | C91: =KOL_Database!$A$31 -> KOL-27 | D91: =KOL_Database!$B$31 -> Laras Ayu | E91: =KOL_Database!$D$31 -> Instagram | F91: =KOL_Database!$E$31 -> Home & Living | G91: =IFERROR(INDEX(Matching_Engine!$AY$6:$AY$95,MATCH($B91&"|"&$C91,Matching_Engine!$AZ$6:$AZ$95,0)),0) -> 59 | H91: =IFERROR(INDEX(Matching_Engine!$S$6:$S$95,MATCH($B91&"|"&$C91,Matching_Engine!$AZ$6:$AZ$95,0)),0) -> 74 | I91: =IFERROR(INDEX(Matching_Engine!$W$6:$W$95,MATCH($B91&"|"&$C91,Matching_Engine!$AZ$6:$AZ$95,0)),0) -> 45 | J91: =IFERROR(INDEX(Matching_Engine!$Y$6:$Y$95,MATCH($B91&"|"&$C91,Matching_Engine!$AZ$6:$AZ$95,0)),0) -> 35 | K91: =IFERROR(INDEX(Matching_Engine!$Z$6:$Z$95,MATCH($B91&"|"&$C91,Matching_Engine!$AZ$6:$AZ$95,0)),0) -> 65 | L91: =IFERROR(INDEX(Matching_Engine!$AB$6:$AB$95,MATCH($B91&"|"&$C91,Matching_Engine!$AZ$6:$AZ$95,0)),0) -> 70 | M91: =ROUND($H91*0.3+$I91*0.3+$J91*0.25+$L91*0.15,1) -> 55 | N91: =ROUND($G91*0.7+$M91*0.3,1) -> 57.8 | O91: =IF($N91>=85,"Excellent Match",IF($N91>=70,"Strong Match",IF($N91>=55,"Good Match","Weak Match"))) -> Good Match | P91: ="Brand "&ROUND($G91,0)&"/100; Audience "&ROUND($H91,0)&"/100; Style "&ROUND($I91,0)&"/100; Personality "&ROUND($J91,0)&"/100. Campaign Fit "&ROUND($M91,0)&"/100." -> Brand 59/100; Audience 74/100; Style 45/100; Personality 35/100. Campaign Fit 55/100.
A92: =Campaign_Profile!$D$5 -> CAMP-C | B92: =Campaign_Profile!$D$6 -> BRAND-C | C92: =KOL_Database!$A$32 -> KOL-28 | D92: =KOL_Database!$B$32 -> Tiara Nisrina | E92: =KOL_Database!$D$32 -> TikTok | F92: =KOL_Database!$E$32 -> Home & Living | G92: =IFERROR(INDEX(Matching_Engine!$AY$6:$AY$95,MATCH($B92&"|"&$C92,Matching_Engine!$AZ$6:$AZ$95,0)),0) | H92: =IFERROR(INDEX(Matching_Engine!$S$6:$S$95,MATCH($B92&"|"&$C92,Matching_Engine!$AZ$6:$AZ$95,0)),0) -> 68 | I92: =IFERROR(INDEX(Matching_Engine!$W$6:$W$95,MATCH($B92&"|"&$C92,Matching_Engine!$AZ$6:$AZ$95,0)),0) -> 45 | J92: =IFERROR(INDEX(Matching_Engine!$Y$6:$Y$95,MATCH($B92&"|"&$C92,Matching_Engine!$AZ$6:$AZ$95,0)),0) -> 100 | K92: =IFERROR(INDEX(Matching_Engine!$Z$6:$Z$95,MATCH($B92&"|"&$C92,Matching_Engine!$AZ$6:$AZ$95,0)),0) -> 70 | L92: =IFERROR(INDEX(Matching_Engine!$AB$6:$AB$95,MATCH($B92&"|"&$C92,Matching_Engine!$AZ$6:$AZ$95,0)),0) -> 55 | M92: =ROUND($H92*0.3+$I92*0.3+$J92*0.25+$L92*0.15,1) -> 67.2 | N92: =ROUND($G92*0.7+$M92*0.3,1) -> #VALUE! | O92: =IF($N92>=85,"Excellent Match",IF($N92>=70,"Strong Match",IF($N92>=55,"Good Match","Weak Match"))) -> #VALUE! | P92: ="Brand "&ROUND($G92,0)&"/100; Audience "&ROUND($H92,0)&"/100; Style "&ROUND($I92,0)&"/100; Personality "&ROUND($J92,0)&"/100. Campaign Fit "&ROUND($M92,0)&"/100." -> #VALUE!
A93: =Campaign_Profile!$D$5 -> CAMP-C | B93: =Campaign_Profile!$D$6 -> BRAND-C | C93: =KOL_Database!$A$33 -> KOL-29 | D93: =KOL_Database!$B$33 -> Sekar Ayu | E93: =KOL_Database!$D$33 -> TikTok | F93: =KOL_Database!$E$33 -> Beauty | G93: =IFERROR(INDEX(Matching_Engine!$AY$6:$AY$95,MATCH($B93&"|"&$C93,Matching_Engine!$AZ$6:$AZ$95,0)),0) -> 57 | H93: =IFERROR(INDEX(Matching_Engine!$S$6:$S$95,MATCH($B93&"|"&$C93,Matching_Engine!$AZ$6:$AZ$95,0)),0) -> 64 | I93: =IFERROR(INDEX(Matching_Engine!$W$6:$W$95,MATCH($B93&"|"&$C93,Matching_Engine!$AZ$6:$AZ$95,0)),0) -> 45 | J93: =IFERROR(INDEX(Matching_Engine!$Y$6:$Y$95,MATCH($B93&"|"&$C93,Matching_Engine!$AZ$6:$AZ$95,0)),0) -> 100 | K93: =IFERROR(INDEX(Matching_Engine!$Z$6:$Z$95,MATCH($B93&"|"&$C93,Matching_Engine!$AZ$6:$AZ$95,0)),0) -> 65 | L93: =IFERROR(INDEX(Matching_Engine!$AB$6:$AB$95,MATCH($B93&"|"&$C93,Matching_Engine!$AZ$6:$AZ$95,0)),0) -> 60 | M93: =ROUND($H93*0.3+$I93*0.3+$J93*0.25+$L93*0.15,1) -> 66.7 | N93: =ROUND($G93*0.7+$M93*0.3,1) -> 59.9 | O93: =IF($N93>=85,"Excellent Match",IF($N93>=70,"Strong Match",IF($N93>=55,"Good Match","Weak Match"))) -> Good Match | P93: ="Brand "&ROUND($G93,0)&"/100; Audience "&ROUND($H93,0)&"/100; Style "&ROUND($I93,0)&"/100; Personality "&ROUND($J93,0)&"/100. Campaign Fit "&ROUND($M93,0)&"/100." -> Brand 57/100; Audience 64/100; Style 45/100; Personality 100/100. Campaign Fit 67/100.
A94: =Campaign_Profile!$D$5 -> CAMP-C | B94: =Campaign_Profile!$D$6 -> BRAND-C | C94: =KOL_Database!$A$34 -> KOL-30 | D94: =KOL_Database!$B$34 -> Ibnu Faisal | E94: =KOL_Database!$D$34 -> Instagram | F94: =KOL_Database!$E$34 -> Finance | G94: =IFERROR(INDEX(Matching_Engine!$AY$6:$AY$95,MATCH($B94&"|"&$C94,Matching_Engine!$AZ$6:$AZ$95,0)),0) | H94: =IFERROR(INDEX(Matching_Engine!$S$6:$S$95,MATCH($B94&"|"&$C94,Matching_Engine!$AZ$6:$AZ$95,0)),0) -> 68 | I94: =IFERROR(INDEX(Matching_Engine!$W$6:$W$95,MATCH($B94&"|"&$C94,Matching_Engine!$AZ$6:$AZ$95,0)),0) -> 45 | J94: =IFERROR(INDEX(Matching_Engine!$Y$6:$Y$95,MATCH($B94&"|"&$C94,Matching_Engine!$AZ$6:$AZ$95,0)),0) -> 45 | K94: =IFERROR(INDEX(Matching_Engine!$Z$6:$Z$95,MATCH($B94&"|"&$C94,Matching_Engine!$AZ$6:$AZ$95,0)),0) -> 75 | L94: =IFERROR(INDEX(Matching_Engine!$AB$6:$AB$95,MATCH($B94&"|"&$C94,Matching_Engine!$AZ$6:$AZ$95,0)),0) -> 75 | M94: =ROUND($H94*0.3+$I94*0.3+$J94*0.25+$L94*0.15,1) -> 56.4 | N94: =ROUND($G94*0.7+$M94*0.3,1) -> #VALUE! | O94: =IF($N94>=85,"Excellent Match",IF($N94>=70,"Strong Match",IF($N94>=55,"Good Match","Weak Match"))) -> #VALUE! | P94: ="Brand "&ROUND($G94,0)&"/100; Audience "&ROUND($H94,0)&"/100; Style "&ROUND($I94,0)&"/100; Personality "&ROUND($J94,0)&"/100. Campaign Fit "&ROUND($M94,0)&"/100." -> #VALUE!

Sheet Unified_Match
A4: Campaign ID | B4: Brand ID | C4: Campaign | D4: KOL ID | E4: Creator | F4: Platform | G4: Category | H4: Brand Match (70%) | I4: Campaign Fit (30%) | J4: Unified Match | K4: Match Level | L4: Brand Style Fit | M4: Brand Personality Fit | N4: Campaign Style Fit | O4: Campaign Personality Fit | P4: Campaign Objective
A5: =Campaign_Match!$A$5 -> CAMP-A | B5: =Campaign_Match!$B$5 -> BRAND-A | C5: =Campaign_Profile!$B$7 -> Tech Productivity Launch | D5: =Campaign_Match!$C$5 -> KOL-01 | E5: =Campaign_Match!$D$5 -> Ardi Nugraha | F5: =Campaign_Match!$E$5 -> Instagram | G5: =Campaign_Match!$F$5 -> Tech | H5: =Campaign_Match!$G$5 -> 80 | I5: =Campaign_Match!$M$5 -> 80.7 | J5: =Campaign_Match!$N$5 -> 80.2 | K5: =Campaign_Match!$O$5 -> Strong Match | L5: =Campaign_Match!$I$5 -> 80 | M5: =Campaign_Match!$J$5 -> 85 | N5: =Campaign_Match!$I$5 -> 80 | O5: =Campaign_Match!$J$5 -> 85 | P5: =Campaign_Profile!$B$8 -> Awareness
A6: =Campaign_Match!$A$6 -> CAMP-A | B6: =Campaign_Match!$B$6 -> BRAND-A | C6: =Campaign_Profile!$B$7 -> Tech Productivity Launch | D6: =Campaign_Match!$C$6 -> KOL-02 | E6: =Campaign_Match!$D$6 -> Rifqi Pratama | F6: =Campaign_Match!$E$6 -> TikTok | G6: =Campaign_Match!$F$6 -> Tech | H6: =Campaign_Match!$G$6 -> 93 | I6: =Campaign_Match!$M$6 -> 96.1 | J6: =Campaign_Match!$N$6 -> 93.9 | K6: =Campaign_Match!$O$6 -> Excellent Match | L6: =Campaign_Match!$I$6 -> 100 | M6: =Campaign_Match!$J$6 -> 95 | N6: =Campaign_Match!$I$6 -> 100 | O6: =Campaign_Match!$J$6 -> 95 | P6: =Campaign_Profile!$B$8 -> Awareness
A7: =Campaign_Match!$A$7 -> CAMP-A | B7: =Campaign_Match!$B$7 -> BRAND-A | C7: =Campaign_Profile!$B$7 -> Tech Productivity Launch | D7: =Campaign_Match!$C$7 -> KOL-03 | E7: =Campaign_Match!$D$7 -> Salsa Aulia | F7: =Campaign_Match!$E$7 -> Instagram | G7: =Campaign_Match!$F$7 -> Beauty | H7: =Campaign_Match!$G$7 -> 48 | I7: =Campaign_Match!$M$7 -> 73.2 | J7: =Campaign_Match!$N$7 -> 55.6 | K7: =Campaign_Match!$O$7 -> Good Match | L7: =Campaign_Match!$I$7 -> 80 | M7: =Campaign_Match!$J$7 -> 85 | N7: =Campaign_Match!$I$7 -> 80 | O7: =Campaign_Match!$J$7 -> 85 | P7: =Campaign_Profile!$B$8 -> Awareness
A8: =Campaign_Match!$A$8 -> CAMP-A | B8: =Campaign_Match!$B$8 -> BRAND-A | C8: =Campaign_Profile!$B$7 -> Tech Productivity Launch | D8: =Campaign_Match!$C$8 -> KOL-04 | E8: =Campaign_Match!$D$8 -> Nadia Puspa | F8: =Campaign_Match!$E$8 -> TikTok | G8: =Campaign_Match!$F$8 -> Beauty | H8: =Campaign_Match!$G$8 -> 46 | I8: =Campaign_Match!$M$8 -> 76.7 | J8: =Campaign_Match!$N$8 -> 55.2 | K8: =Campaign_Match!$O$8 -> Good Match | L8: =Campaign_Match!$I$8 -> 80 | M8: =Campaign_Match!$J$8 -> 95 | N8: =Campaign_Match!$I$8 -> 80 | O8: =Campaign_Match!$J$8 -> 95 | P8: =Campaign_Profile!$B$8 -> Awareness
A9: =Campaign_Match!$A$9 -> CAMP-A | B9: =Campaign_Match!$B$9 -> BRAND-A | C9: =Campaign_Profile!$B$7 -> Tech Productivity Launch | D9: =Campaign_Match!$C$9 -> KOL-05 | E9: =Campaign_Match!$D$9 -> Bimo Saputra | F9: =Campaign_Match!$E$9 -> TikTok | G9: =Campaign_Match!$F$9 -> Food | H9: =Campaign_Match!$G$9 -> 45 | I9: =Campaign_Match!$M$9 -> 63.2 | J9: =Campaign_Match!$N$9 -> 50.5 | K9: =Campaign_Match!$O$9 -> Weak Match | L9: =Campaign_Match!$I$9 -> 80 | M9: =Campaign_Match!$J$9 -> 50 | N9: =Campaign_Match!$I$9 -> 80 | O9: =Campaign_Match!$J$9 -> 50 | P9: =Campaign_Profile!$B$8 -> Awareness
A10: =Campaign_Match!$A$10 -> CAMP-A | B10: =Campaign_Match!$B$10 -> BRAND-A | C10: =Campaign_Profile!$B$7 -> Tech Productivity Launch | D10: =Campaign_Match!$C$10 -> KOL-06 | E10: =Campaign_Match!$D$10 -> Ayu Lestari | F10: =Campaign_Match!$E$10 -> Instagram | G10: =Campaign_Match!$F$10 -> Food | H10: =Campaign_Match!$G$10 -> 44 | I10: =Campaign_Match!$M$10 -> 65.8 | J10: =Campaign_Match!$N$10 -> 50.5 | K10: =Campaign_Match!$O$10 -> Weak Match | L10: =Campaign_Match!$I$10 -> 80 | M10: =Campaign_Match!$J$10 -> 50 | N10: =Campaign_Match!$I$10 -> 80 | O10: =Campaign_Match!$J$10 -> 50 | P10: =Campaign_Profile!$B$8 -> Awareness
A11: =Campaign_Match!$A$11 -> CAMP-A | B11: =Campaign_Match!$B$11 -> BRAND-A | C11: =Campaign_Profile!$B$7 -> Tech Productivity Launch | D11: =Campaign_Match!$C$11 -> KOL-07 | E11: =Campaign_Match!$D$11 -> Fajar Ramadhan | F11: =Campaign_Match!$E$11 -> Instagram | G11: =Campaign_Match!$F$11 -> Finance | H11: =Campaign_Match!$G$11 -> 87 | I11: =Campaign_Match!$M$11 -> 92.5 | J11: =Campaign_Match!$N$11 -> 88.7 | K11: =Campaign_Match!$O$11 -> Excellent Match | L11: =Campaign_Match!$I$11 -> 100 | M11: =Campaign_Match!$J$11 -> 70 | N11: =Campaign_Match!$I$11 -> 100 | O11: =Campaign_Match!$J$11 -> 70 | P11: =Campaign_Profile!$B$8 -> Awareness
A12: =Campaign_Match!$A$12 -> CAMP-A | B12: =Campaign_Match!$B$12 -> BRAND-A | C12: =Campaign_Profile!$B$7 -> Tech Productivity Launch | D12: =Campaign_Match!$C$12 -> KOL-08 | E12: =Campaign_Match!$D$12 -> Tania Wijaya | F12: =Campaign_Match!$E$12 -> TikTok | G12: =Campaign_Match!$F$12 -> Finance | H12: =Campaign_Match!$G$12 | I12: =Campaign_Match!$M$12 -> 96.4 | J12: =Campaign_Match!$N$12 -> #VALUE! | K12: =Campaign_Match!$O$12 -> #VALUE! | L12: =Campaign_Match!$I$12 -> 100 | M12: =Campaign_Match!$J$12 -> 95 | N12: =Campaign_Match!$I$12 -> 100 | O12: =Campaign_Match!$J$12 -> 95 | P12: =Campaign_Profile!$B$8 -> Awareness
A13: =Campaign_Match!$A$13 -> CAMP-A | B13: =Campaign_Match!$B$13 -> BRAND-A | C13: =Campaign_Profile!$B$7 -> Tech Productivity Launch | D13: =Campaign_Match!$C$13 -> KOL-09 | E13: =Campaign_Match!$D$13 -> Gilang Prakoso | F13: =Campaign_Match!$E$13 -> TikTok | G13: =Campaign_Match!$F$13 -> Education | H13: =Campaign_Match!$G$13 -> 81 | I13: =Campaign_Match!$M$13 -> 93.7 | J13: =Campaign_Match!$N$13 -> 84.8 | K13: =Campaign_Match!$O$13 -> Strong Match | L13: =Campaign_Match!$I$13 -> 100 | M13: =Campaign_Match!$J$13 -> 95 | N13: =Campaign_Match!$I$13 -> 100 | O13: =Campaign_Match!$J$13 -> 95 | P13: =Campaign_Profile!$B$8 -> Awareness
A14: =Campaign_Match!$A$14 -> CAMP-A | B14: =Campaign_Match!$B$14 -> BRAND-A | C14: =Campaign_Profile!$B$7 -> Tech Productivity Launch | D14: =Campaign_Match!$C$14 -> KOL-10 | E14: =Campaign_Match!$D$14 -> Mira Handayani | F14: =Campaign_Match!$E$14 -> Instagram | G14: =Campaign_Match!$F$14 -> Education | H14: =Campaign_Match!$G$14 -> 74 | I14: =Campaign_Match!$M$14 -> 84.2 | J14: =Campaign_Match!$N$14 -> 77.1 | K14: =Campaign_Match!$O$14 -> Strong Match | L14: =Campaign_Match!$I$14 -> 80 | M14: =Campaign_Match!$J$14 -> 95 | N14: =Campaign_Match!$I$14 -> 80 | O14: =Campaign_Match!$J$14 -> 95 | P14: =Campaign_Profile!$B$8 -> Awareness
A15: =Campaign_Match!$A$15 -> CAMP-A | B15: =Campaign_Match!$B$15 -> BRAND-A | C15: =Campaign_Profile!$B$7 -> Tech Productivity Launch | D15: =Campaign_Match!$C$15 -> KOL-11 | E15: =Campaign_Match!$D$15 -> Dimas Anggara | F15: =Campaign_Match!$E$15 -> Instagram | G15: =Campaign_Match!$F$15 -> Fitness | H15: =Campaign_Match!$G$15 | I15: =Campaign_Match!$M$15 -> 70.9 | J15: =Campaign_Match!$N$15 -> #VALUE! | K15: =Campaign_Match!$O$15 -> #VALUE! | L15: =Campaign_Match!$I$15 -> 80 | M15: =Campaign_Match!$J$15 -> 70 | N15: =Campaign_Match!$I$15 -> 80 | O15: =Campaign_Match!$J$15 -> 70 | P15: =Campaign_Profile!$B$8 -> Awareness
A16: =Campaign_Match!$A$16 -> CAMP-A | B16: =Campaign_Match!$B$16 -> BRAND-A | C16: =Campaign_Profile!$B$7 -> Tech Productivity Launch | D16: =Campaign_Match!$C$16 -> KOL-12 | E16: =Campaign_Match!$D$16 -> Rani Kusuma | F16: =Campaign_Match!$E$16 -> TikTok | G16: =Campaign_Match!$F$16 -> Fitness | H16: =Campaign_Match!$G$16 -> 48 | I16: =Campaign_Match!$M$16 -> 70.5 | J16: =Campaign_Match!$N$16 -> 54.8 | K16: =Campaign_Match!$O$16 -> Weak Match | L16: =Campaign_Match!$I$16 -> 80 | M16: =Campaign_Match!$J$16 -> 70 | N16: =Campaign_Match!$I$16 -> 80 | O16: =Campaign_Match!$J$16 -> 70 | P16: =Campaign_Profile!$B$8 -> Awareness
A17: =Campaign_Match!$A$17 -> CAMP-A | B17: =Campaign_Match!$B$17 -> BRAND-A | C17: =Campaign_Profile!$B$7 -> Tech Productivity Launch | D17: =Campaign_Match!$C$17 -> KOL-13 | E17: =Campaign_Match!$D$17 -> Kevin Halim | F17: =Campaign_Match!$E$17 -> Instagram | G17: =Campaign_Match!$F$17 -> Fashion | H17: =Campaign_Match!$G$17 -> 45 | I17: =Campaign_Match!$M$17 -> 61.4 | J17: =Campaign_Match!$N$17 -> 49.9 | K17: =Campaign_Match!$O$17 -> Weak Match | L17: =Campaign_Match!$I$17 -> 45 | M17: =Campaign_Match!$J$17 -> 95 | N17: =Campaign_Match!$I$17 -> 45 | O17: =Campaign_Match!$J$17 -> 95 | P17: =Campaign_Profile!$B$8 -> Awareness
A18: =Campaign_Match!$A$18 -> CAMP-A | B18: =Campaign_Match!$B$18 -> BRAND-A | C18: =Campaign_Profile!$B$7 -> Tech Productivity Launch | D18: =Campaign_Match!$C$18 -> KOL-14 | E18: =Campaign_Match!$D$18 -> Zahra Amelia | F18: =Campaign_Match!$E$18 -> Instagram | G18: =Campaign_Match!$F$18 -> Fashion | H18: =Campaign_Match!$G$18 | I18: =Campaign_Match!$M$18 -> 50 | J18: =Campaign_Match!$N$18 -> #VALUE! | K18: =Campaign_Match!$O$18 -> #VALUE! | L18: =Campaign_Match!$I$18 -> 45 | M18: =Campaign_Match!$J$18 -> 60 | N18: =Campaign_Match!$I$18 -> 45 | O18: =Campaign_Match!$J$18 -> 60 | P18: =Campaign_Profile!$B$8 -> Awareness
A19: =Campaign_Match!$A$19 -> CAMP-A | B19: =Campaign_Match!$B$19 -> BRAND-A | C19: =Campaign_Profile!$B$7 -> Tech Productivity Launch | D19: =Campaign_Match!$C$19 -> KOL-15 | E19: =Campaign_Match!$D$19 -> Andini Rahma | F19: =Campaign_Match!$E$19 -> Instagram | G19: =Campaign_Match!$F$19 -> Lifestyle | H19: =Campaign_Match!$G$19 -> 48 | I19: =Campaign_Match!$M$19 -> 50.9 | J19: =Campaign_Match!$N$19 -> 48.9 | K19: =Campaign_Match!$O$19 -> Weak Match | L19: =Campaign_Match!$I$19 -> 45 | M19: =Campaign_Match!$J$19 -> 50 | N19: =Campaign_Match!$I$19 -> 45 | O19: =Campaign_Match!$J$19 -> 50 | P19: =Campaign_Profile!$B$8 -> Awareness
A20: =Campaign_Match!$A$20 -> CAMP-A | B20: =Campaign_Match!$B$20 -> BRAND-A | C20: =Campaign_Profile!$B$7 -> Tech Productivity Launch | D20: =Campaign_Match!$C$20 -> KOL-16 | E20: =Campaign_Match!$D$20 -> Yoga Pratama | F20: =Campaign_Match!$E$20 -> TikTok | G20: =Campaign_Match!$F$20 -> Lifestyle | H20: =Campaign_Match!$G$20 -> 67 | I20: =Campaign_Match!$M$20 -> 64.9 | J20: =Campaign_Match!$N$20 -> 66.4 | K20: =Campaign_Match!$O$20 -> Good Match | L20: =Campaign_Match!$I$20 -> 45 | M20: =Campaign_Match!$J$20 -> 70 | N20: =Campaign_Match!$I$20 -> 45 | O20: =Campaign_Match!$J$20 -> 70 | P20: =Campaign_Profile!$B$8 -> Awareness
A21: =Campaign_Match!$A$21 -> CAMP-A | B21: =Campaign_Match!$B$21 -> BRAND-A | C21: =Campaign_Profile!$B$7 -> Tech Productivity Launch | D21: =Campaign_Match!$C$21 -> KOL-17 | E21: =Campaign_Match!$D$21 -> Sinta Maharani | F21: =Campaign_Match!$E$21 -> Instagram | G21: =Campaign_Match!$F$21 -> Travel | H21: =Campaign_Match!$G$21 -> 42 | I21: =Campaign_Match!$M$21 -> 50 | J21: =Campaign_Match!$N$21 -> 44.4 | K21: =Campaign_Match!$O$21 -> Weak Match | L21: =Campaign_Match!$I$21 -> 45 | M21: =Campaign_Match!$J$21 -> 60 | N21: =Campaign_Match!$I$21 -> 45 | O21: =Campaign_Match!$J$21 -> 60 | P21: =Campaign_Profile!$B$8 -> Awareness
A22: =Campaign_Match!$A$22 -> CAMP-A | B22: =Campaign_Match!$B$22 -> BRAND-A | C22: =Campaign_Profile!$B$7 -> Tech Productivity Launch | D22: =Campaign_Match!$C$22 -> KOL-18 | E22: =Campaign_Match!$D$22 -> Reza Fadillah | F22: =Campaign_Match!$E$22 -> TikTok | G22: =Campaign_Match!$F$22 -> Travel | H22: =Campaign_Match!$G$22 -> 48 | I22: =Campaign_Match!$M$22 -> 48.1 | J22: =Campaign_Match!$N$22 -> 48 | K22: =Campaign_Match!$O$22 -> Weak Match | L22: =Campaign_Match!$I$22 -> 45 | M22: =Campaign_Match!$J$22 -> 40 | N22: =Campaign_Match!$I$22 -> 45 | O22: =Campaign_Match!$J$22 -> 40 | P22: =Campaign_Profile!$B$8 -> Awareness
A23: =Campaign_Match!$A$23 -> CAMP-A | B23: =Campaign_Match!$B$23 -> BRAND-A | C23: =Campaign_Profile!$B$7 -> Tech Productivity Launch | D23: =Campaign_Match!$C$23 -> KOL-19 | E23: =Campaign_Match!$D$23 -> Putri Amanda | F23: =Campaign_Match!$E$23 -> Instagram | G23: =Campaign_Match!$F$23 -> Parenting | H23: =Campaign_Match!$G$23 -> 41 | I23: =Campaign_Match!$M$23 -> 49.7 | J23: =Campaign_Match!$N$23 -> 43.6 | K23: =Campaign_Match!$O$23 -> Weak Match | L23: =Campaign_Match!$I$23 -> 45 | M23: =Campaign_Match!$J$23 -> 50 | N23: =Campaign_Match!$I$23 -> 45 | O23: =Campaign_Match!$J$23 -> 50 | P23: =Campaign_Profile!$B$8 -> Awareness
A24: =Campaign_Match!$A$24 -> CAMP-A | B24: =Campaign_Match!$B$24 -> BRAND-A | C24: =Campaign_Profile!$B$7 -> Tech Productivity Launch | D24: =Campaign_Match!$C$24 -> KOL-20 | E24: =Campaign_Match!$D$24 -> Hendra Wijoyo | F24: =Campaign_Match!$E$24 -> TikTok | G24: =Campaign_Match!$F$24 -> Parenting | H24: =Campaign_Match!$G$24 -> 45 | I24: =Campaign_Match!$M$24 -> 44.1 | J24: =Campaign_Match!$N$24 -> 44.7 | K24: =Campaign_Match!$O$24 -> Weak Match | L24: =Campaign_Match!$I$24 -> 45 | M24: =Campaign_Match!$J$24 -> 30 | N24: =Campaign_Match!$I$24 -> 45 | O24: =Campaign_Match!$J$24 -> 30 | P24: =Campaign_Profile!$B$8 -> Awareness
A25: =Campaign_Match!$A$25 -> CAMP-A | B25: =Campaign_Match!$B$25 -> BRAND-A | C25: =Campaign_Profile!$B$7 -> Tech Productivity Launch | D25: =Campaign_Match!$C$25 -> KOL-21 | E25: =Campaign_Match!$D$25 -> Bagas Setiawan | F25: =Campaign_Match!$E$25 -> TikTok | G25: =Campaign_Match!$F$25 -> Entertainment | H25: =Campaign_Match!$G$25 | I25: =Campaign_Match!$M$25 -> 40.2 | J25: =Campaign_Match!$N$25 -> #VALUE! | K25: =Campaign_Match!$O$25 -> #VALUE! | L25: =Campaign_Match!$I$25 -> 45 | M25: =Campaign_Match!$J$25 -> 30 | N25: =Campaign_Match!$I$25 -> 45 | O25: =Campaign_Match!$J$25 -> 30 | P25: =Campaign_Profile!$B$8 -> Awareness
A26: =Campaign_Match!$A$26 -> CAMP-A | B26: =Campaign_Match!$B$26 -> BRAND-A | C26: =Campaign_Profile!$B$7 -> Tech Productivity Launch | D26: =Campaign_Match!$C$26 -> KOL-22 | E26: =Campaign_Match!$D$26 -> Nabila Kirana | F26: =Campaign_Match!$E$26 -> Instagram | G26: =Campaign_Match!$F$26 -> Entertainment | H26: =Campaign_Match!$G$26 | I26: =Campaign_Match!$M$26 -> 60.2 | J26: =Campaign_Match!$N$26 -> #VALUE! | K26: =Campaign_Match!$O$26 -> #VALUE! | L26: =Campaign_Match!$I$26 -> 45 | M26: =Campaign_Match!$J$26 -> 95 | N26: =Campaign_Match!$I$26 -> 45 | O26: =Campaign_Match!$J$26 -> 95 | P26: =Campaign_Profile!$B$8 -> Awareness
A27: =Campaign_Match!$A$27 -> CAMP-A | B27: =Campaign_Match!$B$27 -> BRAND-A | C27: =Campaign_Profile!$B$7 -> Tech Productivity Launch | D27: =Campaign_Match!$C$27 -> KOL-23 | E27: =Campaign_Match!$D$27 -> Arya Mahendra | F27: =Campaign_Match!$E$27 -> TikTok | G27: =Campaign_Match!$F$27 -> Gaming | H27: =Campaign_Match!$G$27 -> 57 | I27: =Campaign_Match!$M$27 -> 47.9 | J27: =Campaign_Match!$N$27 -> 54.3 | K27: =Campaign_Match!$O$27 -> Weak Match | L27: =Campaign_Match!$I$27 -> 45 | M27: =Campaign_Match!$J$27 -> 45 | N27: =Campaign_Match!$I$27 -> 45 | O27: =Campaign_Match!$J$27 -> 45 | P27: =Campaign_Profile!$B$8 -> Awareness
A28: =Campaign_Match!$A$28 -> CAMP-A | B28: =Campaign_Match!$B$28 -> BRAND-A | C28: =Campaign_Profile!$B$7 -> Tech Productivity Launch | D28: =Campaign_Match!$C$28 -> KOL-24 | E28: =Campaign_Match!$D$28 -> Rio Saputra | F28: =Campaign_Match!$E$28 -> Instagram | G28: =Campaign_Match!$F$28 -> Gaming | H28: =Campaign_Match!$G$28 -> 66 | I28: =Campaign_Match!$M$28 -> 81.4 | J28: =Campaign_Match!$N$28 -> 70.6 | K28: =Campaign_Match!$O$28 -> Strong Match | L28: =Campaign_Match!$I$28 -> 80 | M28: =Campaign_Match!$J$28 -> 100 | N28: =Campaign_Match!$I$28 -> 80 | O28: =Campaign_Match!$J$28 -> 100 | P28: =Campaign_Profile!$B$8 -> Awareness
A29: =Campaign_Match!$A$29 -> CAMP-A | B29: =Campaign_Match!$B$29 -> BRAND-A | C29: =Campaign_Profile!$B$7 -> Tech Productivity Launch | D29: =Campaign_Match!$C$29 -> KOL-25 | E29: =Campaign_Match!$D$29 -> Denny Kurniawan | F29: =Campaign_Match!$E$29 -> TikTok | G29: =Campaign_Match!$F$29 -> Automotive | H29: =Campaign_Match!$G$29 -> 54 | I29: =Campaign_Match!$M$29 -> 48.1 | J29: =Campaign_Match!$N$29 -> 52.2 | K29: =Campaign_Match!$O$29 -> Weak Match | L29: =Campaign_Match!$I$29 -> 45 | M29: =Campaign_Match!$J$29 -> 40 | N29: =Campaign_Match!$I$29 -> 45 | O29: =Campaign_Match!$J$29 -> 40 | P29: =Campaign_Profile!$B$8 -> Awareness
A30: =Campaign_Match!$A$30 -> CAMP-A | B30: =Campaign_Match!$B$30 -> BRAND-A | C30: =Campaign_Profile!$B$7 -> Tech Productivity Launch | D30: =Campaign_Match!$C$30 -> KOL-26 | E30: =Campaign_Match!$D$30 -> Wisnu Adi | F30: =Campaign_Match!$E$30 -> Instagram | G30: =Campaign_Match!$F$30 -> Automotive | H30: =Campaign_Match!$G$30 | I30: =Campaign_Match!$M$30 -> 76.9 | J30: =Campaign_Match!$N$30 -> #VALUE! | K30: =Campaign_Match!$O$30 -> #VALUE! | L30: =Campaign_Match!$I$30 -> 80 | M30: =Campaign_Match!$J$30 -> 70 | N30: =Campaign_Match!$I$30 -> 80 | O30: =Campaign_Match!$J$30 -> 70 | P30: =Campaign_Profile!$B$8 -> Awareness
A31: =Campaign_Match!$A$31 -> CAMP-A | B31: =Campaign_Match!$B$31 -> BRAND-A | C31: =Campaign_Profile!$B$7 -> Tech Productivity Launch | D31: =Campaign_Match!$C$31 -> KOL-27 | E31: =Campaign_Match!$D$31 -> Laras Ayu | F31: =Campaign_Match!$E$31 -> Instagram | G31: =Campaign_Match!$F$31 -> Home & Living | H31: =Campaign_Match!$G$31 -> 42 | I31: =Campaign_Match!$M$31 -> 50 | J31: =Campaign_Match!$N$31 -> 44.4 | K31: =Campaign_Match!$O$31 -> Weak Match | L31: =Campaign_Match!$I$31 -> 45 | M31: =Campaign_Match!$J$31 -> 60 | N31: =Campaign_Match!$I$31 -> 45 | O31: =Campaign_Match!$J$31 -> 60 | P31: =Campaign_Profile!$B$8 -> Awareness
A32: =Campaign_Match!$A$32 -> CAMP-A | B32: =Campaign_Match!$B$32 -> BRAND-A | C32: =Campaign_Profile!$B$7 -> Tech Productivity Launch | D32: =Campaign_Match!$C$32 -> KOL-28 | E32: =Campaign_Match!$D$32 -> Tiara Nisrina | F32: =Campaign_Match!$E$32 -> TikTok | G32: =Campaign_Match!$F$32 -> Home & Living | H32: =Campaign_Match!$G$32 -> 55 | I32: =Campaign_Match!$M$32 -> 70.6 | J32: =Campaign_Match!$N$32 -> 59.7 | K32: =Campaign_Match!$O$32 -> Good Match | L32: =Campaign_Match!$I$32 -> 80 | M32: =Campaign_Match!$J$32 -> 50 | N32: =Campaign_Match!$I$32 -> 80 | O32: =Campaign_Match!$J$32 -> 50 | P32: =Campaign_Profile!$B$8 -> Awareness
A33: =Campaign_Match!$A$33 -> CAMP-A | B33: =Campaign_Match!$B$33 -> BRAND-A | C33: =Campaign_Profile!$B$7 -> Tech Productivity Launch | D33: =Campaign_Match!$C$33 -> KOL-29 | E33: =Campaign_Match!$D$33 -> Sekar Ayu | F33: =Campaign_Match!$E$33 -> TikTok | G33: =Campaign_Match!$F$33 -> Beauty | H33: =Campaign_Match!$G$33 -> 47 | I33: =Campaign_Match!$M$33 -> 61.7 | J33: =Campaign_Match!$N$33 -> 51.4 | K33: =Campaign_Match!$O$33 -> Weak Match | L33: =Campaign_Match!$I$33 -> 80 | M33: =Campaign_Match!$J$33 -> 50 | N33: =Campaign_Match!$I$33 -> 80 | O33: =Campaign_Match!$J$33 -> 50 | P33: =Campaign_Profile!$B$8 -> Awareness
A34: =Campaign_Match!$A$34 -> CAMP-A | B34: =Campaign_Match!$B$34 -> BRAND-A | C34: =Campaign_Profile!$B$7 -> Tech Productivity Launch | D34: =Campaign_Match!$C$34 -> KOL-30 | E34: =Campaign_Match!$D$34 -> Ibnu Faisal | F34: =Campaign_Match!$E$34 -> Instagram | G34: =Campaign_Match!$F$34 -> Finance | H34: =Campaign_Match!$G$34 -> 82 | I34: =Campaign_Match!$M$34 -> 82.5 | J34: =Campaign_Match!$N$34 -> 82.2 | K34: =Campaign_Match!$O$34 -> Strong Match | L34: =Campaign_Match!$I$34 -> 80 | M34: =Campaign_Match!$J$34 -> 70 | N34: =Campaign_Match!$I$34 -> 80 | O34: =Campaign_Match!$J$34 -> 70 | P34: =Campaign_Profile!$B$8 -> Awareness
A35: =Campaign_Match!$A$35 -> CAMP-B | B35: =Campaign_Match!$B$35 -> BRAND-B | C35: =Campaign_Profile!$C$7 -> Glow Up Routine | D35: =Campaign_Match!$C$35 -> KOL-01 | E35: =Campaign_Match!$D$35 -> Ardi Nugraha | F35: =Campaign_Match!$E$35 -> Instagram | G35: =Campaign_Match!$F$35 -> Tech | H35: =Campaign_Match!$G$35 | I35: =Campaign_Match!$M$35 -> 81.5 | J35: =Campaign_Match!$N$35 -> #VALUE! | K35: =Campaign_Match!$O$35 -> #VALUE! | L35: =Campaign_Match!$I$35 -> 100 | M35: =Campaign_Match!$J$35 -> 95 | N35: =Campaign_Match!$I$35 -> 100 | O35: =Campaign_Match!$J$35 -> 95 | P35: =Campaign_Profile!$C$8 -> Engagement
A36: =Campaign_Match!$A$36 -> CAMP-B | B36: =Campaign_Match!$B$36 -> BRAND-B | C36: =Campaign_Profile!$C$7 -> Glow Up Routine | D36: =Campaign_Match!$C$36 -> KOL-02 | E36: =Campaign_Match!$D$36 -> Rifqi Pratama | F36: =Campaign_Match!$E$36 -> TikTok | G36: =Campaign_Match!$F$36 -> Tech | H36: =Campaign_Match!$G$36 -> 45 | I36: =Campaign_Match!$M$36 -> 61.9 | J36: =Campaign_Match!$N$36 -> 50.1 | K36: =Campaign_Match!$O$36 -> Weak Match | L36: =Campaign_Match!$I$36 -> 80 | M36: =Campaign_Match!$J$36 -> 55 | N36: =Campaign_Match!$I$36 -> 80 | O36: =Campaign_Match!$J$36 -> 55 | P36: =Campaign_Profile!$C$8 -> Engagement
A37: =Campaign_Match!$A$37 -> CAMP-B | B37: =Campaign_Match!$B$37 -> BRAND-B | C37: =Campaign_Profile!$C$7 -> Glow Up Routine | D37: =Campaign_Match!$C$37 -> KOL-03 | E37: =Campaign_Match!$D$37 -> Salsa Aulia | F37: =Campaign_Match!$E$37 -> Instagram | G37: =Campaign_Match!$F$37 -> Beauty | H37: =Campaign_Match!$G$37 | I37: =Campaign_Match!$M$37 -> 92 | J37: =Campaign_Match!$N$37 -> #VALUE! | K37: =Campaign_Match!$O$37 -> #VALUE! | L37: =Campaign_Match!$I$37 -> 100 | M37: =Campaign_Match!$J$37 -> 95 | N37: =Campaign_Match!$I$37 -> 100 | O37: =Campaign_Match!$J$37 -> 95 | P37: =Campaign_Profile!$C$8 -> Engagement
A38: =Campaign_Match!$A$38 -> CAMP-B | B38: =Campaign_Match!$B$38 -> BRAND-B | C38: =Campaign_Profile!$C$7 -> Glow Up Routine | D38: =Campaign_Match!$C$38 -> KOL-04 | E38: =Campaign_Match!$D$38 -> Nadia Puspa | F38: =Campaign_Match!$E$38 -> TikTok | G38: =Campaign_Match!$F$38 -> Beauty | H38: =Campaign_Match!$G$38 | I38: =Campaign_Match!$M$38 -> 77.8 | J38: =Campaign_Match!$N$38 -> #VALUE! | K38: =Campaign_Match!$O$38 -> #VALUE! | L38: =Campaign_Match!$I$38 -> 80 | M38: =Campaign_Match!$J$38 -> 65 | N38: =Campaign_Match!$I$38 -> 80 | O38: =Campaign_Match!$J$38 -> 65 | P38: =Campaign_Profile!$C$8 -> Engagement
A39: =Campaign_Match!$A$39 -> CAMP-B | B39: =Campaign_Match!$B$39 -> BRAND-B | C39: =Campaign_Profile!$C$7 -> Glow Up Routine | D39: =Campaign_Match!$C$39 -> KOL-05 | E39: =Campaign_Match!$D$39 -> Bimo Saputra | F39: =Campaign_Match!$E$39 -> TikTok | G39: =Campaign_Match!$F$39 -> Food | H39: =Campaign_Match!$G$39 | I39: =Campaign_Match!$M$39 -> 70.1 | J39: =Campaign_Match!$N$39 -> #VALUE! | K39: =Campaign_Match!$O$39 -> #VALUE! | L39: =Campaign_Match!$I$39 -> 100 | M39: =Campaign_Match!$J$39 -> 35 | N39: =Campaign_Match!$I$39 -> 100 | O39: =Campaign_Match!$J$39 -> 35 | P39: =Campaign_Profile!$C$8 -> Engagement
A40: =Campaign_Match!$A$40 -> CAMP-B | B40: =Campaign_Match!$B$40 -> BRAND-B | C40: =Campaign_Profile!$C$7 -> Glow Up Routine | D40: =Campaign_Match!$C$40 -> KOL-06 | E40: =Campaign_Match!$D$40 -> Ayu Lestari | F40: =Campaign_Match!$E$40 -> Instagram | G40: =Campaign_Match!$F$40 -> Food | H40: =Campaign_Match!$G$40 -> 56 | I40: =Campaign_Match!$M$40 -> 64 | J40: =Campaign_Match!$N$40 -> 58.4 | K40: =Campaign_Match!$O$40 -> Good Match | L40: =Campaign_Match!$I$40 -> 80 | M40: =Campaign_Match!$J$40 -> 35 | N40: =Campaign_Match!$I$40 -> 80 | O40: =Campaign_Match!$J$40 -> 35 | P40: =Campaign_Profile!$C$8 -> Engagement
A41: =Campaign_Match!$A$41 -> CAMP-B | B41: =Campaign_Match!$B$41 -> BRAND-B | C41: =Campaign_Profile!$C$7 -> Glow Up Routine | D41: =Campaign_Match!$C$41 -> KOL-07 | E41: =Campaign_Match!$D$41 -> Fajar Ramadhan | F41: =Campaign_Match!$E$41 -> Instagram | G41: =Campaign_Match!$F$41 -> Finance | H41: =Campaign_Match!$G$41 | I41: =Campaign_Match!$M$41 -> 70 | J41: =Campaign_Match!$N$41 -> #VALUE! | K41: =Campaign_Match!$O$41 -> #VALUE! | L41: =Campaign_Match!$I$41 -> 80 | M41: =Campaign_Match!$J$41 -> 85 | N41: =Campaign_Match!$I$41 -> 80 | O41: =Campaign_Match!$J$41 -> 85 | P41: =Campaign_Profile!$C$8 -> Engagement
A42: =Campaign_Match!$A$42 -> CAMP-B | B42: =Campaign_Match!$B$42 -> BRAND-B | C42: =Campaign_Profile!$C$7 -> Glow Up Routine | D42: =Campaign_Match!$C$42 -> KOL-08 | E42: =Campaign_Match!$D$42 -> Tania Wijaya | F42: =Campaign_Match!$E$42 -> TikTok | G42: =Campaign_Match!$F$42 -> Finance | H42: =Campaign_Match!$G$42 | I42: =Campaign_Match!$M$42 -> 69.7 | J42: =Campaign_Match!$N$42 -> #VALUE! | K42: =Campaign_Match!$O$42 -> #VALUE! | L42: =Campaign_Match!$I$42 -> 80 | M42: =Campaign_Match!$J$42 -> 55 | N42: =Campaign_Match!$I$42 -> 80 | O42: =Campaign_Match!$J$42 -> 55 | P42: =Campaign_Profile!$C$8 -> Engagement
A43: =Campaign_Match!$A$43 -> CAMP-B | B43: =Campaign_Match!$B$43 -> BRAND-B | C43: =Campaign_Profile!$C$7 -> Glow Up Routine | D43: =Campaign_Match!$C$43 -> KOL-09 | E43: =Campaign_Match!$D$43 -> Gilang Prakoso | F43: =Campaign_Match!$E$43 -> TikTok | G43: =Campaign_Match!$F$43 -> Education | H43: =Campaign_Match!$G$43 | I43: =Campaign_Match!$M$43 -> 64.9 | J43: =Campaign_Match!$N$43 -> #VALUE! | K43: =Campaign_Match!$O$43 -> #VALUE! | L43: =Campaign_Match!$I$43 -> 80 | M43: =Campaign_Match!$J$43 -> 55 | N43: =Campaign_Match!$I$43 -> 80 | O43: =Campaign_Match!$J$43 -> 55 | P43: =Campaign_Profile!$C$8 -> Engagement
A44: =Campaign_Match!$A$44 -> CAMP-B | B44: =Campaign_Match!$B$44 -> BRAND-B | C44: =Campaign_Profile!$C$7 -> Glow Up Routine | D44: =Campaign_Match!$C$44 -> KOL-10 | E44: =Campaign_Match!$D$44 -> Mira Handayani | F44: =Campaign_Match!$E$44 -> Instagram | G44: =Campaign_Match!$F$44 -> Education | H44: =Campaign_Match!$G$44 -> 50 | I44: =Campaign_Match!$M$44 -> 69 | J44: =Campaign_Match!$N$44 -> 55.7 | K44: =Campaign_Match!$O$44 -> Good Match | L44: =Campaign_Match!$I$44 -> 80 | M44: =Campaign_Match!$J$44 -> 55 | N44: =Campaign_Match!$I$44 -> 80 | O44: =Campaign_Match!$J$44 -> 55 | P44: =Campaign_Profile!$C$8 -> Engagement
A45: =Campaign_Match!$A$45 -> CAMP-B | B45: =Campaign_Match!$B$45 -> BRAND-B | C45: =Campaign_Profile!$C$7 -> Glow Up Routine | D45: =Campaign_Match!$C$45 -> KOL-11 | E45: =Campaign_Match!$D$45 -> Dimas Anggara | F45: =Campaign_Match!$E$45 -> Instagram | G45: =Campaign_Match!$F$45 -> Fitness | H45: =Campaign_Match!$G$45 | I45: =Campaign_Match!$M$45 -> 77.2 | J45: =Campaign_Match!$N$45 -> #VALUE! | K45: =Campaign_Match!$O$45 -> #VALUE! | L45: =Campaign_Match!$I$45 -> 80 | M45: =Campaign_Match!$J$45 -> 85 | N45: =Campaign_Match!$I$45 -> 80 | O45: =Campaign_Match!$J$45 -> 85 | P45: =Campaign_Profile!$C$8 -> Engagement
A46: =Campaign_Match!$A$46 -> CAMP-B | B46: =Campaign_Match!$B$46 -> BRAND-B | C46: =Campaign_Profile!$C$7 -> Glow Up Routine | D46: =Campaign_Match!$C$46 -> KOL-12 | E46: =Campaign_Match!$D$46 -> Rani Kusuma | F46: =Campaign_Match!$E$46 -> TikTok | G46: =Campaign_Match!$F$46 -> Fitness | H46: =Campaign_Match!$G$46 | I46: =Campaign_Match!$M$46 -> 73 | J46: =Campaign_Match!$N$46 -> #VALUE! | K46: =Campaign_Match!$O$46 -> #VALUE! | L46: =Campaign_Match!$I$46 -> 80 | M46: =Campaign_Match!$J$46 -> 65 | N46: =Campaign_Match!$I$46 -> 80 | O46: =Campaign_Match!$J$46 -> 65 | P46: =Campaign_Profile!$C$8 -> Engagement
A47: =Campaign_Match!$A$47 -> CAMP-B | B47: =Campaign_Match!$B$47 -> BRAND-B | C47: =Campaign_Profile!$C$7 -> Glow Up Routine | D47: =Campaign_Match!$C$47 -> KOL-13 | E47: =Campaign_Match!$D$47 -> Kevin Halim | F47: =Campaign_Match!$E$47 -> Instagram | G47: =Campaign_Match!$F$47 -> Fashion | H47: =Campaign_Match!$G$47 -> 69 | I47: =Campaign_Match!$M$47 -> 67.6 | J47: =Campaign_Match!$N$47 -> 68.6 | K47: =Campaign_Match!$O$47 -> Good Match | L47: =Campaign_Match!$I$47 -> 45 | M47: =Campaign_Match!$J$47 -> 65 | N47: =Campaign_Match!$I$47 -> 45 | O47: =Campaign_Match!$J$47 -> 65 | P47: =Campaign_Profile!$C$8 -> Engagement
A48: =Campaign_Match!$A$48 -> CAMP-B | B48: =Campaign_Match!$B$48 -> BRAND-B | C48: =Campaign_Profile!$C$7 -> Glow Up Routine | D48: =Campaign_Match!$C$48 -> KOL-14 | E48: =Campaign_Match!$D$48 -> Zahra Amelia | F48: =Campaign_Match!$E$48 -> Instagram | G48: =Campaign_Match!$F$48 -> Fashion | H48: =Campaign_Match!$G$48 | I48: =Campaign_Match!$M$48 -> 80.5 | J48: =Campaign_Match!$N$48 -> #VALUE! | K48: =Campaign_Match!$O$48 -> #VALUE! | L48: =Campaign_Match!$I$48 -> 45 | M48: =Campaign_Match!$J$48 -> 100 | N48: =Campaign_Match!$I$48 -> 45 | O48: =Campaign_Match!$J$48 -> 100 | P48: =Campaign_Profile!$C$8 -> Engagement
A49: =Campaign_Match!$A$49 -> CAMP-B | B49: =Campaign_Match!$B$49 -> BRAND-B | C49: =Campaign_Profile!$C$7 -> Glow Up Routine | D49: =Campaign_Match!$C$49 -> KOL-15 | E49: =Campaign_Match!$D$49 -> Andini Rahma | F49: =Campaign_Match!$E$49 -> Instagram | G49: =Campaign_Match!$F$49 -> Lifestyle | H49: =Campaign_Match!$G$49 -> 71 | I49: =Campaign_Match!$M$49 -> 62 | J49: =Campaign_Match!$N$49 -> 68.3 | K49: =Campaign_Match!$O$49 -> Good Match | L49: =Campaign_Match!$I$49 -> 45 | M49: =Campaign_Match!$J$49 -> 35 | N49: =Campaign_Match!$I$49 -> 45 | O49: =Campaign_Match!$J$49 -> 35 | P49: =Campaign_Profile!$C$8 -> Engagement
A50: =Campaign_Match!$A$50 -> CAMP-B | B50: =Campaign_Match!$B$50 -> BRAND-B | C50: =Campaign_Profile!$C$7 -> Glow Up Routine | D50: =Campaign_Match!$C$50 -> KOL-16 | E50: =Campaign_Match!$D$50 -> Yoga Pratama | F50: =Campaign_Match!$E$50 -> TikTok | G50: =Campaign_Match!$F$50 -> Lifestyle | H50: =Campaign_Match!$G$50 | I50: =Campaign_Match!$M$50 -> 59.2 | J50: =Campaign_Match!$N$50 -> #VALUE! | K50: =Campaign_Match!$O$50 -> #VALUE! | L50: =Campaign_Match!$I$50 -> 45 | M50: =Campaign_Match!$J$50 -> 65 | N50: =Campaign_Match!$I$50 -> 45 | O50: =Campaign_Match!$J$50 -> 65 | P50: =Campaign_Profile!$C$8 -> Engagement
A51: =Campaign_Match!$A$51 -> CAMP-B | B51: =Campaign_Match!$B$51 -> BRAND-B | C51: =Campaign_Profile!$C$7 -> Glow Up Routine | D51: =Campaign_Match!$C$51 -> KOL-17 | E51: =Campaign_Match!$D$51 -> Sinta Maharani | F51: =Campaign_Match!$E$51 -> Instagram | G51: =Campaign_Match!$F$51 -> Travel | H51: =Campaign_Match!$G$51 | I51: =Campaign_Match!$M$51 -> 77.2 | J51: =Campaign_Match!$N$51 -> #VALUE! | K51: =Campaign_Match!$O$51 -> #VALUE! | L51: =Campaign_Match!$I$51 -> 45 | M51: =Campaign_Match!$J$51 -> 100 | N51: =Campaign_Match!$I$51 -> 45 | O51: =Campaign_Match!$J$51 -> 100 | P51: =Campaign_Profile!$C$8 -> Engagement
A52: =Campaign_Match!$A$52 -> CAMP-B | B52: =Campaign_Match!$B$52 -> BRAND-B | C52: =Campaign_Profile!$C$7 -> Glow Up Routine | D52: =Campaign_Match!$C$52 -> KOL-18 | E52: =Campaign_Match!$D$52 -> Reza Fadillah | F52: =Campaign_Match!$E$52 -> TikTok | G52: =Campaign_Match!$F$52 -> Travel | H52: =Campaign_Match!$G$52 -> 56 | I52: =Campaign_Match!$M$52 -> 52.3 | J52: =Campaign_Match!$N$52 -> 54.9 | K52: =Campaign_Match!$O$52 -> Weak Match | L52: =Campaign_Match!$I$52 -> 45 | M52: =Campaign_Match!$J$52 -> 25 | N52: =Campaign_Match!$I$52 -> 45 | O52: =Campaign_Match!$J$52 -> 25 | P52: =Campaign_Profile!$C$8 -> Engagement
A53: =Campaign_Match!$A$53 -> CAMP-B | B53: =Campaign_Match!$B$53 -> BRAND-B | C53: =Campaign_Profile!$C$7 -> Glow Up Routine | D53: =Campaign_Match!$C$53 -> KOL-19 | E53: =Campaign_Match!$D$53 -> Putri Amanda | F53: =Campaign_Match!$E$53 -> Instagram | G53: =Campaign_Match!$F$53 -> Parenting | H53: =Campaign_Match!$G$53 | I53: =Campaign_Match!$M$53 -> 55 | J53: =Campaign_Match!$N$53 -> #VALUE! | K53: =Campaign_Match!$O$53 -> #VALUE! | L53: =Campaign_Match!$I$53 -> 45 | M53: =Campaign_Match!$J$53 -> 35 | N53: =Campaign_Match!$I$53 -> 45 | O53: =Campaign_Match!$J$53 -> 35 | P53: =Campaign_Profile!$C$8 -> Engagement
A54: =Campaign_Match!$A$54 -> CAMP-B | B54: =Campaign_Match!$B$54 -> BRAND-B | C54: =Campaign_Profile!$C$7 -> Glow Up Routine | D54: =Campaign_Match!$C$54 -> KOL-20 | E54: =Campaign_Match!$D$54 -> Hendra Wijoyo | F54: =Campaign_Match!$E$54 -> TikTok | G54: =Campaign_Match!$F$54 -> Parenting | H54: =Campaign_Match!$G$54 -> 52 | I54: =Campaign_Match!$M$54 -> 46.4 | J54: =Campaign_Match!$N$54 -> 50.3 | K54: =Campaign_Match!$O$54 -> Weak Match | L54: =Campaign_Match!$I$54 -> 45 | M54: =Campaign_Match!$J$54 -> 20 | N54: =Campaign_Match!$I$54 -> 45 | O54: =Campaign_Match!$J$54 -> 20 | P54: =Campaign_Profile!$C$8 -> Engagement
A55: =Campaign_Match!$A$55 -> CAMP-B | B55: =Campaign_Match!$B$55 -> BRAND-B | C55: =Campaign_Profile!$C$7 -> Glow Up Routine | D55: =Campaign_Match!$C$55 -> KOL-21 | E55: =Campaign_Match!$D$55 -> Bagas Setiawan | F55: =Campaign_Match!$E$55 -> TikTok | G55: =Campaign_Match!$F$55 -> Entertainment | H55: =Campaign_Match!$G$55 | I55: =Campaign_Match!$M$55 -> 47.5 | J55: =Campaign_Match!$N$55 -> #VALUE! | K55: =Campaign_Match!$O$55 -> #VALUE! | L55: =Campaign_Match!$I$55 -> 45 | M55: =Campaign_Match!$J$55 -> 20 | N55: =Campaign_Match!$I$55 -> 45 | O55: =Campaign_Match!$J$55 -> 20 | P55: =Campaign_Profile!$C$8 -> Engagement
A56: =Campaign_Match!$A$56 -> CAMP-B | B56: =Campaign_Match!$B$56 -> BRAND-B | C56: =Campaign_Profile!$C$7 -> Glow Up Routine | D56: =Campaign_Match!$C$56 -> KOL-22 | E56: =Campaign_Match!$D$56 -> Nabila Kirana | F56: =Campaign_Match!$E$56 -> Instagram | G56: =Campaign_Match!$F$56 -> Entertainment | H56: =Campaign_Match!$G$56 | I56: =Campaign_Match!$M$56 -> 71.8 | J56: =Campaign_Match!$N$56 -> #VALUE! | K56: =Campaign_Match!$O$56 -> #VALUE! | L56: =Campaign_Match!$I$56 -> 45 | M56: =Campaign_Match!$J$56 -> 65 | N56: =Campaign_Match!$I$56 -> 45 | O56: =Campaign_Match!$J$56 -> 65 | P56: =Campaign_Profile!$C$8 -> Engagement
A57: =Campaign_Match!$A$57 -> CAMP-B | B57: =Campaign_Match!$B$57 -> BRAND-B | C57: =Campaign_Profile!$C$7 -> Glow Up Routine | D57: =Campaign_Match!$C$57 -> KOL-23 | E57: =Campaign_Match!$D$57 -> Arya Mahendra | F57: =Campaign_Match!$E$57 -> TikTok | G57: =Campaign_Match!$F$57 -> Gaming | H57: =Campaign_Match!$G$57 | I57: =Campaign_Match!$M$57 -> 49.8 | J57: =Campaign_Match!$N$57 -> #VALUE! | K57: =Campaign_Match!$O$57 -> #VALUE! | L57: =Campaign_Match!$I$57 -> 45 | M57: =Campaign_Match!$J$57 -> 30 | N57: =Campaign_Match!$I$57 -> 45 | O57: =Campaign_Match!$J$57 -> 30 | P57: =Campaign_Profile!$C$8 -> Engagement
A58: =Campaign_Match!$A$58 -> CAMP-B | B58: =Campaign_Match!$B$58 -> BRAND-B | C58: =Campaign_Profile!$C$7 -> Glow Up Routine | D58: =Campaign_Match!$C$58 -> KOL-24 | E58: =Campaign_Match!$D$58 -> Rio Saputra | F58: =Campaign_Match!$E$58 -> Instagram | G58: =Campaign_Match!$F$58 -> Gaming | H58: =Campaign_Match!$G$58 -> 49 | I58: =Campaign_Match!$M$58 -> 66.1 | J58: =Campaign_Match!$N$58 -> 54.1 | K58: =Campaign_Match!$O$58 -> Weak Match | L58: =Campaign_Match!$I$58 -> 80 | M58: =Campaign_Match!$J$58 -> 50 | N58: =Campaign_Match!$I$58 -> 80 | O58: =Campaign_Match!$J$58 -> 50 | P58: =Campaign_Profile!$C$8 -> Engagement
A59: =Campaign_Match!$A$59 -> CAMP-B | B59: =Campaign_Match!$B$59 -> BRAND-B | C59: =Campaign_Profile!$C$7 -> Glow Up Routine | D59: =Campaign_Match!$C$59 -> KOL-25 | E59: =Campaign_Match!$D$59 -> Denny Kurniawan | F59: =Campaign_Match!$E$59 -> TikTok | G59: =Campaign_Match!$F$59 -> Automotive | H59: =Campaign_Match!$G$59 | I59: =Campaign_Match!$M$59 -> 49.3 | J59: =Campaign_Match!$N$59 -> #VALUE! | K59: =Campaign_Match!$O$59 -> #VALUE! | L59: =Campaign_Match!$I$59 -> 45 | M59: =Campaign_Match!$J$59 -> 25 | N59: =Campaign_Match!$I$59 -> 45 | O59: =Campaign_Match!$J$59 -> 25 | P59: =Campaign_Profile!$C$8 -> Engagement
A60: =Campaign_Match!$A$60 -> CAMP-B | B60: =Campaign_Match!$B$60 -> BRAND-B | C60: =Campaign_Profile!$C$7 -> Glow Up Routine | D60: =Campaign_Match!$C$60 -> KOL-26 | E60: =Campaign_Match!$D$60 -> Wisnu Adi | F60: =Campaign_Match!$E$60 -> Instagram | G60: =Campaign_Match!$F$60 -> Automotive | H60: =Campaign_Match!$G$60 | I60: =Campaign_Match!$M$60 -> 77.2 | J60: =Campaign_Match!$N$60 -> #VALUE! | K60: =Campaign_Match!$O$60 -> #VALUE! | L60: =Campaign_Match!$I$60 -> 100 | M60: =Campaign_Match!$J$60 -> 85 | N60: =Campaign_Match!$I$60 -> 100 | O60: =Campaign_Match!$J$60 -> 85 | P60: =Campaign_Profile!$C$8 -> Engagement
A61: =Campaign_Match!$A$61 -> CAMP-B | B61: =Campaign_Match!$B$61 -> BRAND-B | C61: =Campaign_Profile!$C$7 -> Glow Up Routine | D61: =Campaign_Match!$C$61 -> KOL-27 | E61: =Campaign_Match!$D$61 -> Laras Ayu | F61: =Campaign_Match!$E$61 -> Instagram | G61: =Campaign_Match!$F$61 -> Home & Living | H61: =Campaign_Match!$G$61 -> 62 | I61: =Campaign_Match!$M$61 -> 77.2 | J61: =Campaign_Match!$N$61 -> 66.6 | K61: =Campaign_Match!$O$61 -> Good Match | L61: =Campaign_Match!$I$61 -> 45 | M61: =Campaign_Match!$J$61 -> 100 | N61: =Campaign_Match!$I$61 -> 45 | O61: =Campaign_Match!$J$61 -> 100 | P61: =Campaign_Profile!$C$8 -> Engagement
A62: =Campaign_Match!$A$62 -> CAMP-B | B62: =Campaign_Match!$B$62 -> BRAND-B | C62: =Campaign_Profile!$C$7 -> Glow Up Routine | D62: =Campaign_Match!$C$62 -> KOL-28 | E62: =Campaign_Match!$D$62 -> Tiara Nisrina | F62: =Campaign_Match!$E$62 -> TikTok | G62: =Campaign_Match!$F$62 -> Home & Living | H62: =Campaign_Match!$G$62 | I62: =Campaign_Match!$M$62 -> 67 | J62: =Campaign_Match!$N$62 -> #VALUE! | K62: =Campaign_Match!$O$62 -> #VALUE! | L62: =Campaign_Match!$I$62 -> 80 | M62: =Campaign_Match!$J$62 -> 35 | N62: =Campaign_Match!$I$62 -> 80 | O62: =Campaign_Match!$J$62 -> 35 | P62: =Campaign_Profile!$C$8 -> Engagement
